Workbook

Sheet Raw Data
A1: ticker | B1: name | C1: currency | D1: exchange | E1: industry | F1: logo | G1: weburl | H1: environment_grade | I1: environment_level | J1: social_grade | K1: social_level | L1: governance_grade | M1: governance_level | N1: environment_score | O1: social_score | P1: governance_score | Q1: total_score | R1: last_processing_date | S1: total_grade | T1: total_level | U1: cik
A2: dis | B2: Walt Disney Co | C2: USD | D2: NEW YORK STOCK EXCHANGE, INC. | E2: Media | F2: https://static.finnhub.io/logo/ef50b4a2b263c847211b567a01edb702cae8b9ef46ca1f6856ca4432a70e9f52.png | G2: https://thewaltdisneycompany.com/ | H2: A | I2: High | J2: BB | K2: Medium | L2: BB | M2: Medium | N2: 510 | O2: 316 | P2: 321 | Q2: 1147 | R2: 44670 | S2: BBB | T2: High | U2: 1744489
A3: gm | B3: General Motors Co | C3: USD | D3: NEW YORK STOCK EXCHANGE, INC. | E3: Automobiles | F3: https://static.finnhub.io/logo/9253db78-80c9-11ea-920d-00000000092a.png | G3: https://www.gm.com/ | H3: A | I3: High | J3: BB | K3: Medium | L3: B | M3: Medium | N3: 510 | O3: 303 | P3: 255 | Q3: 1068 | R3: 44668 | S3: BBB | T3: High | U3: 1467858
A4: gww | B4: WW Grainger Inc | C4: USD | D4: NEW YORK STOCK EXCHANGE, INC. | E4: Trading Companies and Distributors | F4: https://static.finnhub.io/logo/f153dcda-80eb-11ea-bc2e-00000000092a.png | G4: https://www.grainger.com/ | H4: B | I4: Medium | J4: BB | K4: Medium | L4: B | M4: Medium | N4: 255 | O4: 385 | P4: 240 | Q4: 880 | R4: 44670 | S4: BB | T4: Medium | U4: 277135
A5: mhk | B5: Mohawk Industries Inc | C5: USD | D5: NEW YORK STOCK EXCHANGE, INC. | E5: Consumer products | F5: https://static.finnhub.io/logo/26868a62-80ec-11ea-9712-00000000092a.png | G5: https://mohawkind.com/ | H5: A | I5: High | J5: B | K5: Medium | L5: BB | M5: Medium | N5: 570 | O5: 298 | P5: 303 | Q5: 1171 | R5: 44669 | S5: BBB | T5: High | U5: 851968
A6: lyv | B6: Live Nation Entertainment Inc | C6: USD | D6: NEW YORK STOCK EXCHANGE, INC. | E6: Media | F6: https://static.finnhub.io/logo/1cd144d2-80ec-11ea-b50a-00000000092a.png | G6: https://www.livenationentertainment.com/ | H6: BBB | I6: High | J6: BB | K6: Medium | L6: B | M6: Medium | N6: 492 | O6: 310 | P6: 250 | Q6: 1052 | R6: 44669 | S6: BBB | T6: High | U6: 1335258
A7: lvs | B7: Las Vegas Sands Corp | C7: USD | D7: NEW YORK STOCK EXCHANGE, INC. | E7: Hotels Restaurants and Leisure | F7: https://static.finnhub.io/logo/7256a9be-8279-11ea-874d-00000000092a.png | G7: https://www.sands.com/ | H7: A | I7: High | J7: BB | K7: Medium | L7: BB | M7: Medium | N7: 547 | O7: 318 | P7: 313 | Q7: 1178 | R7: 44669 | S7: BBB | T7: High | U7: 1300514
A8: clx | B8: Clorox Co | C8: USD | D8: NEW YORK STOCK EXCHANGE, INC. | E8: Consumer products | F8: https://static.finnhub.io/logo/a67c34fe-80eb-11ea-a87f-00000000092a.png | G8: https://www.thecloroxcompany.com/ | H8: A | I8: High | J8: BB | K8: Medium | L8: BB | M8: Medium | N8: 560 | O8: 350 | P8: 345 | Q8: 1255 | R8: 44667 | S8: A | T8: High | U8: 21076
A9: aacg | B9: ATA Creativity Global | C9: CNY | D9: NASDAQ NMS - GLOBAL MARKET | E9: Diversified Consumer Services | F9: https://static2.finnhub.io/file/publicdatany/finnhubimage/stock_logo/AACG.svg | G9: http://www.ata.net.cn | H9: B | I9: Medium | J9: B | K9: Medium | L9: B | M9: Medium | N9: 203 | O9: 200 | P9: 205 | Q9: 608 | R9: 44743 | S9: B | T9: Medium | U9: 1420529
A10: aal | B10: American Airlines Group Inc | C10: USD | D10: NASDAQ NMS - GLOBAL MARKET | E10: Airlines | F10: https://static2.finnhub.io/file/publicdatany/finnhubimage/stock_logo/AAL.png | G10: https://americanairlines.gcs-web.com/ | H10: B | I10: Medium | J10: B | K10: Medium | L10: B | M10: Medium | N10: 270 | O10: 211 | P10: 265 | Q10: 746 | R10: 44667 | S10: B | T10: Medium | U10: 6201
A11: aame | B11: Atlantic American Corp | C11: USD | D11: NASDAQ NMS - GLOBAL MARKET | E11: Insurance | F11: https://static.finnhub.io/logo/6b536b3e-826a-11ea-bc66-00000000092a.png | G11: http://www.atlam.com/ | H11: B | I11: Medium | J11: B | K11: Medium | L11: BB | M11: Medium | N11: 220 | O11: 221 | P11: 300 | Q11: 741 | R11: 44667 | S11: B | T11: Medium | U11: 8177
A12: aaoi | B12: Applied Optoelectronics Inc | C12: USD | D12: NASDAQ NMS - GLOBAL MARKET | E12: Communications | F12: https://static.finnhub.io/logo/7afdb95a-80ce-11ea-849c-00000000092a.png | G12: http://ao-inc.com/ | H12: BB | I12: Medium | J12: B | K12: Medium | L12: B | M12: Medium | N12: 311 | O12: 256 | P12: 218 | Q12: 785 | R12: 44667 | S12: BB | T12: Medium | U12: 1158114
A13: aaon | B13: Aaon Inc | C13: USD | D13: NASDAQ NMS - GLOBAL MARKET | E13: Building | F13: https://static.finnhub.io/logo/8819421c-80df-11ea-80b9-00000000092a.png | G13: https://www.aaon.com/ | H13: A | I13: High | J13: BB | K13: Medium | L13: B | M13: Medium | N13: 500 | O13: 300 | P13: 223 | Q13: 1023 | R13: 44667 | S13: BBB | T13: High | U13: 824142
A14: aapl | B14: Apple Inc | C14: USD | D14: NASDAQ NMS - GLOBAL MARKET | E14: Technology | F14: https://static.finnhub.io/logo/87cb30d8-80df-11ea-8951-00000000092a.png | G14: https://www.apple.com/ | H14: BB | I14: Medium | J14: B | K14: Medium | L14: B | M14: Medium | N14: 355 | O14: 281 | P14: 255 | Q14: 891 | R14: 44667 | S14: BB | T14: Medium | U14: 320193
A15: aatc | B15: Autoscope Technologies Corp | C15: USD | D15: NASDAQ NMS - GLOBAL MARKET | E15: Electrical Equipment | H15: BBB | I15: High | J15: B | K15: Medium | L15: B | M15: Medium | N15: 410 | O15: 286 | P15: 240 | Q15: 936 | R15: 44723 | S15: BBB | T15: High | U15: 943034
A16: aaww | B16: Atlas Air Worldwide Holdings Inc | C16: USD | D16: NASDAQ NMS - GLOBAL MARKET | E16: Logistics and Transportation | F16: https://static.finnhub.io/logo/8b74bf8a-80df-11ea-8463-00000000092a.png | G16: https://www.atlasairworldwide.com/ | H16: A | I16: High | J16: B | K16: Medium | L16: B | M16: Medium | N16: 520 | O16: 243 | P16: 237 | Q16: 1000 | R16: 44667 | S16: BBB | T16: High | U16: 1135185
A17: aaci | B17: Armada Acquisition Corp I | C17: USD | D17: NASDAQ NMS - GLOBAL MARKET | E17: N/A | H17: B | I17: Medium | J17: B | K17: Medium | L17: B | M17: Medium | N17: 205 | O17: 200 | P17: 200 | Q17: 605 | R17: 44732 | S17: B | T17: Medium | U17: 1844817
A18: aadi | B18: Aadi Bioscience Inc | C18: USD | D18: NASDAQ NMS - GLOBAL MARKET | E18: Biotechnology | F18: https://static.finnhub.io/logo/358b0921e9d761a529cffa812e99b140f4bb9c2e1e63bfeee3a4ea7165257e7b.png | G18: https://aadibio.com/ | H18: B | I18: Medium | J18: B | K18: Medium | L18: B | M18: Medium | N18: 200 | O18: 201 | P18: 203 | Q18: 604 | R18: 44723 | S18: B | T18: Medium | U18: 1422142
A19: abeo | B19: Abeona Therapeutics Inc | C19: USD | D19: NASDAQ NMS - GLOBAL MARKET | E19: Biotechnology | F19: https://static.finnhub.io/logo/33b2a5a8-80d1-11ea-8de8-00000000092a.png | G19: https://abeonatherapeutics.com/ | H19: B | I19: Medium | J19: BB | K19: Medium | L19: BB | M19: Medium | N19: 205 | O19: 306 | P19: 310 | Q19: 821 | R19: 44667 | S19: BB | T19: Medium | U19: 318306
A20: abnb | B20: Airbnb Inc | C20: USD | D20: NASDAQ NMS - GLOBAL MARKET | E20: Hotels Restaurants and Leisure | F20: https://static2.finnhub.io/file/publicdatany/finnhubimage/stock_logo/ABNB.png | G20: https://www.airbnb.co.in/ | H20: A | I20: High | J20: A | K20: High | L20: BBB | M20: High | N20: 505 | O20: 570 | P20: 400 | Q20: 1475 | R20: 44722 | S20: A | T20: High | U20: 1559720
A21: abio | B21: ARCA Biopharma Inc | C21: USD | D21: NASDAQ NMS - GLOBAL MARKET | E21: Biotechnology | F21: https://static.finnhub.io/logo/52ec4c2e0c249a506cbce41ef284e287901cccb0a08db285aa9a9d4091ba8434.png | G21: http://arcabio.com/ | H21: B | I21: Medium | J21: B | K21: Medium | L21: B | M21: Medium | N21: 200 | O21: 222 | P21: 290 | Q21: 712 | R21: 44667 | S21: B | T21: Medium | U21: 907654
A22: abmd | B22: ABIOMED Inc | C22: USD | D22: NASDAQ NMS - GLOBAL MARKET | E22: Health Care | F22: https://static.finnhub.io/logo/8b2cc7cc-80df-11ea-b8c7-00000000092a.png | G22: https://www.abiomed.com/ | H22: A | I22: High | J22: BB | K22: Medium | L22: BB | M22: Medium | N22: 500 | O22: 324 | P22: 305 | Q22: 1129 | R22: 44667 | S22: BBB | T22: High | U22: 815094
A23: abos | B23: Acumen Pharmaceuticals Inc | C23: USD | D23: NASDAQ NMS - GLOBAL MARKET | E23: Biotechnology | F23: https://static.finnhub.io/logo/f1081a3d8031ad222b050bbbcfef7a073cea50638ad028f1fd31c5ca934f3820.png | G23: https://acumenpharm.com/ | H23: B | I23: Medium | J23: B | K23: Medium | L23: B | M23: Medium | N23: 205 | O23: 201 | P23: 200 | Q23: 606 | R23: 44723 | S23: B | T23: Medium | U23: 1576885
A24: absi | B24: Absci Corp | C24: USD | D24: NASDAQ NMS - GLOBAL MARKET | E24: Life Sciences Tools and Services | F24: https://static.finnhub.io/logo/d030f309b5a348085ba6297eadf507c1d7410dbf605e6147f34eec997f6f073f.png | G24: https://www.absci.com/ | H24: B | I24: Medium | J24: B | K24: Medium | L24: B | M24: Medium | N24: 205 | O24: 224 | P24: 230 | Q24: 659 | R24: 44723 | S24: B | T24: Medium | U24: 1672688
A25: abtx | B25: Allegiance Bancshares Inc | C25: USD | D25: NASDAQ NMS - GLOBAL MARKET | E25: Banking | F25: https://static.finnhub.io/logo/b34c7c52-80d2-11ea-8e19-00000000092a.png | G25: https://ir.allegiancebank.com/ | H25: B | I25: Medium | J25: BB | K25: Medium | L25: BB | M25: Medium | N25: 298 | O25: 300 | P25: 300 | Q25: 898 | R25: 44667 | S25: BB | T25: Medium | U25: 1642081
A26: abus | B26: Arbutus Biopharma Corp | C26: USD | D26: NASDAQ NMS - GLOBAL MARKET | E26: Biotechnology | F26: https://static.finnhub.io/logo/0068df02-80ca-11ea-abb6-00000000092a.png | G26: https://www.arbutusbio.com/ | H26: B | I26: Medium | J26: B | K26: Medium | L26: BB | M26: Medium | N26: 203 | O26: 204 | P26: 338 | Q26: 745 | R26: 44667 | S26: B | T26: Medium | U26: 1447028
A27: abvc | B27: ABVC Biopharma Inc | C27: USD | D27: NASDAQ NMS - GLOBAL MARKET | E27: Biotechnology | F27: https://static.finnhub.io/logo/2b1c9fbcfafa70dcfa10247ad6ebe12858ca5878a4c90e32840a2080a507eb3d.png | G27: https://abvcpharma.com/ | H27: B | I27: Medium | J27: B | K27: Medium | L27: B | M27: Medium | N27: 220 | O27: 212 | P27: 205 | Q27: 637 | R27: 44723 | S27: B | T27: Medium | U27: 1173313
A28: acad | B28: ACADIA Pharmaceuticals Inc | C28: USD | D28: NASDAQ NMS - GLOBAL MARKET | E28: Biotechnology | F28: https://static.finnhub.io/logo/2d87da57d47f7a5c0225c54f67d806d3a906cec1ea63d739dad084772cf5079c.png | G28: https://acadia.com/ | H28: B | I28: Medium | J28: B | K28: Medium | L28: BB | M28: Medium | N28: 230 | O28: 230 | P28: 305 | Q28: 765 | R28: 44667 | S28: BB | T28: Medium | U28: 1070494
A29: acac | B29: Acri Capital Acquisition Corp | C29: USD | D29: NASDAQ NMS - GLOBAL MARKET | E29: N/A | H29: B | I29: Medium | J29: B | K29: Medium | L29: BB | M29: Medium | N29: 200 | O29: 205 | P29: 300 | Q29: 705 | R29: 44722 | S29: B | T29: Medium | U29: 1914023
A30: accd | B30: Accolade Inc | C30: USD | D30: NASDAQ NMS - GLOBAL MARKET | E30: Health Care | F30: https://static.finnhub.io/logo/a967c80c75f9c72bb31fd3ae796a0a4e1e0dec7378ade4f78c06f10d89acf8bf.png | G30: https://www.accolade.com | H30: B | I30: Medium | J30: B | K30: Medium | L30: B | M30: Medium | N30: 255 | O30: 254 | P30: 235 | Q30: 744 | R30: 44722 | S30: B | T30: Medium | U30: 1481646
A31: acet | B31: Adicet Bio Inc | C31: USD | D31: NASDAQ NMS - GLOBAL MARKET | E31: Biotechnology | F31: https://static.finnhub.io/logo/ea701be36180b02128c519975a35fcca2ef8ef5cd412e65e7ff39eb054703270.png | G31: https://www.adicetbio.com/ | H31: B | I31: Medium | J31: B | K31: Medium | L31: BB | M31: Medium | N31: 215 | O31: 211 | P31: 305 | Q31: 731 | R31: 44667 | S31: B | T31: Medium | U31: 1720580
A32: abcl | B32: Abcellera Biologics Inc | C32: USD | D32: NASDAQ NMS - GLOBAL MARKET | E32: Life Sciences Tools and Services | F32: https://static.finnhub.io/logo/cd950365b552eae0cadf348f427e5a4dd05974468d5803b8b63e44da362a5ee9.png | G32: https://www.abcellera.com/ | H32: A | I32: High | J32: BB | K32: Medium | L32: BB | M32: Medium | N32: 540 | O32: 354 | P32: 345 | Q32: 1239 | R32: 44722 | S32: A | T32: High | U32: 1703057
A33: abcb | B33: Ameris Bancorp | C33: USD | D33: NASDAQ NMS - GLOBAL MARKET | E33: Banking | F33: https://static.finnhub.io/logo/8cea9450-80df-11ea-80b8-00000000092a.png | G33: https://www.amerisbank.com/ | H33: B | I33: Medium | J33: BB | K33: Medium | L33: B | M33: Medium | N33: 290 | O33: 300 | P33: 250 | Q33: 840 | R33: 44667 | S33: BB | T33: Medium | U33: 351569
A34: acev | B34: ACE Convergence Acquisition Corp | C34: USD | D34: NASDAQ NMS - GLOBAL MARKET | E34: N/A | F34: https://static.finnhub.io/logo/d86f14d77a3f95acbb00c602a4e2d735df7f2d3cfd22be9263a22876630ae65d.png | G34: http://acev.io/home/ | H34: B | I34: Medium | J34: B | K34: Medium | L34: B | M34: Medium | N34: 225 | O34: 211 | P34: 215 | Q34: 651 | R34: 44722 | S34: B | T34: Medium | U34: 1813658
A35: achl | B35: Achilles Therapeutics PLC | C35: USD | D35: NASDAQ NMS - GLOBAL MARKET | E35: Biotechnology | F35: https://static.finnhub.io/logo/6147e0afabb6d97c0483d7921c255166e49adccf043d5bf956068f9c4c546cae.png | G35: https://www.achillestx.com/ | H35: B | I35: Medium | J35: B | K35: Medium | L35: B | M35: Medium | N35: 230 | O35: 288 | P35: 285 | Q35: 803 | R35: 44722 | S35: BB | T35: Medium | U35: 1830749
A36: achc | B36: Acadia Healthcare Company Inc | C36: USD | D36: NASDAQ NMS - GLOBAL MARKET | E36: Health Care | F36: https://static.finnhub.io/logo/4b6b2e5a4cfce5b1377719219ab5a354a629c9b9fb43067b5993423152fef1fb.png | G36: https://www.acadiahealthcare.com/ | H36: BB | I36: Medium | J36: B | K36: Medium | L36: B | M36: Medium | N36: 330 | O36: 231 | P36: 220 | Q36: 781 | R36: 44667 | S36: BB | T36: Medium | U36: 1520697
A37: aciw | B37: ACI Worldwide Inc | C37: USD | D37: NASDAQ NMS - GLOBAL MARKET | E37: Technology | F37: https://static.finnhub.io/logo/875c5a76-80df-11ea-ab99-00000000092a.png | G37: https://www.aciworldwide.com/ | H37: A | I37: High | J37: BB | K37: Medium | L37: BB | M37: Medium | N37: 500 | O37: 327 | P37: 300 | Q37: 1127 | R37: 44667 | S37: BBB | T37: High | U37: 935036
A38: acls | B38: Axcelis Technologies Inc | C38: USD | D38: NASDAQ NMS - GLOBAL MARKET | E38: Semiconductors | F38: https://static.finnhub.io/logo/88b5f730-80df-11ea-94d0-00000000092a.png | G38: https://www.axcelis.com/ | H38: A | I38: High | J38: BB | K38: Medium | L38: B | M38: Medium | N38: 515 | O38: 306 | P38: 260 | Q38: 1081 | R38: 44667 | S38: BBB | T38: High | U38: 1113232
A39: aciu | B39: AC Immune SA | C39: CHF | D39: NASDAQ NMS - GLOBAL MARKET | E39: Biotechnology | F39: https://static.finnhub.io/logo/f93a1c3e-80db-11ea-a2b4-00000000092a.png | G39: https://www.acimmune.com/ | H39: B | I39: Medium | J39: B | K39: Medium | L39: BB | M39: Medium | N39: 250 | O39: 296 | P39: 305 | Q39: 851 | R39: 44667 | S39: BB | T39: Medium | U39: 1651625
A40: achv | B40: Achieve Life Sciences Inc | C40: USD | D40: NASDAQ NMS - GLOBAL MARKET | E40: Biotechnology | F40: https://static.finnhub.io/logo/bf32de26-80e0-11ea-962e-00000000092a.png | G40: http://achievelifesciences.com/ | H40: B | I40: Medium | J40: B | K40: Medium | L40: BB | M40: Medium | N40: 215 | O40: 222 | P40: 305 | Q40: 742 | R40: 44722 | S40: B | T40: Medium | U40: 949858
A41: acmr | B41: ACM Research Inc | C41: USD | D41: NASDAQ NMS - GLOBAL MARKET | E41: Semiconductors | F41: https://static.finnhub.io/logo/bd3e9ce4b1a48aa839d6a0ff155fc165309d14773a651b8fb39fe880212870b2.png | G41: https://www.acmrcsh.com/ | H41: BBB | I41: High | J41: B | K41: Medium | L41: BB | M41: Medium | N41: 410 | O41: 232 | P41: 325 | Q41: 967 | R41: 44722 | S41: BBB | T41: High | U41: 1680062
... A58: acer | B58: Acer Therapeutics Inc | C58: USD | D58: NASDAQ NMS - GLOBAL MARKET | E58: Pharmaceuticals | F58: https://static.finnhub.io/logo/da0a6c40-80e0-11ea-81ae-00000000092a.png | G58: https://acertx.com/ | H58: B | I58: Medium | J58: B | K58: Medium | L58: BB | M58: Medium | N58: 223 | O58: 291 | P58: 310 | Q58: 824 | R58: 44722 | S58: BB | T58: Medium | U58: 1069308
A59: adoc | B59: Edoc Acquisition Corp | C59: USD | D59: NASDAQ NMS - GLOBAL MARKET | E59: N/A | H59: B | I59: Medium | J59: BB | K59: Medium | L59: BB | M59: Medium | N59: 215 | O59: 301 | P59: 300 | Q59: 816 | R59: 44667 | S59: BB | T59: Medium | U59: 1824884
A60: adus | B60: Addus Homecare Corp | C60: USD | D60: NASDAQ NMS - GLOBAL MARKET | E60: Health Care | F60: https://static.finnhub.io/logo/20ba9a37b3127f14370410e76dcf5f2e7db9e068cc08f2da0e740aa7aaa6bf52.png | G60: https://addus.com/ | H60: B | I60: Medium | J60: B | K60: Medium | L60: B | M60: Medium | N60: 210 | O60: 215 | P60: 218 | Q60: 643 | R60: 44667 | S60: B | T60: Medium | U60: 1468328
A61: acgl | B61: Arch Capital Group Ltd | C61: USD | D61: NASDAQ NMS - GLOBAL MARKET | E61: Insurance | F61: https://static.finnhub.io/logo/8c4d69f6-80df-11ea-8233-00000000092a.png | G61: https://www.archgroup.com/ | H61: A | I61: High | J61: BB | K61: Medium | L61: BB | M61: Medium | N61: 500 | O61: 300 | P61: 300 | Q61: 1100 | R61: 44667 | S61: BBB | T61: High | U61: 947484
A62: adpt | B62: Adaptive Biotechnologies Corp | C62: USD | D62: NASDAQ NMS - GLOBAL MARKET | E62: Life Sciences Tools and Services | F62: https://static.finnhub.io/logo/49f91794-80da-11ea-be7a-00000000092a.png | G62: https://www.adaptivebiotech.com | H62: B | I62: Medium | J62: BB | K62: Medium | L62: B | M62: Medium | N62: 260 | O62: 348 | P62: 260 | Q62: 868 | R62: 44667 | S62: BB | T62: Medium | U62: 1478320
A63: adsk | B63: Autodesk Inc | C63: USD | D63: NASDAQ NMS - GLOBAL MARKET | E63: Technology | F63: https://static.finnhub.io/logo/99d251e4-80df-11ea-ad7f-00000000092a.png | G63: https://www.autodesk.com/ | H63: A | I63: High | J63: BB | K63: Medium | L63: BB | M63: Medium | N63: 555 | O63: 304 | P63: 310 | Q63: 1169 | R63: 44667 | S63: BBB | T63: High | U63: 769397
A64: adp | B64: Automatic Data Processing Inc | C64: USD | D64: NASDAQ NMS - GLOBAL MARKET | E64: Technology | F64: https://static.finnhub.io/logo/987cc1f6-80df-11ea-96e8-00000000092a.png | G64: https://www.adp.com/ | H64: A | I64: High | J64: BB | K64: Medium | L64: B | M64: Medium | N64: 500 | O64: 300 | P64: 200 | Q64: 1000 | R64: 44767 | S64: BBB | T64: High | U64: 8670
A65: adtx | B65: Aditxt Inc | C65: USD | D65: NASDAQ NMS - GLOBAL MARKET | E65: Biotechnology | F65: https://static.finnhub.io/logo/278ebd47277db15b770d06958e2e2b981b0f75047d9485ef7fd67eabe0c557f0.png | G65: https://aditxt.com/ | H65: B | I65: Medium | J65: B | K65: Medium | L65: BB | M65: Medium | N65: 210 | O65: 224 | P65: 305 | Q65: 739 | R65: 44722 | S65: B | T65: Medium | U65: 1726711
A66: adv | B66: Advantage Solutions Inc | C66: USD | D66: NASDAQ NMS - GLOBAL MARKET | E66: Media | F66: https://static.finnhub.io/logo/4191147864cd494d9602ea7d462b368568307c389e3447f9d958e091675fc1b7.png | G66: https://advantagesolutions.net/ | H66: A | I66: High | J66: B | K66: Medium | L66: BB | M66: Medium | N66: 515 | O66: 269 | P66: 328 | Q66: 1112 | R66: 44671 | S66: BBB | T66: High | U66: 1776661
A67: advm | B67: Adverum Biotechnologies Inc | C67: USD | D67: NASDAQ NMS - GLOBAL MARKET | E67: Biotechnology | F67: https://static.finnhub.io/logo/2a8c64fe-80d0-11ea-9f54-00000000092a.png | G67: https://adverum.com/ | H67: B | I67: Medium | J67: BB | K67: Medium | L67: B | M67: Medium | N67: 262 | O67: 321 | P67: 235 | Q67: 818 | R67: 44667 | S67: BB | T67: Medium | U67: 1501756
A68: aehr | B68: Aehr Test Systems | C68: USD | D68: NASDAQ NMS - GLOBAL MARKET | E68: Semiconductors | F68: https://static.finnhub.io/logo/9a8fe21e-80df-11ea-8837-00000000092a.png | G68: https://www.aehr.com/ | H68: B | I68: Medium | J68: B | K68: Medium | L68: BB | M68: Medium | N68: 290 | O68: 262 | P68: 300 | Q68: 852 | R68: 44667 | S68: BB | T68: Medium | U68: 1040470
A69: aehl | B69: Antelope Enterprise Holdings Ltd | C69: CNY | D69: NASDAQ NMS - GLOBAL MARKET | E69: Building | F69: https://static.finnhub.io/logo/9a75e4385b34c0cb39ac72f06791b387f2ee941735bc144041b63d26403c5301.png | G69: https://www.aehltd.com/ | H69: B | I69: Medium | J69: B | K69: Medium | L69: BB | M69: Medium | N69: 238 | O69: 237 | P69: 325 | Q69: 800 | R69: 44722 | S69: BB | T69: Medium | U69: 1470683
A70: aei | B70: Alset Ehome International Inc | C70: USD | D70: NASDAQ NMS - GLOBAL MARKET | E70: Real Estate | F70: https://static.finnhub.io/logo/98c8d7c249f43e2d9209af2a93fb646dc774a1a85a30840fc88e94859962870c.png | G70: http://www.hfenterp.com | H70: A | I70: High | J70: B | K70: Medium | L70: B | M70: Medium | N70: 520 | O70: 207 | P70: 210 | Q70: 937 | R70: 44671 | S70: BBB | T70: High | U70: 1750106
A71: aeis | B71: Advanced Energy Industries Inc | C71: USD | D71: NASDAQ NMS - GLOBAL MARKET | E71: Electrical Equipment | F71: https://static.finnhub.io/logo/9ae27426-80df-11ea-a9fa-00000000092a.png | G71: https://www.advancedenergy.com/ | H71: A | I71: High | J71: BB | K71: Medium | L71: BB | M71: Medium | N71: 500 | O71: 300 | P71: 300 | Q71: 1100 | R71: 44667 | S71: BBB | T71: High | U71: 927003
... A77: aey | B77: ADDvantage Technologies Group Inc | C77: USD | D77: NASDAQ NMS - GLOBAL MARKET | E77: Electrical Equipment | F77: https://static.finnhub.io/logo/d2abb4b87e579c2bb32357938df36ceafc9b5d1e999aee923ea9938b2acee94c.png | G77: http://www.addvantagetechnologies.com/ | H77: B | I77: Medium | J77: B | K77: Medium | L77: BB | M77: Medium | N77: 235 | O77: 234 | P77: 300 | Q77: 769 | R77: 44667 | S77: BB | T77: Medium | U77: 874292
A78: afaq | B78: AF Acquisition Corp | C78: USD | D78: NASDAQ NMS - GLOBAL MARKET | E78: N/A | H78: B | I78: Medium | J78: B | K78: Medium | L78: B | M78: Medium | N78: 200 | O78: 200 | P78: 200 | Q78: 600 | R78: 44733 | S78: B | T78: Medium | U78: 1841661
A79: afmd | B79: Affimed NV | C79: EUR | D79: NASDAQ NMS - GLOBAL MARKET | E79: Biotechnology | F79: https://static.finnhub.io/logo/29cc761a-80d0-11ea-ab42-00000000092a.png | G79: https://www.affimed.com/ | H79: BB | I79: Medium | J79: BB | K79: Medium | L79: BB | M79: Medium | N79: 368 | O79: 304 | P79: 310 | Q79: 982 | R79: 44667 | S79: BBB | T79: High | U79: 1608390
A80: afcg | B80: AFC Gamma Inc | C80: USD | D80: NASDAQ NMS - GLOBAL MARKET | E80: Real Estate | F80: https://static.finnhub.io/logo/f0ef42fade24d578bbdf91be70ad822290a91ced952da4c22093df2e1c015b1b.png | G80: https://afcgamma.com/ | H80: B | I80: Medium | J80: B | K80: Medium | L80: B | M80: Medium | N80: 255 | O80: 204 | P80: 226 | Q80: 685 | R80: 44722 | S80: B | T80: Medium | U80: 1822523
A81: afbi | B81: Affinity Bancshares Inc | C81: USD | D81: NASDAQ NMS - GLOBAL MARKET | E81: Banking | G81: https://communityfirstbancshares.q4ir.com/ | H81: B | I81: Medium | J81: B | K81: Medium | L81: B | M81: Medium | N81: 200 | O81: 207 | P81: 200 | Q81: 607 | R81: 44722 | S81: B | T81: Medium | U81: 1823406
A82: afrm | B82: Affirm Holdings Inc | C82: USD | D82: NASDAQ NMS - GLOBAL MARKET | E82: Technology | F82: https://static2.finnhub.io/file/publicdatany/finnhubimage/stock_logo/AFRM.png | G82: https://www.affirm.com/ | H82: B | I82: Medium | J82: BB | K82: Medium | L82: BB | M82: Medium | N82: 225 | O82: 335 | P82: 335 | Q82: 895 | R82: 44722 | S82: BB | T82: Medium | U82: 1820953
A83: afib | B83: Acutus Medical Inc | C83: USD | D83: NASDAQ NMS - GLOBAL MARKET | E83: Health Care | F83: https://static.finnhub.io/logo/352bd59a63f14910c54166ecc5aa8f67ac11b7d8828185bc023d5915d7cf0457.png | G83: http://www.acutusmedical.com/ | H83: B | I83: Medium | J83: B | K83: Medium | L83: B | M83: Medium | N83: 205 | O83: 211 | P83: 235 | Q83: 651 | R83: 44722 | S83: B | T83: Medium | U83: 1522860
A84: agen | B84: Agenus Inc | C84: USD | D84: NASDAQ NMS - GLOBAL MARKET | E84: Biotechnology | F84: https://static.finnhub.io/logo/9ccb30fe-80df-11ea-993b-00000000092a.png | G84: https://agenusbio.com/ | H84: B | I84: Medium | J84: B | K84: Medium | L84: BB | M84: Medium | N84: 290 | O84: 245 | P84: 300 | Q84: 835 | R84: 44667 | S84: BB | T84: Medium | U84: 1098972
A85: afya | B85: Afya Ltd | C85: BRL | D85: NASDAQ NMS - GLOBAL MARKET | E85: Diversified Consumer Services | F85: https://static.finnhub.io/logo/c57ab10fd72c2aa8b1db15524838647943d52bf5f5ad9be3c1f19d9c5c03a762.png | G85: https://www.afya.com.br/ | H85: B | I85: Medium | J85: B | K85: Medium | L85: B | M85: Medium | N85: 290 | O85: 203 | P85: 205 | Q85: 698 | R85: 44722 | S85: B | T85: Medium | U85: 1771007
A86: agfs | B86: AgroFresh Solutions Inc | C86: USD | D86: NASDAQ NMS - GLOBAL MARKET | E86: Chemicals | F86: https://static.finnhub.io/logo/b57e8700-80cf-11ea-b35b-00000000092a.png | G86: https://www.agrofresh.com/ | H86: A | I86: High | J86: BB | K86: Medium | L86: B | M86: Medium | N86: 500 | O86: 301 | P86: 275 | Q86: 1076 | R86: 44667 | S86: BBB | T86: High | U86: 1592016
A87: agfy | B87: Agrify Corp | C87: USD | D87: NASDAQ NMS - GLOBAL MARKET | E87: Machinery | F87: https://static.finnhub.io/logo/aa5216aab348419b7fcfc5d9d79e4b271d486e16e75a4938dee5bd2343263eb9.png | G87: https://www.agrify.com/ | H87: A | I87: High | J87: BB | K87: Medium | L87: BB | M87: Medium | N87: 540 | O87: 361 | P87: 305 | Q87: 1206 | R87: 44722 | S87: A | T87: High | U87: 1800637
A88: agil | B88: AgileThought Inc | C88: USD | D88: NASDAQ NMS - GLOBAL MARKET | E88: Technology | F88: https://static.finnhub.io/logo/becb547f102d410d67137477f782925246bd6ca61915f634a3fa91063ff51d0c.png | G88: https://agilethought.com/ | H88: BB | I88: Medium | J88: B | K88: Medium | L88: BB | M88: Medium | N88: 340 | O88: 299 | P88: 305 | Q88: 944 | R88: 44723 | S88: BBB | T88: High | U88: 1790625
A89: agmh | B89: AGM Group Holdings Inc | C89: USD | D89: NASDAQ NMS - GLOBAL MARKET | E89: Financial Services | F89: https://static.finnhub.io/logo/7f908b9c-80db-11ea-96c9-00000000092a.png | G89: http://www.agmprime.com/ | H89: B | I89: Medium | J89: B | K89: Medium | L89: B | M89: Medium | N89: 205 | O89: 204 | P89: 210 | Q89: 619 | R89: 44722 | S89: B | T89: Medium | U89: 1705402
A90: agio | B90: Agios Pharmaceuticals Inc | C90: USD | D90: NASDAQ NMS - GLOBAL MARKET | E90: Biotechnology | F90: https://static.finnhub.io/logo/4298fc14-80ce-11ea-ace7-00000000092a.png | G90: https://www.agios.com/ | H90: A | I90: High | J90: BB | K90: Medium | L90: BB | M90: Medium | N90: 520 | O90: 303 | P90: 325 | Q90: 1148 | R90: 44667 | S90: BBB | T90: High | U90: 1439222
A91: agle | B91: Aeglea Bio Therapeutics Inc | C91: USD | D91: NASDAQ NMS - GLOBAL MARKET | E91: Biotechnology | F91: https://static.finnhub.io/logo/523351d2-80d2-11ea-b332-00000000092a.png | G91: https://www.aeglea.com/ | H91: B | I91: Medium | J91: B | K91: Medium | L91: B | M91: Medium | N91: 205 | O91: 223 | P91: 200 | Q91: 628 | R91: 44820 | S91: B | T91: Medium | U91: 1636282
A92: agnc | B92: AGNC Investment Corp | C92: USD | D92: NASDAQ NMS - GLOBAL MARKET | E92: Real Estate | F92: https://static.finnhub.io/logo/2f35e91b0085245b224c9799c269249eec328a9687dcd6c3345b79a268802cb0.png | G92: https://agnc.com/ | H92: BB | I92: Medium | J92: B | K92: Medium | L92: BB | M92: Medium | N92: 382 | O92: 242 | P92: 305 | Q92: 929 | R92: 44667 | S92: BBB | T92: High | U92: 1423689
A93: agri | B93: AgriFORCE Growing Systems Ltd | C93: USD | D93: NASDAQ NMS - GLOBAL MARKET | E93: Food Products | F93: https://static.finnhub.io/logo/13b2627f534d45aba679196877fcbf2fe8af01324ddfa2aecc3dbba8c1132239.png | G93: https://agriforcegs.com/ | H93: A | I93: High | J93: B | K93: Medium | L93: BB | M93: Medium | N93: 510 | O93: 248 | P93: 305 | Q93: 1063 | R93: 44723 | S93: BBB | T93: High | U93: 1826397
... A98: ahpi | B98: Allied Healthcare Products Inc | C98: USD | D98: NASDAQ NMS - GLOBAL MARKET | E98: Health Care | F98: https://static.finnhub.io/logo/a505c155a53bb84a0c27e5a919e287f856f4a255e509bc48f499f9f73b588069.png | G98: http://www.alliedhpi.com/ | H98: B | I98: Medium | J98: B | K98: Medium | L98: BB | M98: Medium | N98: 210 | O98: 228 | P98: 325 | Q98: 763 | R98: 44667 | S98: BB | T98: Medium | U98: 874710
A99: aib | B99: AIB Acquisition Corp | C99: USD | D99: NASDAQ NMS - GLOBAL MARKET | E99: N/A | H99: B | I99: Medium | J99: B | K99: Medium | L99: BB | M99: Medium | N99: 215 | O99: 227 | P99: 300 | Q99: 742 | R99: 44705 | S99: B | T99: Medium | U99: 1882963
A100: adtn | B100: ADTRAN Inc | C100: USD | D100: NASDAQ NMS - GLOBAL MARKET | E100: Communications | F100: https://static.finnhub.io/logo/544d99910973b1d04b345cd611449e802ade0468588c1066ad0a5be905a80a84.png | G100: https://www.adtran.com/ | H100: A | I100: High | J100: BB | K100: Medium | L100: BB | M100: Medium | N100: 510 | O100: 308 | P100: 300 | Q100: 1118 | R100: 44667 | S100: BBB | T100: High | U100: 926282
A101: adn | B101: Advent Technologies Holdings Inc | C101: USD | D101: NASDAQ NMS - GLOBAL MARKET | E101: Electrical Equipment | F101: https://static.finnhub.io/logo/adca3c2e-80da-11ea-9ab0-00000000092a.png | G101: http://amciacquisition.com/ | H101: B | I101: Medium | J101: B | K101: Medium | L101: B | M101: Medium | N101: 250 | O101: 203 | P101: 220 | Q101: 673 | R101: 44671 | S101: B | T101: Medium | U101: 1744494
A102: aiki | B102: Aikido Pharma Inc | C102: USD | D102: NASDAQ NMS - GLOBAL MARKET | E102: Biotechnology | F102: https://static.finnhub.io/logo/b16fc664-80e0-11ea-9b8a-00000000092a.png | G102: https://aikidopharma.com/ | H102: B | I102: Medium | J102: B | K102: Medium | L102: B | M102: Medium | N102: 200 | O102: 235 | P102: 205 | Q102: 640 | R102: 44722 | S102: B | T102: Medium | U102: 12239
A103: akic | B103: Sports Ventures Acquisition Corp | C103: USD | D103: NASDAQ NMS - GLOBAL MARKET | E103: N/A | H103: B | I103: Medium | J103: B | K103: Medium | L103: B | M103: Medium | N103: 200 | O103: 205 | P103: 230 | Q103: 635 | R103: 44723 | S103: B | T103: Medium | U103: 1826574
A104: aip | B104: Arteris Inc | C104: USD | D104: NASDAQ NMS - GLOBAL MARKET | E104: Technology | F104: https://static.finnhub.io/logo/6429ccca605b3faa9498cbbc2727b1c4fb8e3c24e577855ff8bf45eeff7d21b2.png | G104: https://www.arteris.com/ | H104: A | I104: High | J104: B | K104: Medium | L104: BB | M104: Medium | N104: 500 | O104: 286 | P104: 300 | Q104: 1086 | R104: 44719 | S104: BBB | T104: High | U104: 1667011
A105: akro | B105: Akero Therapeutics Inc | C105: USD | D105: NASDAQ NMS - GLOBAL MARKET | E105: Biotechnology | F105: https://static.finnhub.io/logo/5ac79f50-80da-11ea-8fee-00000000092a.png | G105: https://www.akerotx.com/ | H105: B | I105: Medium | J105: B | K105: Medium | L105: BB | M105: Medium | N105: 250 | O105: 246 | P105: 305 | Q105: 801 | R105: 44722 | S105: BB | T105: Medium | U105: 1744659
A106: airt | B106: Air T Inc | C106: USD | D106: NASDAQ NMS - GLOBAL MARKET | E106: Logistics and Transportation | F106: https://static.finnhub.io/logo/9e54807a-80df-11ea-9dbf-00000000092a.png | G106: http://www.airt.net/ | H106: B | I106: Medium | J106: B | K106: Medium | L106: BB | M106: Medium | N106: 234 | O106: 210 | P106: 325 | Q106: 769 | R106: 44667 | S106: BB | T106: Medium | U106: 353184
A107: aimc | B107: Altra Industrial Motion Corp | C107: USD | D107: NASDAQ NMS - GLOBAL MARKET | E107: Machinery | F107: https://static.finnhub.io/logo/9da7f902-80df-11ea-b5a0-00000000092a.png | G107: https://www.altramotion.com/ | H107: A | I107: High | J107: BB | K107: Medium | L107: BB | M107: Medium | N107: 525 | O107: 315 | P107: 305 | Q107: 1145 | R107: 44667 | S107: BBB | T107: High | U107: 1374535
A108: akba | B108: Akebia Therapeutics Inc | C108: USD | D108: NASDAQ NMS - GLOBAL MARKET | E108: Biotechnology | F108: https://static.finnhub.io/logo/7d6670f8-80cf-11ea-aab1-00000000092a.png | G108: https://akebia.com/ | H108: B | I108: Medium | J108: B | K108: Medium | L108: B | M108: Medium | N108: 200 | O108: 218 | P108: 215 | Q108: 633 | R108: 44667 | S108: B | T108: Medium | U108: 1517022
A109: airg | B109: Airgain Inc | C109: USD | D109: NASDAQ NMS - GLOBAL MARKET | E109: Electrical Equipment | F109: https://static.finnhub.io/logo/ff72eaca-80db-11ea-a64a-00000000092a.png | G109: http://www.airgain.com/ | H109: A | I109: High | J109: BB | K109: Medium | L109: BB | M109: Medium | N109: 500 | O109: 300 | P109: 330 | Q109: 1130 | R109: 44667 | S109: BBB | T109: High | U109: 1272842
A110: airs | B110: Airsculpt Technologies Inc | C110: USD | D110: NASDAQ NMS - GLOBAL MARKET | E110: Health Care | F110: https://static.finnhub.io/logo/e5484b255e157a1ac5f11571a56a7a14e23cb71d6cf02440a54c447cae42e82a.png | G110: https://elitebodysculpture.com/ | H110: B | I110: Medium | J110: B | K110: Medium | L110: B | M110: Medium | N110: 210 | O110: 201 | P110: 205 | Q110: 616 | R110: 44723 | S110: B | T110: Medium | U110: 1870940
A111: akam | B111: Akamai Technologies Inc | C111: USD | D111: NASDAQ NMS - GLOBAL MARKET | E111: Technology | F111: https://static.finnhub.io/logo/0982f80bff901e6c53bbeda92444bf52ccfe7fb4b559716e0e2bc14037d6ca3f.png | G111: https://www.akamai.com/ | H111: A | I111: High | J111: BB | K111: Medium | L111: BB | M111: Medium | N111: 515 | O111: 341 | P111: 305 | Q111: 1161 | R111: 44667 | S111: BBB | T111: High | U111: 1086222
A112: aku | B112: Akumin Inc | C112: USD | D112: NASDAQ NMS - GLOBAL MARKET | E112: Health Care | F112: https://static.finnhub.io/logo/60c47c38-80db-11ea-aa7b-00000000092a.png | G112: https://www.akumin.com | H112: BBB | I112: High | J112: BB | K112: Medium | L112: BB | M112: Medium | N112: 455 | O112: 347 | P112: 300 | Q112: 1102 | R112: 44672 | S112: BBB | T112: High | U112: 1776197
A113: akus | B113: Akouos Inc | C113: USD | D113: NASDAQ NMS - GLOBAL MARKET | E113: Biotechnology | F113: https://static.finnhub.io/logo/a33692c919e7f03a35025ca5873e5f14ee8f53cd5bc190cd22d677f58ceaf538.png | G113: https://akouos.com/ | H113: B | I113: Medium | J113: B | K113: Medium | L113: B | M113: Medium | N113: 205 | O113: 221 | P113: 295 | Q113: 721 | R113: 44722 | S113: B | T113: Medium | U113: 1722271
A114: akts | B114: Akoustis Technologies Inc | C114: USD | D114: NASDAQ NMS - GLOBAL MARKET | E114: Electrical Equipment | F114: https://static.finnhub.io/logo/c87e2de6-80db-11ea-b469-00000000092a.png | G114: https://ir.akoustis.com/ | H114: B | I114: Medium | J114: BB | K114: Medium | L114: BBB | M114: High | N114: 222 | O114: 302 | P114: 428 | Q114: 952 | R114: 44667 | S114: BBB | T114: High | U114: 1584754
A115: aktx | B115: Akari Therapeutics PLC | C115: USD | D115: NASDAQ NMS - GLOBAL MARKET | E115: Pharmaceuticals | F115: https://static.finnhub.io/logo/6566bacc-80cf-11ea-a49e-00000000092a.png | G115: http://akaritx.com/ | H115: B | I115: Medium | J115: B | K115: Medium | L115: BB | M115: Medium | N115: 225 | O115: 216 | P115: 305 | Q115: 746 | R115: 44667 | S115: B | T115: Medium | U115: 1541157
... A563: trtx | B563: TPG RE Finance Trust Inc | C563: USD | D563: NEW YORK STOCK EXCHANGE, INC. | E563: Real Estate | F563: https://static.finnhub.io/logo/b65451e4-80db-11ea-8f3c-00000000092a.png | G563: https://www.tpgrefinance.com/ | H563: B | I563: Medium | J563: B | K563: Medium | L563: BB | M563: Medium | N563: 230 | O563: 239 | P563: 300 | Q563: 769 | R563: 44723 | S563: BB | T563: Medium | U563: 1630472
A564: tru | B564: TransUnion | C564: USD | D564: NEW YORK STOCK EXCHANGE, INC. | E564: Professional Services | F564: https://static.finnhub.io/logo/3b251312-80d2-11ea-bca1-00000000092a.png | H564: A | I564: High | J564: BB | K564: Medium | L564: BB | M564: Medium | N564: 510 | O564: 313 | P564: 310 | Q564: 1133 | R564: 44670 | S564: BBB | T564: High | U564: 1552033
A565: yeti | B565: Yeti Holdings Inc | C565: USD | D565: NEW YORK STOCK EXCHANGE, INC. | E565: Leisure Products | F565: https://static.finnhub.io/logo/0aebcc9d893922905d4dfe5df11876799ebe829ec6f95211b7ad13b40ef8e950.png | G565: https://www.yeti.com | H565: B | I565: Medium | J565: B | K565: Medium | L565: BB | M565: Medium | N565: 269 | O565: 253 | P565: 305 | Q565: 827 | R565: 44723 | S565: BB | T565: Medium | U565: 1670592
A566: yelp | B566: Yelp Inc | C566: USD | D566: NEW YORK STOCK EXCHANGE, INC. | E566: Media | F566: https://static.finnhub.io/logo/51ef2134-80cc-11ea-9e31-00000000092a.png | G566: https://www.yelp.com/ | H566: B | I566: Medium | J566: A | K566: High | L566: B | M566: Medium | N566: 245 | O566: 515 | P566: 213 | Q566: 973 | R566: 44671 | S566: BBB | T566: High | U566: 1345016
A567: yext | B567: Yext Inc | C567: USD | D567: NEW YORK STOCK EXCHANGE, INC. | E567: Technology | F567: https://static.finnhub.io/logo/c2fec934-80db-11ea-bf15-00000000092a.png | G567: https://www.yext.com/ | H567: BB | I567: Medium | J567: BB | K567: Medium | L567: BB | M567: Medium | N567: 325 | O567: 314 | P567: 310 | Q567: 949 | R567: 44723 | S567: BBB | T567: High | U567: 1614178
A568: spr | B568: Spirit AeroSystems Holdings Inc | C568: USD | D568: NEW YORK STOCK EXCHANGE, INC. | E568: Aerospace and Defense | F568: https://static.finnhub.io/logo/74abb718-80ec-11ea-9f1c-00000000092a.png | G568: https://www.spiritaero.com/ | H568: A | I568: High | J568: BB | K568: Medium | L568: BB | M568: Medium | N568: 515 | O568: 337 | P568: 300 | Q568: 1152 | R568: 44670 | S568: BBB | T568: High | U568: 1364885
A569: ysg | B569: Yatsen Holding Ltd | C569: CNY | D569: NEW YORK STOCK EXCHANGE, INC. | E569: Consumer products | G569: http://ir.yatsenglobal.com/ | H569: BB | I569: Medium | J569: B | K569: Medium | L569: BB | M569: Medium | N569: 355 | O569: 217 | P569: 325 | Q569: 897 | R569: 44723 | S569: BB | T569: Medium | U569: 1819580
A570: yrd | B570: Yiren Digital Ltd | C570: CNY | D570: NEW YORK STOCK EXCHANGE, INC. | E570: Financial Services | F570: https://static.finnhub.io/logo/58187a7e-80d3-11ea-ad3d-00000000092a.png | G570: https://www.yirendai.com/ | H570: B | I570: Medium | J570: B | K570: Medium | L570: B | M570: Medium | N570: 200 | O570: 205 | P570: 205 | Q570: 610 | R570: 44671 | S570: B | T570: Medium | U570: 1631761
A571: yumc | B571: Yum China Holdings Inc | C571: USD | D571: NEW YORK STOCK EXCHANGE, INC. | E571: Hotels Restaurants and Leisure | F571: https://static.finnhub.io/logo/5273b318-81c3-11ea-a69e-00000000092a.png | G571: http://www.yumchina.com | H571: B | I571: Medium | J571: B | K571: Medium | L571: B | M571: Medium | N571: 205 | O571: 217 | P571: 220 | Q571: 642 | R571: 44723 | S571: B | T571: Medium | U571: 1673358
A572: trox | B572: Tronox Holdings PLC | C572: USD | D572: NEW YORK STOCK EXCHANGE, INC. | E572: Chemicals | F572: https://static.finnhub.io/logo/cae7770c-80cc-11ea-b95f-00000000092a.png | G572: https://www.tronox.com/ | H572: A | I572: High | J572: BB | K572: Medium | L572: BB | M572: Medium | N572: 503 | O572: 320 | P572: 300 | Q572: 1123 | R572: 44670 | S572: BBB | T572: High | U572: 1530804
...

Sheet Benchmarking
A1: ESG COMPANY BENCHMARKING
A2: Company-level scores vs. dynamically calculated industry benchmarks | Source: Raw Data (722 companies) | Positive = above industry average, Negative = below
A3: Company | B3: Ticker | C3: Industry | D3: Environmental Score | E3: Social Score | F3: Governance Score | G3: Total ESG Score | H3: Industry Avg ESG | I3: ESG vs Industry | J3: ESG vs Industry % | K3: Industry Avg Environmental | L3: Environmental vs Industry | M3: Industry Avg Social | N3: Social vs Industry | O3: Industry Avg Governance | P3: Governance vs Industry
A4: ='Raw Data'!B2 -> Walt Disney Co | B4: ='Raw Data'!A2 -> dis | C4: =IF('Raw Data'!E2="N/A","Unclassified",TRIM(SUBSTITUTE('Raw Data'!E2," and "," & "))) -> Media | D4: ='Raw Data'!N2 -> 510 | E4: ='Raw Data'!O2 -> 316 | F4: ='Raw Data'!P2 -> 321 | G4: ='Raw Data'!Q2 -> 1147 | H4: =INDEX('Industry Stats'!$F$2:$F$49,MATCH($C4,'Industry Stats'!$A$2:$A$49,0)) -> 935.26087 | I4: =G4-H4 -> 211.73913 | J4: =I4/H4 -> 0.2263958 | K4: =INDEX('Industry Stats'!$C$2:$C$49,MATCH($C4,'Industry Stats'!$A$2:$A$49,0)) -> 346.91304 | L4: =D4-K4 -> 163.08696 | M4: =INDEX('Industry Stats'!$D$2:$D$49,MATCH($C4,'Industry Stats'!$A$2:$A$49,0)) -> 313 | N4: =E4-M4 -> 3 | O4: =INDEX('Industry Stats'!$E$2:$E$49,MATCH($C4,'Industry Stats'!$A$2:$A$49,0)) -> 275.34783 | P4: =F4-O4 -> 45.652174 | R4: =G4+(10000-ROW())/10000000 -> 1147.001 | S4: =D4+(10000-ROW())/10000000 -> 510.001 | T4: =E4+(10000-ROW())/10000000 -> 316.001 | U4: =F4+(10000-ROW())/10000000 -> 321.001 | V4: =I4+(10000-ROW())/10000000 -> 211.74013 | W4: =-I4+(10000-ROW())/10000000 -> -211.73813
A5: ='Raw Data'!B3 -> General Motors Co | B5: ='Raw Data'!A3 -> gm | C5: =IF('Raw Data'!E3="N/A","Unclassified",TRIM(SUBSTITUTE('Raw Data'!E3," and "," & "))) -> Automobiles | D5: ='Raw Data'!N3 -> 510 | E5: ='Raw Data'!O3 -> 303 | F5: ='Raw Data'!P3 -> 255 | G5: ='Raw Data'!Q3 -> 1068 | H5: =INDEX('Industry Stats'!$F$2:$F$49,MATCH($C5,'Industry Stats'!$A$2:$A$49,0)) -> 859.25 | I5: =G5-H5 -> 208.75 | J5: =I5/H5 -> 0.24294443 | K5: =INDEX('Industry Stats'!$C$2:$C$49,MATCH($C5,'Industry Stats'!$A$2:$A$49,0)) -> 393 | L5: =D5-K5 -> 117 | M5: =INDEX('Industry Stats'!$D$2:$D$49,MATCH($C5,'Industry Stats'!$A$2:$A$49,0)) -> 229.25 | N5: =E5-M5 -> 73.75 | O5: =INDEX('Industry Stats'!$E$2:$E$49,MATCH($C5,'Industry Stats'!$A$2:$A$49,0)) -> 237 | P5: =F5-O5 -> 18 | R5: =G5+(10000-ROW())/10000000 -> 1068.001 | S5: =D5+(10000-ROW())/10000000 -> 510.001 | T5: =E5+(10000-ROW())/10000000 -> 303.001 | U5: =F5+(10000-ROW())/10000000 -> 255.001 | V5: =I5+(10000-ROW())/10000000 -> 208.751 | W5: =-I5+(10000-ROW())/10000000 -> -208.749
A6: ='Raw Data'!B4 -> WW Grainger Inc | B6: ='Raw Data'!A4 -> gww | C6: =IF('Raw Data'!E4="N/A","Unclassified",TRIM(SUBSTITUTE('Raw Data'!E4," and "," & "))) -> Trading Companies & Distributors | D6: ='Raw Data'!N4 -> 255 | E6: ='Raw Data'!O4 -> 385 | F6: ='Raw Data'!P4 -> 240 | G6: ='Raw Data'!Q4 -> 880 | H6: =INDEX('Industry Stats'!$F$2:$F$49,MATCH($C6,'Industry Stats'!$A$2:$A$49,0)) -> 885.2 | I6: =G6-H6 -> -5.2 | J6: =I6/H6 -> -0.0058743787 | K6: =INDEX('Industry Stats'!$C$2:$C$49,MATCH($C6,'Industry Stats'!$A$2:$A$49,0)) -> 332.8 | L6: =D6-K6 -> -77.8 | M6: =INDEX('Industry Stats'!$D$2:$D$49,MATCH($C6,'Industry Stats'!$A$2:$A$49,0)) -> 302.4 | N6: =E6-M6 -> 82.6 | O6: =INDEX('Industry Stats'!$E$2:$E$49,MATCH($C6,'Industry Stats'!$A$2:$A$49,0)) -> 250 | P6: =F6-O6 -> -10 | R6: =G6+(10000-ROW())/10000000 -> 880.001 | S6: =D6+(10000-ROW())/10000000 -> 255.001 | T6: =E6+(10000-ROW())/10000000 -> 385.001 | U6: =F6+(10000-ROW())/10000000 -> 240.001 | V6: =I6+(10000-ROW())/10000000 -> -5.1990006 | W6: =-I6+(10000-ROW())/10000000 -> 5.2009994
A7: ='Raw Data'!B5 -> Mohawk Industries Inc | B7: ='Raw Data'!A5 -> mhk | C7: =IF('Raw Data'!E5="N/A","Unclassified",TRIM(SUBSTITUTE('Raw Data'!E5," and "," & "))) -> Consumer products | D7: ='Raw Data'!N5 -> 570 | E7: ='Raw Data'!O5 -> 298 | F7: ='Raw Data'!P5 -> 303 | G7: ='Raw Data'!Q5 -> 1171 | H7: =INDEX('Industry Stats'!$F$2:$F$49,MATCH($C7,'Industry Stats'!$A$2:$A$49,0)) -> 945.55 | I7: =G7-H7 -> 225.45 | J7: =I7/H7 -> 0.23843266 | K7: =INDEX('Industry Stats'!$C$2:$C$49,MATCH($C7,'Industry Stats'!$A$2:$A$49,0)) -> 384.9 | L7: =D7-K7 -> 185.1 | M7: =INDEX('Industry Stats'!$D$2:$D$49,MATCH($C7,'Industry Stats'!$A$2:$A$49,0)) -> 285.7 | N7: =E7-M7 -> 12.3 | O7: =INDEX('Industry Stats'!$E$2:$E$49,MATCH($C7,'Industry Stats'!$A$2:$A$49,0)) -> 274.95 | P7: =F7-O7 -> 28.05 | R7: =G7+(10000-ROW())/10000000 -> 1171.001 | S7: =D7+(10000-ROW())/10000000 -> 570.001 | T7: =E7+(10000-ROW())/10000000 -> 298.001 | U7: =F7+(10000-ROW())/10000000 -> 303.001 | V7: =I7+(10000-ROW())/10000000 -> 225.451 | W7: =-I7+(10000-ROW())/10000000 -> -225.449
A8: ='Raw Data'!B6 -> Live Nation Entertainment Inc | B8: ='Raw Data'!A6 -> lyv | C8: =IF('Raw Data'!E6="N/A","Unclassified",TRIM(SUBSTITUTE('Raw Data'!E6," and "," & "))) -> Media | D8: ='Raw Data'!N6 -> 492 | E8: ='Raw Data'!O6 -> 310 | F8: ='Raw Data'!P6 -> 250 | G8: ='Raw Data'!Q6 -> 1052 | H8: =INDEX('Industry Stats'!$F$2:$F$49,MATCH($C8,'Industry Stats'!$A$2:$A$49,0)) -> 935.26087 | I8: =G8-H8 -> 116.73913 | J8: =I8/H8 -> 0.12481986 | K8: =INDEX('Industry Stats'!$C$2:$C$49,MATCH($C8,'Industry Stats'!$A$2:$A$49,0)) -> 346.91304 | L8: =D8-K8 -> 145.08696 | M8: =INDEX('Industry Stats'!$D$2:$D$49,MATCH($C8,'Industry Stats'!$A$2:$A$49,0)) -> 313 | N8: =E8-M8 -> -3 | O8: =INDEX('Industry Stats'!$E$2:$E$49,MATCH($C8,'Industry Stats'!$A$2:$A$49,0)) -> 275.34783 | P8: =F8-O8 -> -25.347826 | R8: =G8+(10000-ROW())/10000000 -> 1052.001 | S8: =D8+(10000-ROW())/10000000 -> 492.001 | T8: =E8+(10000-ROW())/10000000 -> 310.001 | U8: =F8+(10000-ROW())/10000000 -> 250.001 | V8: =I8+(10000-ROW())/10000000 -> 116.74013 | W8: =-I8+(10000-ROW())/10000000 -> -116.73813
A9: ='Raw Data'!B7 -> Las Vegas Sands Corp | B9: ='Raw Data'!A7 -> lvs | C9: =IF('Raw Data'!E7="N/A","Unclassified",TRIM(SUBSTITUTE('Raw Data'!E7," and "," & "))) -> Hotels Restaurants & Leisure | D9: ='Raw Data'!N7 -> 547 | E9: ='Raw Data'!O7 -> 318 | F9: ='Raw Data'!P7 -> 313 | G9: ='Raw Data'!Q7 -> 1178 | H9: =INDEX('Industry Stats'!$F$2:$F$49,MATCH($C9,'Industry Stats'!$A$2:$A$49,0)) -> 918.86364 | I9: =G9-H9 -> 259.13636 | J9: =I9/H9 -> 0.2820183 | K9: =INDEX('Industry Stats'!$C$2:$C$49,MATCH($C9,'Industry Stats'!$A$2:$A$49,0)) -> 374.63636 | L9: =D9-K9 -> 172.36364 | M9: =INDEX('Industry Stats'!$D$2:$D$49,MATCH($C9,'Industry Stats'!$A$2:$A$49,0)) -> 283.04545 | N9: =E9-M9 -> 34.954545 | O9: =INDEX('Industry Stats'!$E$2:$E$49,MATCH($C9,'Industry Stats'!$A$2:$A$49,0)) -> 261.18182 | P9: =F9-O9 -> 51.818182 | R9: =G9+(10000-ROW())/10000000 -> 1178.001 | S9: =D9+(10000-ROW())/10000000 -> 547.001 | T9: =E9+(10000-ROW())/10000000 -> 318.001 | U9: =F9+(10000-ROW())/10000000 -> 313.001 | V9: =I9+(10000-ROW())/10000000 -> 259.13736 | W9: =-I9+(10000-ROW())/10000000 -> -259.13536
A10: ='Raw Data'!B8 -> Clorox Co | B10: ='Raw Data'!A8 -> clx | C10: =IF('Raw Data'!E8="N/A","Unclassified",TRIM(SUBSTITUTE('Raw Data'!E8," and "," & "))) -> Consumer products | D10: ='Raw Data'!N8 -> 560 | E10: ='Raw Data'!O8 -> 350 | F10: ='Raw Data'!P8 -> 345 | G10: ='Raw Data'!Q8 -> 1255 | H10: =INDEX('Industry Stats'!$F$2:$F$49,MATCH($C10,'Industry Stats'!$A$2:$A$49,0)) -> 945.55 | I10: =G10-H10 -> 309.45 | J10: =I10/H10 -> 0.32726984 | K10: =INDEX('Industry Stats'!$C$2:$C$49,MATCH($C10,'Industry Stats'!$A$2:$A$49,0)) -> 384.9 | L10: =D10-K10 -> 175.1 | M10: =INDEX('Industry Stats'!$D$2:$D$49,MATCH($C10,'Industry Stats'!$A$2:$A$49,0)) -> 285.7 | N10: =E10-M10 -> 64.3 | O10: =INDEX('Industry Stats'!$E$2:$E$49,MATCH($C10,'Industry Stats'!$A$2:$A$49,0)) -> 274.95 | P10: =F10-O10 -> 70.05 | R10: =G10+(10000-ROW())/10000000 -> 1255.001 | S10: =D10+(10000-ROW())/10000000 -> 560.001 | T10: =E10+(10000-ROW())/10000000 -> 350.001 | U10: =F10+(10000-ROW())/10000000 -> 345.001 | V10: =I10+(10000-ROW())/10000000 -> 309.451 | W10: =-I10+(10000-ROW())/10000000 -> -309.449
A11: ='Raw Data'!B9 -> ATA Creativity Global | B11: ='Raw Data'!A9 -> aacg | C11: =IF('Raw Data'!E9="N/A","Unclassified",TRIM(SUBSTITUTE('Raw Data'!E9," and "," & "))) -> Diversified Consumer Services | D11: ='Raw Data'!N9 -> 203 | E11: ='Raw Data'!O9 -> 200 | F11: ='Raw Data'!P9 -> 205 | G11: ='Raw Data'!Q9 -> 608 | H11: =INDEX('Industry Stats'!$F$2:$F$49,MATCH($C11,'Industry Stats'!$A$2:$A$49,0)) -> 739.33333 | I11: =G11-H11 -> -131.33333 | J11: =I11/H11 -> -0.17763751 | K11: =INDEX('Industry Stats'!$C$2:$C$49,MATCH($C11,'Industry Stats'!$A$2:$A$49,0)) -> 286 | L11: =D11-K11 -> -83 | M11: =INDEX('Industry Stats'!$D$2:$D$49,MATCH($C11,'Industry Stats'!$A$2:$A$49,0)) -> 233.33333 | N11: =E11-M11 -> -33.333333 | O11: =INDEX('Industry Stats'!$E$2:$E$49,MATCH($C11,'Industry Stats'!$A$2:$A$49,0)) -> 220 | P11: =F11-O11 -> -15 | R11: =G11+(10000-ROW())/10000000 -> 608.001 | S11: =D11+(10000-ROW())/10000000 -> 203.001 | T11: =E11+(10000-ROW())/10000000 -> 200.001 | U11: =F11+(10000-ROW())/10000000 -> 205.001 | V11: =I11+(10000-ROW())/10000000 -> -131.33233 | W11: =-I11+(10000-ROW())/10000000 -> 131.33433
A12: ='Raw Data'!B10 -> American Airlines Group Inc | B12: ='Raw Data'!A10 -> aal | C12: =IF('Raw Data'!E10="N/A","Unclassified",TRIM(SUBSTITUTE('Raw Data'!E10," and "," & "))) -> Airlines | D12: ='Raw Data'!N10 -> 270 | E12: ='Raw Data'!O10 -> 211 | F12: ='Raw Data'!P10 -> 265 | G12: ='Raw Data'!Q10 -> 746 | H12: =INDEX('Industry Stats'!$F$2:$F$49,MATCH($C12,'Industry Stats'!$A$2:$A$49,0)) -> 838.71429 | I12: =G12-H12 -> -92.714286 | J12: =I12/H12 -> -0.11054335 | K12: =INDEX('Industry Stats'!$C$2:$C$49,MATCH($C12,'Industry Stats'!$A$2:$A$49,0)) -> 326.71429 | L12: =D12-K12 -> -56.714286 | M12: =INDEX('Industry Stats'!$D$2:$D$49,MATCH($C12,'Industry Stats'!$A$2:$A$49,0)) -> 265.71429 | N12: =E12-M12 -> -54.714286 | O12: =INDEX('Industry Stats'!$E$2:$E$49,MATCH($C12,'Industry Stats'!$A$2:$A$49,0)) -> 246.28571 | P12: =F12-O12 -> 18.714286 | R12: =G12+(10000-ROW())/10000000 -> 746.001 | S12: =D12+(10000-ROW())/10000000 -> 270.001 | T12: =E12+(10000-ROW())/10000000 -> 211.001 | U12: =F12+(10000-ROW())/10000000 -> 265.001 | V12: =I12+(10000-ROW())/10000000 -> -92.713287 | W12: =-I12+(10000-ROW())/10000000 -> 92.715285
A13: ='Raw Data'!B11 -> Atlantic American Corp | B13: ='Raw Data'!A11 -> aame | C13: =IF('Raw Data'!E11="N/A","Unclassified",TRIM(SUBSTITUTE('Raw Data'!E11," and "," & "))) -> Insurance | D13: ='Raw Data'!N11 -> 220 | E13: ='Raw Data'!O11 -> 221 | F13: ='Raw Data'!P11 -> 300 | G13: ='Raw Data'!Q11 -> 741 | H13: =INDEX('Industry Stats'!$F$2:$F$49,MATCH($C13,'Industry Stats'!$A$2:$A$49,0)) -> 1012.3704 | I13: =G13-H13 -> -271.37037 | J13: =I13/H13 -> -0.26805444 | K13: =INDEX('Industry Stats'!$C$2:$C$49,MATCH($C13,'Industry Stats'!$A$2:$A$49,0)) -> 425.25926 | L13: =D13-K13 -> -205.25926 | M13: =INDEX('Industry Stats'!$D$2:$D$49,MATCH($C13,'Industry Stats'!$A$2:$A$49,0)) -> 295.66667 | N13: =E13-M13 -> -74.666667 | O13: =INDEX('Industry Stats'!$E$2:$E$49,MATCH($C13,'Industry Stats'!$A$2:$A$49,0)) -> 291.44444 | P13: =F13-O13 -> 8.5555556 | R13: =G13+(10000-ROW())/10000000 -> 741.001 | S13: =D13+(10000-ROW())/10000000 -> 220.001 | T13: =E13+(10000-ROW())/10000000 -> 221.001 | U13: =F13+(10000-ROW())/10000000 -> 300.001 | V13: =I13+(10000-ROW())/10000000 -> -271.36937 | W13: =-I13+(10000-ROW())/10000000 -> 271.37137
A14: ='Raw Data'!B12 -> Applied Optoelectronics Inc | B14: ='Raw Data'!A12 -> aaoi | C14: =IF('Raw Data'!E12="N/A","Unclassified",TRIM(SUBSTITUTE('Raw Data'!E12," and "," & "))) -> Communications | D14: ='Raw Data'!N12 -> 311 | E14: ='Raw Data'!O12 -> 256 | F14: ='Raw Data'!P12 -> 218 | G14: ='Raw Data'!Q12 -> 785 | H14: =INDEX('Industry Stats'!$F$2:$F$49,MATCH($C14,'Industry Stats'!$A$2:$A$49,0)) -> 938.22222 | I14: =G14-H14 -> -153.22222 | J14: =I14/H14 -> -0.16331123 | K14: =INDEX('Industry Stats'!$C$2:$C$49,MATCH($C14,'Industry Stats'!$A$2:$A$49,0)) -> 385 | L14: =D14-K14 -> -74 | M14: =INDEX('Industry Stats'!$D$2:$D$49,MATCH($C14,'Industry Stats'!$A$2:$A$49,0)) -> 278.77778 | N14: =E14-M14 -> -22.777778 | O14: =INDEX('Industry Stats'!$E$2:$E$49,MATCH($C14,'Industry Stats'!$A$2:$A$49,0)) -> 274.44444 | P14: =F14-O14 -> -56.444444 | R14: =G14+(10000-ROW())/10000000 -> 785.001 | S14: =D14+(10000-ROW())/10000000 -> 311.001 | T14: =E14+(10000-ROW())/10000000 -> 256.001 | U14: =F14+(10000-ROW())/10000000 -> 218.001 | V14: =I14+(10000-ROW())/10000000 -> -153.22122 | W14: =-I14+(10000-ROW())/10000000 -> 153.22322
A15: ='Raw Data'!B13 -> Aaon Inc | B15: ='Raw Data'!A13 -> aaon | C15: =IF('Raw Data'!E13="N/A","Unclassified",TRIM(SUBSTITUTE('Raw Data'!E13," and "," & "))) -> Building | D15: ='Raw Data'!N13 -> 500 | E15: ='Raw Data'!O13 -> 300 | F15: ='Raw Data'!P13 -> 223 | G15: ='Raw Data'!Q13 -> 1023 | H15: =INDEX('Industry Stats'!$F$2:$F$49,MATCH($C15,'Industry Stats'!$A$2:$A$49,0)) -> 1074.2 | I15: =G15-H15 -> -51.2 | J15: =I15/H15 -> -0.047663377 | K15: =INDEX('Industry Stats'!$C$2:$C$49,MATCH($C15,'Industry Stats'!$A$2:$A$49,0)) -> 476.7 | L15: =D15-K15 -> 23.3 | M15: =INDEX('Industry Stats'!$D$2:$D$49,MATCH($C15,'Industry Stats'!$A$2:$A$49,0)) -> 305.1 | N15: =E15-M15 -> -5.1 | O15: =INDEX('Industry Stats'!$E$2:$E$49,MATCH($C15,'Industry Stats'!$A$2:$A$49,0)) -> 292.4 | P15: =F15-O15 -> -69.4 | R15: =G15+(10000-ROW())/10000000 -> 1023.001 | S15: =D15+(10000-ROW())/10000000 -> 500.001 | T15: =E15+(10000-ROW())/10000000 -> 300.001 | U15: =F15+(10000-ROW())/10000000 -> 223.001 | V15: =I15+(10000-ROW())/10000000 -> -51.199002 | W15: =-I15+(10000-ROW())/10000000 -> 51.200999
... A725: ='Raw Data'!B723 -> HEICO Corp | B725: ='Raw Data'!A723 -> hei | C725: =IF('Raw Data'!E723="N/A","Unclassified",TRIM(SUBSTITUTE('Raw Data'!E723," and "," & "))) -> Aerospace & Defense | D725: ='Raw Data'!N723 -> 225 | E725: ='Raw Data'!O723 -> 203 | F725: ='Raw Data'!P723 -> 205 | G725: ='Raw Data'!Q723 -> 633 | H725: =INDEX('Industry Stats'!$F$2:$F$49,MATCH($C725,'Industry Stats'!$A$2:$A$49,0)) -> 1048.1818 | I725: =G725-H725 -> -415.18182 | J725: =I725/H725 -> -0.39609714 | K725: =INDEX('Industry Stats'!$C$2:$C$49,MATCH($C725,'Industry Stats'!$A$2:$A$49,0)) -> 461.36364 | L725: =D725-K725 -> -236.36364 | M725: =INDEX('Industry Stats'!$D$2:$D$49,MATCH($C725,'Industry Stats'!$A$2:$A$49,0)) -> 296.36364 | N725: =E725-M725 -> -93.363636 | O725: =INDEX('Industry Stats'!$E$2:$E$49,MATCH($C725,'Industry Stats'!$A$2:$A$49,0)) -> 290.45455 | P725: =F725-O725 -> -85.454545 | R725: =G725+(10000-ROW())/10000000 -> 633.00093 | S725: =D725+(10000-ROW())/10000000 -> 225.00093 | T725: =E725+(10000-ROW())/10000000 -> 203.00093 | U725: =F725+(10000-ROW())/10000000 -> 205.00093 | V725: =I725+(10000-ROW())/10000000 -> -415.18089 | W725: =-I725+(10000-ROW())/10000000 -> 415.18275

Sheet Pillar Analysis
A1: PILLAR ANALYSIS (E / S / G)
A2: Moves beyond the aggregate ESG score to examine balance and imbalance across Environmental, Social and Governance pillars. "Pillar Range", "percentile" and "Investigation Flag" are project-created analytical measures for this workbook only — they are NOT an official ESG risk rating, methodology, or third-party score of any kind.
A3: Company | B3: Ticker | C3: Industry | D3: Environmental Score | E3: Social Score | F3: Governance Score | G3: Total ESG Score | H3: Strongest Pillar | I3: Weakest Pillar | J3: E - S Gap | K3: S - G Gap | L3: E - G Gap | M3: Pillar Range (Max-Min) | N3: Total ESG Percentile | O3: Weakest Pillar Percentile | P3: Pillar Imbalance Gap | Q3: Investigation Flag (Project-Created Analytical Flag, Not an Official ESG Rating)
A4: =Benchmarking!A4 -> Walt Disney Co | B4: =Benchmarking!B4 -> dis | C4: =Benchmarking!C4 -> Media | D4: =Benchmarking!D4 -> 510 | E4: =Benchmarking!E4 -> 316 | F4: =Benchmarking!F4 -> 321 | G4: =Benchmarking!G4 -> 1147 | H4: =IF(AND(D4>=E4,D4>=F4),"Environmental",IF(AND(E4>=D4,E4>=F4),"Social","Governance")) -> Environmental | I4: =IF(AND(D4<=E4,D4<=F4),"Environmental",IF(AND(E4<=D4,E4<=F4),"Social","Governance")) -> Social | J4: =D4-E4 -> 194 | K4: =E4-F4 -> -5 | L4: =D4-F4 -> 189 | M4: =MAX(D4:F4)-MIN(D4:F4) -> 194 | N4: =RANK(G4,$G$4:$G$725,1)/COUNT($G$4:$G$725) -> 0.76038781 | O4: =MIN(RANK(D4,$D$4:$D$725,1)/COUNT($D$4:$D$725),RANK(E4,$E$4:$E$725,1)/COUNT($E$4:$E$725),RANK(F4,$F$4:$F$725,1)/COUNT($F$4:$F$725)) -> 0.66620499 | P4: =N4-O4 -> 0.094182825 | Q4: =IF(AND(N4>=0.7,P4>=0.4),"High ESG / weak pillar (analytical flag - not an ESG rating) - warrants investigation","") | S4: =M4+(10000-ROW())/10000000 -> 194.001 | T4: =P4+(10000-ROW())/10000000 -> 0.095182425
A5: =Benchmarking!A5 -> General Motors Co | B5: =Benchmarking!B5 -> gm | C5: =Benchmarking!C5 -> Automobiles | D5: =Benchmarking!D5 -> 510 | E5: =Benchmarking!E5 -> 303 | F5: =Benchmarking!F5 -> 255 | G5: =Benchmarking!G5 -> 1068 | H5: =IF(AND(D5>=E5,D5>=F5),"Environmental",IF(AND(E5>=D5,E5>=F5),"Social","Governance")) -> Environmental | I5: =IF(AND(D5<=E5,D5<=F5),"Environmental",IF(AND(E5<=D5,E5<=F5),"Social","Governance")) -> Governance | J5: =D5-E5 -> 207 | K5: =E5-F5 -> 48 | L5: =D5-F5 -> 255 | M5: =MAX(D5:F5)-MIN(D5:F5) -> 255 | N5: =RANK(G5,$G$4:$G$725,1)/COUNT($G$4:$G$725) -> 0.52770083 | O5: =MIN(RANK(D5,$D$4:$D$725,1)/COUNT($D$4:$D$725),RANK(E5,$E$4:$E$725,1)/COUNT($E$4:$E$725),RANK(F5,$F$4:$F$725,1)/COUNT($F$4:$F$725)) -> 0.31024931 | P5: =N5-O5 -> 0.21745152 | Q5: =IF(AND(N5>=0.7,P5>=0.4),"High ESG / weak pillar (analytical flag - not an ESG rating) - warrants investigation","") | S5: =M5+(10000-ROW())/10000000 -> 255.001 | T5: =P5+(10000-ROW())/10000000 -> 0.21845102
A6: =Benchmarking!A6 -> WW Grainger Inc | B6: =Benchmarking!B6 -> gww | C6: =Benchmarking!C6 -> Trading Companies & Distributors | D6: =Benchmarking!D6 -> 255 | E6: =Benchmarking!E6 -> 385 | F6: =Benchmarking!F6 -> 240 | G6: =Benchmarking!G6 -> 880 | H6: =IF(AND(D6>=E6,D6>=F6),"Environmental",IF(AND(E6>=D6,E6>=F6),"Social","Governance")) -> Social | I6: =IF(AND(D6<=E6,D6<=F6),"Environmental",IF(AND(E6<=D6,E6<=F6),"Social","Governance")) -> Governance | J6: =D6-E6 -> -130 | K6: =E6-F6 -> 145 | L6: =D6-F6 -> 15 | M6: =MAX(D6:F6)-MIN(D6:F6) -> 145 | N6: =RANK(G6,$G$4:$G$725,1)/COUNT($G$4:$G$725) -> 0.35734072 | O6: =MIN(RANK(D6,$D$4:$D$725,1)/COUNT($D$4:$D$725),RANK(E6,$E$4:$E$725,1)/COUNT($E$4:$E$725),RANK(F6,$F$4:$F$725,1)/COUNT($F$4:$F$725)) -> 0.27423823 | P6: =N6-O6 -> 0.083102493 | Q6: =IF(AND(N6>=0.7,P6>=0.4),"High ESG / weak pillar (analytical flag - not an ESG rating) - warrants investigation","") | S6: =M6+(10000-ROW())/10000000 -> 145.001 | T6: =P6+(10000-ROW())/10000000 -> 0.084101893
A7: =Benchmarking!A7 -> Mohawk Industries Inc | B7: =Benchmarking!B7 -> mhk | C7: =Benchmarking!C7 -> Consumer products | D7: =Benchmarking!D7 -> 570 | E7: =Benchmarking!E7 -> 298 | F7: =Benchmarking!F7 -> 303 | G7: =Benchmarking!G7 -> 1171 | H7: =IF(AND(D7>=E7,D7>=F7),"Environmental",IF(AND(E7>=D7,E7>=F7),"Social","Governance")) -> Environmental | I7: =IF(AND(D7<=E7,D7<=F7),"Environmental",IF(AND(E7<=D7,E7<=F7),"Social","Governance")) -> Social | J7: =D7-E7 -> 272 | K7: =E7-F7 -> -5 | L7: =D7-F7 -> 267 | M7: =MAX(D7:F7)-MIN(D7:F7) -> 272 | N7: =RANK(G7,$G$4:$G$725,1)/COUNT($G$4:$G$725) -> 0.82825485 | O7: =MIN(RANK(D7,$D$4:$D$725,1)/COUNT($D$4:$D$725),RANK(E7,$E$4:$E$725,1)/COUNT($E$4:$E$725),RANK(F7,$F$4:$F$725,1)/COUNT($F$4:$F$725)) -> 0.35872576 | P7: =N7-O7 -> 0.46952909 | Q7: =IF(AND(N7>=0.7,P7>=0.4),"High ESG / weak pillar (analytical flag - not an ESG rating) - warrants investigation","") -> High ESG / weak pillar (analytical flag - not an ESG rating) - warrants investigation | S7: =M7+(10000-ROW())/10000000 -> 272.001 | T7: =P7+(10000-ROW())/10000000 -> 0.47052839
A8: =Benchmarking!A8 -> Live Nation Entertainment Inc | B8: =Benchmarking!B8 -> lyv | C8: =Benchmarking!C8 -> Media | D8: =Benchmarking!D8 -> 492 | E8: =Benchmarking!E8 -> 310 | F8: =Benchmarking!F8 -> 250 | G8: =Benchmarking!G8 -> 1052 | H8: =IF(AND(D8>=E8,D8>=F8),"Environmental",IF(AND(E8>=D8,E8>=F8),"Social","Governance")) -> Environmental | I8: =IF(AND(D8<=E8,D8<=F8),"Environmental",IF(AND(E8<=D8,E8<=F8),"Social","Governance")) -> Governance | J8: =D8-E8 -> 182 | K8: =E8-F8 -> 60 | L8: =D8-F8 -> 242 | M8: =MAX(D8:F8)-MIN(D8:F8) -> 242 | N8: =RANK(G8,$G$4:$G$725,1)/COUNT($G$4:$G$725) -> 0.50692521 | O8: =MIN(RANK(D8,$D$4:$D$725,1)/COUNT($D$4:$D$725),RANK(E8,$E$4:$E$725,1)/COUNT($E$4:$E$725),RANK(F8,$F$4:$F$725,1)/COUNT($F$4:$F$725)) -> 0.29639889 | P8: =N8-O8 -> 0.21052632 | Q8: =IF(AND(N8>=0.7,P8>=0.4),"High ESG / weak pillar (analytical flag - not an ESG rating) - warrants investigation","") | S8: =M8+(10000-ROW())/10000000 -> 242.001 | T8: =P8+(10000-ROW())/10000000 -> 0.21152552
A9: =Benchmarking!A9 -> Las Vegas Sands Corp | B9: =Benchmarking!B9 -> lvs | C9: =Benchmarking!C9 -> Hotels Restaurants & Leisure | D9: =Benchmarking!D9 -> 547 | E9: =Benchmarking!E9 -> 318 | F9: =Benchmarking!F9 -> 313 | G9: =Benchmarking!G9 -> 1178 | H9: =IF(AND(D9>=E9,D9>=F9),"Environmental",IF(AND(E9>=D9,E9>=F9),"Social","Governance")) -> Environmental | I9: =IF(AND(D9<=E9,D9<=F9),"Environmental",IF(AND(E9<=D9,E9<=F9),"Social","Governance")) -> Governance | J9: =D9-E9 -> 229 | K9: =E9-F9 -> 5 | L9: =D9-F9 -> 234 | M9: =MAX(D9:F9)-MIN(D9:F9) -> 234 | N9: =RANK(G9,$G$4:$G$725,1)/COUNT($G$4:$G$725) -> 0.84487535 | O9: =MIN(RANK(D9,$D$4:$D$725,1)/COUNT($D$4:$D$725),RANK(E9,$E$4:$E$725,1)/COUNT($E$4:$E$725),RANK(F9,$F$4:$F$725,1)/COUNT($F$4:$F$725)) -> 0.6966759 | P9: =N9-O9 -> 0.14819945 | Q9: =IF(AND(N9>=0.7,P9>=0.4),"High ESG / weak pillar (analytical flag - not an ESG rating) - warrants investigation","") | S9: =M9+(10000-ROW())/10000000 -> 234.001 | T9: =P9+(10000-ROW())/10000000 -> 0.14919855
A10: =Benchmarking!A10 -> Clorox Co | B10: =Benchmarking!B10 -> clx | C10: =Benchmarking!C10 -> Consumer products | D10: =Benchmarking!D10 -> 560 | E10: =Benchmarking!E10 -> 350 | F10: =Benchmarking!F10 -> 345 | G10: =Benchmarking!G10 -> 1255 | H10: =IF(AND(D10>=E10,D10>=F10),"Environmental",IF(AND(E10>=D10,E10>=F10),"Social","Governance")) -> Environmental | I10: =IF(AND(D10<=E10,D10<=F10),"Environmental",IF(AND(E10<=D10,E10<=F10),"Social","Governance")) -> Governance | J10: =D10-E10 -> 210 | K10: =E10-F10 -> 5 | L10: =D10-F10 -> 215 | M10: =MAX(D10:F10)-MIN(D10:F10) -> 215 | N10: =RANK(G10,$G$4:$G$725,1)/COUNT($G$4:$G$725) -> 0.93767313 | O10: =MIN(RANK(D10,$D$4:$D$725,1)/COUNT($D$4:$D$725),RANK(E10,$E$4:$E$725,1)/COUNT($E$4:$E$725),RANK(F10,$F$4:$F$725,1)/COUNT($F$4:$F$725)) -> 0.90443213 | P10: =N10-O10 -> 0.033240997 | Q10: =IF(AND(N10>=0.7,P10>=0.4),"High ESG / weak pillar (analytical flag - not an ESG rating) - warrants investigation","") | S10: =M10+(10000-ROW())/10000000 -> 215.001 | T10: =P10+(10000-ROW())/10000000 -> 0.034239997
A11: =Benchmarking!A11 -> ATA Creativity Global | B11: =Benchmarking!B11 -> aacg | C11: =Benchmarking!C11 -> Diversified Consumer Services | D11: =Benchmarking!D11 -> 203 | E11: =Benchmarking!E11 -> 200 | F11: =Benchmarking!F11 -> 205 | G11: =Benchmarking!G11 -> 608 | H11: =IF(AND(D11>=E11,D11>=F11),"Environmental",IF(AND(E11>=D11,E11>=F11),"Social","Governance")) -> Governance | I11: =IF(AND(D11<=E11,D11<=F11),"Environmental",IF(AND(E11<=D11,E11<=F11),"Social","Governance")) -> Social | J11: =D11-E11 -> 3 | K11: =E11-F11 -> -5 | L11: =D11-F11 -> -2 | M11: =MAX(D11:F11)-MIN(D11:F11) -> 5 | N11: =RANK(G11,$G$4:$G$725,1)/COUNT($G$4:$G$725) -> 0.022160665 | O11: =MIN(RANK(D11,$D$4:$D$725,1)/COUNT($D$4:$D$725),RANK(E11,$E$4:$E$725,1)/COUNT($E$4:$E$725),RANK(F11,$F$4:$F$725,1)/COUNT($F$4:$F$725)) -> 0.0027700831 | P11: =N11-O11 -> 0.019390582 | Q11: =IF(AND(N11>=0.7,P11>=0.4),"High ESG / weak pillar (analytical flag - not an ESG rating) - warrants investigation","") | S11: =M11+(10000-ROW())/10000000 -> 5.0009989 | T11: =P11+(10000-ROW())/10000000 -> 0.020389482
A12: =Benchmarking!A12 -> American Airlines Group Inc | B12: =Benchmarking!B12 -> aal | C12: =Benchmarking!C12 -> Airlines | D12: =Benchmarking!D12 -> 270 | E12: =Benchmarking!E12 -> 211 | F12: =Benchmarking!F12 -> 265 | G12: =Benchmarking!G12 -> 746 | H12: =IF(AND(D12>=E12,D12>=F12),"Environmental",IF(AND(E12>=D12,E12>=F12),"Social","Governance")) -> Environmental | I12: =IF(AND(D12<=E12,D12<=F12),"Environmental",IF(AND(E12<=D12,E12<=F12),"Social","Governance")) -> Social | J12: =D12-E12 -> 59 | K12: =E12-F12 -> -54 | L12: =D12-F12 -> 5 | M12: =MAX(D12:F12)-MIN(D12:F12) -> 59 | N12: =RANK(G12,$G$4:$G$725,1)/COUNT($G$4:$G$725) -> 0.22160665 | O12: =MIN(RANK(D12,$D$4:$D$725,1)/COUNT($D$4:$D$725),RANK(E12,$E$4:$E$725,1)/COUNT($E$4:$E$725),RANK(F12,$F$4:$F$725,1)/COUNT($F$4:$F$725)) -> 0.11357341 | P12: =N12-O12 -> 0.10803324 | Q12: =IF(AND(N12>=0.7,P12>=0.4),"High ESG / weak pillar (analytical flag - not an ESG rating) - warrants investigation","") | S12: =M12+(10000-ROW())/10000000 -> 59.000999 | T12: =P12+(10000-ROW())/10000000 -> 0.10903204
A13: =Benchmarking!A13 -> Atlantic American Corp | B13: =Benchmarking!B13 -> aame | C13: =Benchmarking!C13 -> Insurance | D13: =Benchmarking!D13 -> 220 | E13: =Benchmarking!E13 -> 221 | F13: =Benchmarking!F13 -> 300 | G13: =Benchmarking!G13 -> 741 | H13: =IF(AND(D13>=E13,D13>=F13),"Environmental",IF(AND(E13>=D13,E13>=F13),"Social","Governance")) -> Governance | I13: =IF(AND(D13<=E13,D13<=F13),"Environmental",IF(AND(E13<=D13,E13<=F13),"Social","Governance")) -> Environmental | J13: =D13-E13 -> -1 | K13: =E13-F13 -> -79 | L13: =D13-F13 -> -80 | M13: =MAX(D13:F13)-MIN(D13:F13) -> 80 | N13: =RANK(G13,$G$4:$G$725,1)/COUNT($G$4:$G$725) -> 0.21052632 | O13: =MIN(RANK(D13,$D$4:$D$725,1)/COUNT($D$4:$D$725),RANK(E13,$E$4:$E$725,1)/COUNT($E$4:$E$725),RANK(F13,$F$4:$F$725,1)/COUNT($F$4:$F$725)) -> 0.1468144 | P13: =N13-O13 -> 0.063711911 | Q13: =IF(AND(N13>=0.7,P13>=0.4),"High ESG / weak pillar (analytical flag - not an ESG rating) - warrants investigation","") | S13: =M13+(10000-ROW())/10000000 -> 80.000999 | T13: =P13+(10000-ROW())/10000000 -> 0.064710611
A14: =Benchmarking!A14 -> Applied Optoelectronics Inc | B14: =Benchmarking!B14 -> aaoi | C14: =Benchmarking!C14 -> Communications | D14: =Benchmarking!D14 -> 311 | E14: =Benchmarking!E14 -> 256 | F14: =Benchmarking!F14 -> 218 | G14: =Benchmarking!G14 -> 785 | H14: =IF(AND(D14>=E14,D14>=F14),"Environmental",IF(AND(E14>=D14,E14>=F14),"Social","Governance")) -> Environmental | I14: =IF(AND(D14<=E14,D14<=F14),"Environmental",IF(AND(E14<=D14,E14<=F14),"Social","Governance")) -> Governance | J14: =D14-E14 -> 55 | K14: =E14-F14 -> 38 | L14: =D14-F14 -> 93 | M14: =MAX(D14:F14)-MIN(D14:F14) -> 93 | N14: =RANK(G14,$G$4:$G$725,1)/COUNT($G$4:$G$725) -> 0.27700831 | O14: =MIN(RANK(D14,$D$4:$D$725,1)/COUNT($D$4:$D$725),RANK(E14,$E$4:$E$725,1)/COUNT($E$4:$E$725),RANK(F14,$F$4:$F$725,1)/COUNT($F$4:$F$725)) -> 0.18559557 | P14: =N14-O14 -> 0.091412742 | Q14: =IF(AND(N14>=0.7,P14>=0.4),"High ESG / weak pillar (analytical flag - not an ESG rating) - warrants investigation","") | S14: =M14+(10000-ROW())/10000000 -> 93.000999 | T14: =P14+(10000-ROW())/10000000 -> 0.092411342
A15: =Benchmarking!A15 -> Aaon Inc | B15: =Benchmarking!B15 -> aaon | C15: =Benchmarking!C15 -> Building | D15: =Benchmarking!D15 -> 500 | E15: =Benchmarking!E15 -> 300 | F15: =Benchmarking!F15 -> 223 | G15: =Benchmarking!G15 -> 1023 | H15: =IF(AND(D15>=E15,D15>=F15),"Environmental",IF(AND(E15>=D15,E15>=F15),"Social","Governance")) -> Environmental | I15: =IF(AND(D15<=E15,D15<=F15),"Environmental",IF(AND(E15<=D15,E15<=F15),"Social","Governance")) -> Governance | J15: =D15-E15 -> 200 | K15: =E15-F15 -> 77 | L15: =D15-F15 -> 277 | M15: =MAX(D15:F15)-MIN(D15:F15) -> 277 | N15: =RANK(G15,$G$4:$G$725,1)/COUNT($G$4:$G$725) -> 0.48753463 | O15: =MIN(RANK(D15,$D$4:$D$725,1)/COUNT($D$4:$D$725),RANK(E15,$E$4:$E$725,1)/COUNT($E$4:$E$725),RANK(F15,$F$4:$F$725,1)/COUNT($F$4:$F$725)) -> 0.2132964 | P15: =N15-O15 -> 0.27423823 | Q15: =IF(AND(N15>=0.7,P15>=0.4),"High ESG / weak pillar (analytical flag - not an ESG rating) - warrants investigation","") | S15: =M15+(10000-ROW())/10000000 -> 277.001 | T15: =P15+(10000-ROW())/10000000 -> 0.27523673
... A725: =Benchmarking!A725 -> HEICO Corp | B725: =Benchmarking!B725 -> hei | C725: =Benchmarking!C725 -> Aerospace & Defense | D725: =Benchmarking!D725 -> 225 | E725: =Benchmarking!E725 -> 203 | F725: =Benchmarking!F725 -> 205 | G725: =Benchmarking!G725 -> 633 | H725: =IF(AND(D725>=E725,D725>=F725),"Environmental",IF(AND(E725>=D725,E725>=F725),"Social","Governance")) -> Environmental | I725: =IF(AND(D725<=E725,D725<=F725),"Environmental",IF(AND(E725<=D725,E725<=F725),"Social","Governance")) -> Social | J725: =D725-E725 -> 22 | K725: =E725-F725 -> -2 | L725: =D725-F725 -> 20 | M725: =MAX(D725:F725)-MIN(D725:F725) -> 22 | N725: =RANK(G725,$G$4:$G$725,1)/COUNT($G$4:$G$725) -> 0.063711911 | O725: =MIN(RANK(D725,$D$4:$D$725,1)/COUNT($D$4:$D$725),RANK(E725,$E$4:$E$725,1)/COUNT($E$4:$E$725),RANK(F725,$F$4:$F$725,1)/COUNT($F$4:$F$725)) -> 0.051246537 | P725: =N725-O725 -> 0.012465374 | Q725: =IF(AND(N725>=0.7,P725>=0.4),"High ESG / weak pillar (analytical flag - not an ESG rating) - warrants investigation","") | S725: =M725+(10000-ROW())/10000000 -> 22.000927 | T725: =P725+(10000-ROW())/10000000 -> 0.013392874

Sheet Rankings
A1: RANKINGS & OUTLIERS
A2: All rankings below are fully formula-driven (LARGE / INDEX / MATCH against the Benchmarking and Pillar Analysis sheets) and will recalculate automatically if the underlying data changes. Ties are broken by original row order.
A4: TOP 15 — OVERALL ESG RANKING
A5: Rank | B5: Company | C5: Ticker | D5: Industry | E5: Total ESG Score
A6: 1 | B6: =INDEX(Benchmarking!$A$4:$A$725,MATCH(LARGE(Benchmarking!$R$4:$R$725,1),Benchmarking!$R$4:$R$725,0)) -> Conocophillips | C6: =INDEX(Benchmarking!$B$4:$B$725,MATCH(LARGE(Benchmarking!$R$4:$R$725,1),Benchmarking!$R$4:$R$725,0)) -> cop | D6: =INDEX(Benchmarking!$C$4:$C$725,MATCH(LARGE(Benchmarking!$R$4:$R$725,1),Benchmarking!$R$4:$R$725,0)) -> Energy | E6: =INDEX(Benchmarking!$G$4:$G$725,MATCH(LARGE(Benchmarking!$R$4:$R$725,1),Benchmarking!$R$4:$R$725,0)) -> 1536
A7: 2 | B7: =INDEX(Benchmarking!$A$4:$A$725,MATCH(LARGE(Benchmarking!$R$4:$R$725,2),Benchmarking!$R$4:$R$725,0)) -> Microsoft Corp | C7: =INDEX(Benchmarking!$B$4:$B$725,MATCH(LARGE(Benchmarking!$R$4:$R$725,2),Benchmarking!$R$4:$R$725,0)) -> msft | D7: =INDEX(Benchmarking!$C$4:$C$725,MATCH(LARGE(Benchmarking!$R$4:$R$725,2),Benchmarking!$R$4:$R$725,0)) -> Technology | E7: =INDEX(Benchmarking!$G$4:$G$725,MATCH(LARGE(Benchmarking!$R$4:$R$725,2),Benchmarking!$R$4:$R$725,0)) -> 1533
A8: 3 | B8: =INDEX(Benchmarking!$A$4:$A$725,MATCH(LARGE(Benchmarking!$R$4:$R$725,3),Benchmarking!$R$4:$R$725,0)) -> Edison International | C8: =INDEX(Benchmarking!$B$4:$B$725,MATCH(LARGE(Benchmarking!$R$4:$R$725,3),Benchmarking!$R$4:$R$725,0)) -> eix | D8: =INDEX(Benchmarking!$C$4:$C$725,MATCH(LARGE(Benchmarking!$R$4:$R$725,3),Benchmarking!$R$4:$R$725,0)) -> Utilities | E8: =INDEX(Benchmarking!$G$4:$G$725,MATCH(LARGE(Benchmarking!$R$4:$R$725,3),Benchmarking!$R$4:$R$725,0)) -> 1528
A9: 4 | B9: =INDEX(Benchmarking!$A$4:$A$725,MATCH(LARGE(Benchmarking!$R$4:$R$725,4),Benchmarking!$R$4:$R$725,0)) -> Airbnb Inc | C9: =INDEX(Benchmarking!$B$4:$B$725,MATCH(LARGE(Benchmarking!$R$4:$R$725,4),Benchmarking!$R$4:$R$725,0)) -> abnb | D9: =INDEX(Benchmarking!$C$4:$C$725,MATCH(LARGE(Benchmarking!$R$4:$R$725,4),Benchmarking!$R$4:$R$725,0)) -> Hotels Restaurants & Leisure | E9: =INDEX(Benchmarking!$G$4:$G$725,MATCH(LARGE(Benchmarking!$R$4:$R$725,4),Benchmarking!$R$4:$R$725,0)) -> 1475
A10: 5 | B10: =INDEX(Benchmarking!$A$4:$A$725,MATCH(LARGE(Benchmarking!$R$4:$R$725,5),Benchmarking!$R$4:$R$725,0)) -> Air Products and Chemicals Inc | C10: =INDEX(Benchmarking!$B$4:$B$725,MATCH(LARGE(Benchmarking!$R$4:$R$725,5),Benchmarking!$R$4:$R$725,0)) -> apd | D10: =INDEX(Benchmarking!$C$4:$C$725,MATCH(LARGE(Benchmarking!$R$4:$R$725,5),Benchmarking!$R$4:$R$725,0)) -> Chemicals | E10: =INDEX(Benchmarking!$G$4:$G$725,MATCH(LARGE(Benchmarking!$R$4:$R$725,5),Benchmarking!$R$4:$R$725,0)) -> 1442
A11: 6 | B11: =INDEX(Benchmarking!$A$4:$A$725,MATCH(LARGE(Benchmarking!$R$4:$R$725,6),Benchmarking!$R$4:$R$725,0)) -> Amazon.com Inc | C11: =INDEX(Benchmarking!$B$4:$B$725,MATCH(LARGE(Benchmarking!$R$4:$R$725,6),Benchmarking!$R$4:$R$725,0)) -> amzn | D11: =INDEX(Benchmarking!$C$4:$C$725,MATCH(LARGE(Benchmarking!$R$4:$R$725,6),Benchmarking!$R$4:$R$725,0)) -> Retail | E11: =INDEX(Benchmarking!$G$4:$G$725,MATCH(LARGE(Benchmarking!$R$4:$R$725,6),Benchmarking!$R$4:$R$725,0)) -> 1433
A12: 7 | B12: =INDEX(Benchmarking!$A$4:$A$725,MATCH(LARGE(Benchmarking!$R$4:$R$725,7),Benchmarking!$R$4:$R$725,0)) -> Newmont Corporation | C12: =INDEX(Benchmarking!$B$4:$B$725,MATCH(LARGE(Benchmarking!$R$4:$R$725,7),Benchmarking!$R$4:$R$725,0)) -> nem | D12: =INDEX(Benchmarking!$C$4:$C$725,MATCH(LARGE(Benchmarking!$R$4:$R$725,7),Benchmarking!$R$4:$R$725,0)) -> Metals & Mining | E12: =INDEX(Benchmarking!$G$4:$G$725,MATCH(LARGE(Benchmarking!$R$4:$R$725,7),Benchmarking!$R$4:$R$725,0)) -> 1419
A13: 8 | B13: =INDEX(Benchmarking!$A$4:$A$725,MATCH(LARGE(Benchmarking!$R$4:$R$725,8),Benchmarking!$R$4:$R$725,0)) -> PepsiCo Inc | C13: =INDEX(Benchmarking!$B$4:$B$725,MATCH(LARGE(Benchmarking!$R$4:$R$725,8),Benchmarking!$R$4:$R$725,0)) -> pep | D13: =INDEX(Benchmarking!$C$4:$C$725,MATCH(LARGE(Benchmarking!$R$4:$R$725,8),Benchmarking!$R$4:$R$725,0)) -> Beverages | E13: =INDEX(Benchmarking!$G$4:$G$725,MATCH(LARGE(Benchmarking!$R$4:$R$725,8),Benchmarking!$R$4:$R$725,0)) -> 1417
A14: 9 | B14: =INDEX(Benchmarking!$A$4:$A$725,MATCH(LARGE(Benchmarking!$R$4:$R$725,9),Benchmarking!$R$4:$R$725,0)) -> Exelon Corp | C14: =INDEX(Benchmarking!$B$4:$B$725,MATCH(LARGE(Benchmarking!$R$4:$R$725,9),Benchmarking!$R$4:$R$725,0)) -> exc | D14: =INDEX(Benchmarking!$C$4:$C$725,MATCH(LARGE(Benchmarking!$R$4:$R$725,9),Benchmarking!$R$4:$R$725,0)) -> Utilities | E14: =INDEX(Benchmarking!$G$4:$G$725,MATCH(LARGE(Benchmarking!$R$4:$R$725,9),Benchmarking!$R$4:$R$725,0)) -> 1413
A15: 10 | B15: =INDEX(Benchmarking!$A$4:$A$725,MATCH(LARGE(Benchmarking!$R$4:$R$725,10),Benchmarking!$R$4:$R$725,0)) -> Pioneer Natural Resources Co | C15: =INDEX(Benchmarking!$B$4:$B$725,MATCH(LARGE(Benchmarking!$R$4:$R$725,10),Benchmarking!$R$4:$R$725,0)) -> pxd | D15: =INDEX(Benchmarking!$C$4:$C$725,MATCH(LARGE(Benchmarking!$R$4:$R$725,10),Benchmarking!$R$4:$R$725,0)) -> Energy | E15: =INDEX(Benchmarking!$G$4:$G$725,MATCH(LARGE(Benchmarking!$R$4:$R$725,10),Benchmarking!$R$4:$R$725,0)) -> 1412
A16: 11 | B16: =INDEX(Benchmarking!$A$4:$A$725,MATCH(LARGE(Benchmarking!$R$4:$R$725,11),Benchmarking!$R$4:$R$725,0)) -> Trane Technologies PLC | C16: =INDEX(Benchmarking!$B$4:$B$725,MATCH(LARGE(Benchmarking!$R$4:$R$725,11),Benchmarking!$R$4:$R$725,0)) -> tt | D16: =INDEX(Benchmarking!$C$4:$C$725,MATCH(LARGE(Benchmarking!$R$4:$R$725,11),Benchmarking!$R$4:$R$725,0)) -> Building | E16: =INDEX(Benchmarking!$G$4:$G$725,MATCH(LARGE(Benchmarking!$R$4:$R$725,11),Benchmarking!$R$4:$R$725,0)) -> 1409
A17: 12 | B17: =INDEX(Benchmarking!$A$4:$A$725,MATCH(LARGE(Benchmarking!$R$4:$R$725,12),Benchmarking!$R$4:$R$725,0)) -> Pinnacle West Capital Corp | C17: =INDEX(Benchmarking!$B$4:$B$725,MATCH(LARGE(Benchmarking!$R$4:$R$725,12),Benchmarking!$R$4:$R$725,0)) -> pnw | D17: =INDEX(Benchmarking!$C$4:$C$725,MATCH(LARGE(Benchmarking!$R$4:$R$725,12),Benchmarking!$R$4:$R$725,0)) -> Utilities | E17: =INDEX(Benchmarking!$G$4:$G$725,MATCH(LARGE(Benchmarking!$R$4:$R$725,12),Benchmarking!$R$4:$R$725,0)) -> 1408
A18: 13 | B18: =INDEX(Benchmarking!$A$4:$A$725,MATCH(LARGE(Benchmarking!$R$4:$R$725,13),Benchmarking!$R$4:$R$725,0)) -> Sempra Energy | C18: =INDEX(Benchmarking!$B$4:$B$725,MATCH(LARGE(Benchmarking!$R$4:$R$725,13),Benchmarking!$R$4:$R$725,0)) -> sre | D18: =INDEX(Benchmarking!$C$4:$C$725,MATCH(LARGE(Benchmarking!$R$4:$R$725,13),Benchmarking!$R$4:$R$725,0)) -> Utilities | E18: =INDEX(Benchmarking!$G$4:$G$725,MATCH(LARGE(Benchmarking!$R$4:$R$725,13),Benchmarking!$R$4:$R$725,0)) -> 1396
A19: 14 | B19: =INDEX(Benchmarking!$A$4:$A$725,MATCH(LARGE(Benchmarking!$R$4:$R$725,14),Benchmarking!$R$4:$R$725,0)) -> Marathon Petroleum Corp | C19: =INDEX(Benchmarking!$B$4:$B$725,MATCH(LARGE(Benchmarking!$R$4:$R$725,14),Benchmarking!$R$4:$R$725,0)) -> mpc | D19: =INDEX(Benchmarking!$C$4:$C$725,MATCH(LARGE(Benchmarking!$R$4:$R$725,14),Benchmarking!$R$4:$R$725,0)) -> Energy | E19: =INDEX(Benchmarking!$G$4:$G$725,MATCH(LARGE(Benchmarking!$R$4:$R$725,14),Benchmarking!$R$4:$R$725,0)) -> 1381
A20: 15 | B20: =INDEX(Benchmarking!$A$4:$A$725,MATCH(LARGE(Benchmarking!$R$4:$R$725,15),Benchmarking!$R$4:$R$725,0)) -> WEC Energy Group Inc | C20: =INDEX(Benchmarking!$B$4:$B$725,MATCH(LARGE(Benchmarking!$R$4:$R$725,15),Benchmarking!$R$4:$R$725,0)) -> wec | D20: =INDEX(Benchmarking!$C$4:$C$725,MATCH(LARGE(Benchmarking!$R$4:$R$725,15),Benchmarking!$R$4:$R$725,0)) -> Utilities | E20: =INDEX(Benchmarking!$G$4:$G$725,MATCH(LARGE(Benchmarking!$R$4:$R$725,15),Benchmarking!$R$4:$R$725,0)) -> 1373
A22: TOP 15 — ENVIRONMENTAL RANKING
A23: Rank | B23: Company | C23: Ticker | D23: Industry | E23: Environmental Score
A24: 1 | B24: =INDEX(Benchmarking!$A$4:$A$725,MATCH(LARGE(Benchmarking!$S$4:$S$725,1),Benchmarking!$S$4:$S$725,0)) -> PepsiCo Inc | C24: =INDEX(Benchmarking!$B$4:$B$725,MATCH(LARGE(Benchmarking!$S$4:$S$725,1),Benchmarking!$S$4:$S$725,0)) -> pep | D24: =INDEX(Benchmarking!$C$4:$C$725,MATCH(LARGE(Benchmarking!$S$4:$S$725,1),Benchmarking!$S$4:$S$725,0)) -> Beverages | E24: =INDEX(Benchmarking!$D$4:$D$725,MATCH(LARGE(Benchmarking!$S$4:$S$725,1),Benchmarking!$S$4:$S$725,0)) -> 719
A25: 2 | B25: =INDEX(Benchmarking!$A$4:$A$725,MATCH(LARGE(Benchmarking!$S$4:$S$725,2),Benchmarking!$S$4:$S$725,0)) -> Microsoft Corp | C25: =INDEX(Benchmarking!$B$4:$B$725,MATCH(LARGE(Benchmarking!$S$4:$S$725,2),Benchmarking!$S$4:$S$725,0)) -> msft | D25: =INDEX(Benchmarking!$C$4:$C$725,MATCH(LARGE(Benchmarking!$S$4:$S$725,2),Benchmarking!$S$4:$S$725,0)) -> Technology | E25: =INDEX(Benchmarking!$D$4:$D$725,MATCH(LARGE(Benchmarking!$S$4:$S$725,2),Benchmarking!$S$4:$S$725,0)) -> 715
A26: 3 | B26: =INDEX(Benchmarking!$A$4:$A$725,MATCH(LARGE(Benchmarking!$S$4:$S$725,3),Benchmarking!$S$4:$S$725,0)) -> Air Products and Chemicals Inc | C26: =INDEX(Benchmarking!$B$4:$B$725,MATCH(LARGE(Benchmarking!$S$4:$S$725,3),Benchmarking!$S$4:$S$725,0)) -> apd | D26: =INDEX(Benchmarking!$C$4:$C$725,MATCH(LARGE(Benchmarking!$S$4:$S$725,3),Benchmarking!$S$4:$S$725,0)) -> Chemicals | E26: =INDEX(Benchmarking!$D$4:$D$725,MATCH(LARGE(Benchmarking!$S$4:$S$725,3),Benchmarking!$S$4:$S$725,0)) -> 700
A27: 4 | B27: =INDEX(Benchmarking!$A$4:$A$725,MATCH(LARGE(Benchmarking!$S$4:$S$725,4),Benchmarking!$S$4:$S$725,0)) -> Edison International | C27: =INDEX(Benchmarking!$B$4:$B$725,MATCH(LARGE(Benchmarking!$S$4:$S$725,4),Benchmarking!$S$4:$S$725,0)) -> eix | D27: =INDEX(Benchmarking!$C$4:$C$725,MATCH(LARGE(Benchmarking!$S$4:$S$725,4),Benchmarking!$S$4:$S$725,0)) -> Utilities | E27: =INDEX(Benchmarking!$D$4:$D$725,MATCH(LARGE(Benchmarking!$S$4:$S$725,4),Benchmarking!$S$4:$S$725,0)) -> 700
A28: 5 | B28: =INDEX(Benchmarking!$A$4:$A$725,MATCH(LARGE(Benchmarking!$S$4:$S$725,5),Benchmarking!$S$4:$S$725,0)) -> Consolidated Edison Inc | C28: =INDEX(Benchmarking!$B$4:$B$725,MATCH(LARGE(Benchmarking!$S$4:$S$725,5),Benchmarking!$S$4:$S$725,0)) -> ed | D28: =INDEX(Benchmarking!$C$4:$C$725,MATCH(LARGE(Benchmarking!$S$4:$S$725,5),Benchmarking!$S$4:$S$725,0)) -> Utilities | E28: =INDEX(Benchmarking!$D$4:$D$725,MATCH(LARGE(Benchmarking!$S$4:$S$725,5),Benchmarking!$S$4:$S$725,0)) -> 700
A29: 6 | B29: =INDEX(Benchmarking!$A$4:$A$725,MATCH(LARGE(Benchmarking!$S$4:$S$725,6),Benchmarking!$S$4:$S$725,0)) -> Marathon Petroleum Corp | C29: =INDEX(Benchmarking!$B$4:$B$725,MATCH(LARGE(Benchmarking!$S$4:$S$725,6),Benchmarking!$S$4:$S$725,0)) -> mpc | D29: =INDEX(Benchmarking!$C$4:$C$725,MATCH(LARGE(Benchmarking!$S$4:$S$725,6),Benchmarking!$S$4:$S$725,0)) -> Energy | E29: =INDEX(Benchmarking!$D$4:$D$725,MATCH(LARGE(Benchmarking!$S$4:$S$725,6),Benchmarking!$S$4:$S$725,0)) -> 700
A30: 7 | B30: =INDEX(Benchmarking!$A$4:$A$725,MATCH(LARGE(Benchmarking!$S$4:$S$725,7),Benchmarking!$S$4:$S$725,0)) -> Pioneer Natural Resources Co | C30: =INDEX(Benchmarking!$B$4:$B$725,MATCH(LARGE(Benchmarking!$S$4:$S$725,7),Benchmarking!$S$4:$S$725,0)) -> pxd | D30: =INDEX(Benchmarking!$C$4:$C$725,MATCH(LARGE(Benchmarking!$S$4:$S$725,7),Benchmarking!$S$4:$S$725,0)) -> Energy | E30: =INDEX(Benchmarking!$D$4:$D$725,MATCH(LARGE(Benchmarking!$S$4:$S$725,7),Benchmarking!$S$4:$S$725,0)) -> 700
A31: 8 | B31: =INDEX(Benchmarking!$A$4:$A$725,MATCH(LARGE(Benchmarking!$S$4:$S$725,8),Benchmarking!$S$4:$S$725,0)) -> Sempra Energy | C31: =INDEX(Benchmarking!$B$4:$B$725,MATCH(LARGE(Benchmarking!$S$4:$S$725,8),Benchmarking!$S$4:$S$725,0)) -> sre | D31: =INDEX(Benchmarking!$C$4:$C$725,MATCH(LARGE(Benchmarking!$S$4:$S$725,8),Benchmarking!$S$4:$S$725,0)) -> Utilities | E31: =INDEX(Benchmarking!$D$4:$D$725,MATCH(LARGE(Benchmarking!$S$4:$S$725,8),Benchmarking!$S$4:$S$725,0)) -> 700
A32: 9 | B32: =INDEX(Benchmarking!$A$4:$A$725,MATCH(LARGE(Benchmarking!$S$4:$S$725,9),Benchmarking!$S$4:$S$725,0)) -> Trane Technologies PLC | C32: =INDEX(Benchmarking!$B$4:$B$725,MATCH(LARGE(Benchmarking!$S$4:$S$725,9),Benchmarking!$S$4:$S$725,0)) -> tt | D32: =INDEX(Benchmarking!$C$4:$C$725,MATCH(LARGE(Benchmarking!$S$4:$S$725,9),Benchmarking!$S$4:$S$725,0)) -> Building | E32: =INDEX(Benchmarking!$D$4:$D$725,MATCH(LARGE(Benchmarking!$S$4:$S$725,9),Benchmarking!$S$4:$S$725,0)) -> 700
A33: 10 | B33: =INDEX(Benchmarking!$A$4:$A$725,MATCH(LARGE(Benchmarking!$S$4:$S$725,10),Benchmarking!$S$4:$S$725,0)) -> Weyerhaeuser Co | C33: =INDEX(Benchmarking!$B$4:$B$725,MATCH(LARGE(Benchmarking!$S$4:$S$725,10),Benchmarking!$S$4:$S$725,0)) -> wy | D33: =INDEX(Benchmarking!$C$4:$C$725,MATCH(LARGE(Benchmarking!$S$4:$S$725,10),Benchmarking!$S$4:$S$725,0)) -> Real Estate | E33: =INDEX(Benchmarking!$D$4:$D$725,MATCH(LARGE(Benchmarking!$S$4:$S$725,10),Benchmarking!$S$4:$S$725,0)) -> 700
A34: 11 | B34: =INDEX(Benchmarking!$A$4:$A$725,MATCH(LARGE(Benchmarking!$S$4:$S$725,11),Benchmarking!$S$4:$S$725,0)) -> Lincoln National Corp | C34: =INDEX(Benchmarking!$B$4:$B$725,MATCH(LARGE(Benchmarking!$S$4:$S$725,11),Benchmarking!$S$4:$S$725,0)) -> lnc | D34: =INDEX(Benchmarking!$C$4:$C$725,MATCH(LARGE(Benchmarking!$S$4:$S$725,11),Benchmarking!$S$4:$S$725,0)) -> Insurance | E34: =INDEX(Benchmarking!$D$4:$D$725,MATCH(LARGE(Benchmarking!$S$4:$S$725,11),Benchmarking!$S$4:$S$725,0)) -> 700
A35: 12 | B35: =INDEX(Benchmarking!$A$4:$A$725,MATCH(LARGE(Benchmarking!$S$4:$S$725,12),Benchmarking!$S$4:$S$725,0)) -> Exelon Corp | C35: =INDEX(Benchmarking!$B$4:$B$725,MATCH(LARGE(Benchmarking!$S$4:$S$725,12),Benchmarking!$S$4:$S$725,0)) -> exc | D35: =INDEX(Benchmarking!$C$4:$C$725,MATCH(LARGE(Benchmarking!$S$4:$S$725,12),Benchmarking!$S$4:$S$725,0)) -> Utilities | E35: =INDEX(Benchmarking!$D$4:$D$725,MATCH(LARGE(Benchmarking!$S$4:$S$725,12),Benchmarking!$S$4:$S$725,0)) -> 694
A36: 13 | B36: =INDEX(Benchmarking!$A$4:$A$725,MATCH(LARGE(Benchmarking!$S$4:$S$725,13),Benchmarking!$S$4:$S$725,0)) -> Conocophillips | C36: =INDEX(Benchmarking!$B$4:$B$725,MATCH(LARGE(Benchmarking!$S$4:$S$725,13),Benchmarking!$S$4:$S$725,0)) -> cop | D36: =INDEX(Benchmarking!$C$4:$C$725,MATCH(LARGE(Benchmarking!$S$4:$S$725,13),Benchmarking!$S$4:$S$725,0)) -> Energy | E36: =INDEX(Benchmarking!$D$4:$D$725,MATCH(LARGE(Benchmarking!$S$4:$S$725,13),Benchmarking!$S$4:$S$725,0)) -> 687
A37: 14 | B37: =INDEX(Benchmarking!$A$4:$A$725,MATCH(LARGE(Benchmarking!$S$4:$S$725,14),Benchmarking!$S$4:$S$725,0)) -> Newmont Corporation | C37: =INDEX(Benchmarking!$B$4:$B$725,MATCH(LARGE(Benchmarking!$S$4:$S$725,14),Benchmarking!$S$4:$S$725,0)) -> nem | D37: =INDEX(Benchmarking!$C$4:$C$725,MATCH(LARGE(Benchmarking!$S$4:$S$725,14),Benchmarking!$S$4:$S$725,0)) -> Metals & Mining | E37: =INDEX(Benchmarking!$D$4:$D$725,MATCH(LARGE(Benchmarking!$S$4:$S$725,14),Benchmarking!$S$4:$S$725,0)) -> 675
A38: 15 | B38: =INDEX(Benchmarking!$A$4:$A$725,MATCH(LARGE(Benchmarking!$S$4:$S$725,15),Benchmarking!$S$4:$S$725,0)) -> Amazon.com Inc | C38: =INDEX(Benchmarking!$B$4:$B$725,MATCH(LARGE(Benchmarking!$S$4:$S$725,15),Benchmarking!$S$4:$S$725,0)) -> amzn | D38: =INDEX(Benchmarking!$C$4:$C$725,MATCH(LARGE(Benchmarking!$S$4:$S$725,15),Benchmarking!$S$4:$S$725,0)) -> Retail | E38: =INDEX(Benchmarking!$D$4:$D$725,MATCH(LARGE(Benchmarking!$S$4:$S$725,15),Benchmarking!$S$4:$S$725,0)) -> 668
A40: TOP 15 — SOCIAL RANKING
A41: Rank | B41: Company | C41: Ticker | D41: Industry | E41: Social Score
A42: 1 | B42: =INDEX(Benchmarking!$A$4:$A$725,MATCH(LARGE(Benchmarking!$T$4:$T$725,1),Benchmarking!$T$4:$T$725,0)) -> CMS Energy Corp | C42: =INDEX(Benchmarking!$B$4:$B$725,MATCH(LARGE(Benchmarking!$T$4:$T$725,1),Benchmarking!$T$4:$T$725,0)) -> cms | D42: =INDEX(Benchmarking!$C$4:$C$725,MATCH(LARGE(Benchmarking!$T$4:$T$725,1),Benchmarking!$T$4:$T$725,0)) -> Utilities | E42: =INDEX(Benchmarking!$E$4:$E$725,MATCH(LARGE(Benchmarking!$T$4:$T$725,1),Benchmarking!$T$4:$T$725,0)) -> 667
A43: 2 | B43: =INDEX(Benchmarking!$A$4:$A$725,MATCH(LARGE(Benchmarking!$T$4:$T$725,2),Benchmarking!$T$4:$T$725,0)) -> Airbnb Inc | C43: =INDEX(Benchmarking!$B$4:$B$725,MATCH(LARGE(Benchmarking!$T$4:$T$725,2),Benchmarking!$T$4:$T$725,0)) -> abnb | D43: =INDEX(Benchmarking!$C$4:$C$725,MATCH(LARGE(Benchmarking!$T$4:$T$725,2),Benchmarking!$T$4:$T$725,0)) -> Hotels Restaurants & Leisure | E43: =INDEX(Benchmarking!$E$4:$E$725,MATCH(LARGE(Benchmarking!$T$4:$T$725,2),Benchmarking!$T$4:$T$725,0)) -> 570
A44: 3 | B44: =INDEX(Benchmarking!$A$4:$A$725,MATCH(LARGE(Benchmarking!$T$4:$T$725,3),Benchmarking!$T$4:$T$725,0)) -> Conocophillips | C44: =INDEX(Benchmarking!$B$4:$B$725,MATCH(LARGE(Benchmarking!$T$4:$T$725,3),Benchmarking!$T$4:$T$725,0)) -> cop | D44: =INDEX(Benchmarking!$C$4:$C$725,MATCH(LARGE(Benchmarking!$T$4:$T$725,3),Benchmarking!$T$4:$T$725,0)) -> Energy | E44: =INDEX(Benchmarking!$E$4:$E$725,MATCH(LARGE(Benchmarking!$T$4:$T$725,3),Benchmarking!$T$4:$T$725,0)) -> 544
A45: 4 | B45: =INDEX(Benchmarking!$A$4:$A$725,MATCH(LARGE(Benchmarking!$T$4:$T$725,4),Benchmarking!$T$4:$T$725,0)) -> Yelp Inc | C45: =INDEX(Benchmarking!$B$4:$B$725,MATCH(LARGE(Benchmarking!$T$4:$T$725,4),Benchmarking!$T$4:$T$725,0)) -> yelp | D45: =INDEX(Benchmarking!$C$4:$C$725,MATCH(LARGE(Benchmarking!$T$4:$T$725,4),Benchmarking!$T$4:$T$725,0)) -> Media | E45: =INDEX(Benchmarking!$E$4:$E$725,MATCH(LARGE(Benchmarking!$T$4:$T$725,4),Benchmarking!$T$4:$T$725,0)) -> 515
A46: 5 | B46: =INDEX(Benchmarking!$A$4:$A$725,MATCH(LARGE(Benchmarking!$T$4:$T$725,5),Benchmarking!$T$4:$T$725,0)) -> Edison International | C46: =INDEX(Benchmarking!$B$4:$B$725,MATCH(LARGE(Benchmarking!$T$4:$T$725,5),Benchmarking!$T$4:$T$725,0)) -> eix | D46: =INDEX(Benchmarking!$C$4:$C$725,MATCH(LARGE(Benchmarking!$T$4:$T$725,5),Benchmarking!$T$4:$T$725,0)) -> Utilities | E46: =INDEX(Benchmarking!$E$4:$E$725,MATCH(LARGE(Benchmarking!$T$4:$T$725,5),Benchmarking!$T$4:$T$725,0)) -> 513
A47: 6 | B47: =INDEX(Benchmarking!$A$4:$A$725,MATCH(LARGE(Benchmarking!$T$4:$T$725,6),Benchmarking!$T$4:$T$725,0)) -> Pinnacle West Capital Corp | C47: =INDEX(Benchmarking!$B$4:$B$725,MATCH(LARGE(Benchmarking!$T$4:$T$725,6),Benchmarking!$T$4:$T$725,0)) -> pnw | D47: =INDEX(Benchmarking!$C$4:$C$725,MATCH(LARGE(Benchmarking!$T$4:$T$725,6),Benchmarking!$T$4:$T$725,0)) -> Utilities | E47: =INDEX(Benchmarking!$E$4:$E$725,MATCH(LARGE(Benchmarking!$T$4:$T$725,6),Benchmarking!$T$4:$T$725,0)) -> 479
A48: 7 | B48: =INDEX(Benchmarking!$A$4:$A$725,MATCH(LARGE(Benchmarking!$T$4:$T$725,7),Benchmarking!$T$4:$T$725,0)) -> Microsoft Corp | C48: =INDEX(Benchmarking!$B$4:$B$725,MATCH(LARGE(Benchmarking!$T$4:$T$725,7),Benchmarking!$T$4:$T$725,0)) -> msft | D48: =INDEX(Benchmarking!$C$4:$C$725,MATCH(LARGE(Benchmarking!$T$4:$T$725,7),Benchmarking!$T$4:$T$725,0)) -> Technology | E48: =INDEX(Benchmarking!$E$4:$E$725,MATCH(LARGE(Benchmarking!$T$4:$T$725,7),Benchmarking!$T$4:$T$725,0)) -> 443
A49: 8 | B49: =INDEX(Benchmarking!$A$4:$A$725,MATCH(LARGE(Benchmarking!$T$4:$T$725,8),Benchmarking!$T$4:$T$725,0)) -> Air Products and Chemicals Inc | C49: =INDEX(Benchmarking!$B$4:$B$725,MATCH(LARGE(Benchmarking!$T$4:$T$725,8),Benchmarking!$T$4:$T$725,0)) -> apd | D49: =INDEX(Benchmarking!$C$4:$C$725,MATCH(LARGE(Benchmarking!$T$4:$T$725,8),Benchmarking!$T$4:$T$725,0)) -> Chemicals | E49: =INDEX(Benchmarking!$E$4:$E$725,MATCH(LARGE(Benchmarking!$T$4:$T$725,8),Benchmarking!$T$4:$T$725,0)) -> 442
A50: 9 | B50: =INDEX(Benchmarking!$A$4:$A$725,MATCH(LARGE(Benchmarking!$T$4:$T$725,9),Benchmarking!$T$4:$T$725,0)) -> WEC Energy Group Inc | C50: =INDEX(Benchmarking!$B$4:$B$725,MATCH(LARGE(Benchmarking!$T$4:$T$725,9),Benchmarking!$T$4:$T$725,0)) -> wec | D50: =INDEX(Benchmarking!$C$4:$C$725,MATCH(LARGE(Benchmarking!$T$4:$T$725,9),Benchmarking!$T$4:$T$725,0)) -> Utilities | E50: =INDEX(Benchmarking!$E$4:$E$725,MATCH(LARGE(Benchmarking!$T$4:$T$725,9),Benchmarking!$T$4:$T$725,0)) -> 438
A51: 10 | B51: =INDEX(Benchmarking!$A$4:$A$725,MATCH(LARGE(Benchmarking!$T$4:$T$725,10),Benchmarking!$T$4:$T$725,0)) -> Old Dominion Freight Line Inc | C51: =INDEX(Benchmarking!$B$4:$B$725,MATCH(LARGE(Benchmarking!$T$4:$T$725,10),Benchmarking!$T$4:$T$725,0)) -> odfl | D51: =INDEX(Benchmarking!$C$4:$C$725,MATCH(LARGE(Benchmarking!$T$4:$T$725,10),Benchmarking!$T$4:$T$725,0)) -> Road & Rail | E51: =INDEX(Benchmarking!$E$4:$E$725,MATCH(LARGE(Benchmarking!$T$4:$T$725,10),Benchmarking!$T$4:$T$725,0)) -> 423
A52: 11 | B52: =INDEX(Benchmarking!$A$4:$A$725,MATCH(LARGE(Benchmarking!$T$4:$T$725,11),Benchmarking!$T$4:$T$725,0)) -> Procter & Gamble Co | C52: =INDEX(Benchmarking!$B$4:$B$725,MATCH(LARGE(Benchmarking!$T$4:$T$725,11),Benchmarking!$T$4:$T$725,0)) -> pg | D52: =INDEX(Benchmarking!$C$4:$C$725,MATCH(LARGE(Benchmarking!$T$4:$T$725,11),Benchmarking!$T$4:$T$725,0)) -> Consumer products | E52: =INDEX(Benchmarking!$E$4:$E$725,MATCH(LARGE(Benchmarking!$T$4:$T$725,11),Benchmarking!$T$4:$T$725,0)) -> 422
A53: 12 | B53: =INDEX(Benchmarking!$A$4:$A$725,MATCH(LARGE(Benchmarking!$T$4:$T$725,12),Benchmarking!$T$4:$T$725,0)) -> Trimble Inc | C53: =INDEX(Benchmarking!$B$4:$B$725,MATCH(LARGE(Benchmarking!$T$4:$T$725,12),Benchmarking!$T$4:$T$725,0)) -> trmb | D53: =INDEX(Benchmarking!$C$4:$C$725,MATCH(LARGE(Benchmarking!$T$4:$T$725,12),Benchmarking!$T$4:$T$725,0)) -> Electrical Equipment | E53: =INDEX(Benchmarking!$E$4:$E$725,MATCH(LARGE(Benchmarking!$T$4:$T$725,12),Benchmarking!$T$4:$T$725,0)) -> 415
A54: 13 | B54: =INDEX(Benchmarking!$A$4:$A$725,MATCH(LARGE(Benchmarking!$T$4:$T$725,13),Benchmarking!$T$4:$T$725,0)) -> Pioneer Natural Resources Co | C54: =INDEX(Benchmarking!$B$4:$B$725,MATCH(LARGE(Benchmarking!$T$4:$T$725,13),Benchmarking!$T$4:$T$725,0)) -> pxd | D54: =INDEX(Benchmarking!$C$4:$C$725,MATCH(LARGE(Benchmarking!$T$4:$T$725,13),Benchmarking!$T$4:$T$725,0)) -> Energy | E54: =INDEX(Benchmarking!$E$4:$E$725,MATCH(LARGE(Benchmarking!$T$4:$T$725,13),Benchmarking!$T$4:$T$725,0)) -> 412
A55: 14 | B55: =INDEX(Benchmarking!$A$4:$A$725,MATCH(LARGE(Benchmarking!$T$4:$T$725,14),Benchmarking!$T$4:$T$725,0)) -> Eversource Energy | C55: =INDEX(Benchmarking!$B$4:$B$725,MATCH(LARGE(Benchmarking!$T$4:$T$725,14),Benchmarking!$T$4:$T$725,0)) -> es | D55: =INDEX(Benchmarking!$C$4:$C$725,MATCH(LARGE(Benchmarking!$T$4:$T$725,14),Benchmarking!$T$4:$T$725,0)) -> Utilities | E55: =INDEX(Benchmarking!$E$4:$E$725,MATCH(LARGE(Benchmarking!$T$4:$T$725,14),Benchmarking!$T$4:$T$725,0)) -> 409
A56: 15 | B56: =INDEX(Benchmarking!$A$4:$A$725,MATCH(LARGE(Benchmarking!$T$4:$T$725,15),Benchmarking!$T$4:$T$725,0)) -> Waste Management Inc | C56: =INDEX(Benchmarking!$B$4:$B$725,MATCH(LARGE(Benchmarking!$T$4:$T$725,15),Benchmarking!$T$4:$T$725,0)) -> wm | D56: =INDEX(Benchmarking!$C$4:$C$725,MATCH(LARGE(Benchmarking!$T$4:$T$725,15),Benchmarking!$T$4:$T$725,0)) -> Commercial Services & Supplies | E56: =INDEX(Benchmarking!$E$4:$E$725,MATCH(LARGE(Benchmarking!$T$4:$T$725,15),Benchmarking!$T$4:$T$725,0)) -> 408
A58: TOP 15 — GOVERNANCE RANKING
A59: Rank | B59: Company | C59: Ticker | D59: Industry | E59: Governance Score
A60: 1 | B60: =INDEX(Benchmarking!$A$4:$A$725,MATCH(LARGE(Benchmarking!$U$4:$U$725,1),Benchmarking!$U$4:$U$725,0)) -> Amphenol Corp | C60: =INDEX(Benchmarking!$B$4:$B$725,MATCH(LARGE(Benchmarking!$U$4:$U$725,1),Benchmarking!$U$4:$U$725,0)) -> aph | D60: =INDEX(Benchmarking!$C$4:$C$725,MATCH(LARGE(Benchmarking!$U$4:$U$725,1),Benchmarking!$U$4:$U$725,0)) -> Electrical Equipment | E60: =INDEX(Benchmarking!$F$4:$F$725,MATCH(LARGE(Benchmarking!$U$4:$U$725,1),Benchmarking!$U$4:$U$725,0)) -> 475
A61: 2 | B61: =INDEX(Benchmarking!$A$4:$A$725,MATCH(LARGE(Benchmarking!$U$4:$U$725,2),Benchmarking!$U$4:$U$725,0)) -> Amazon.com Inc | C61: =INDEX(Benchmarking!$B$4:$B$725,MATCH(LARGE(Benchmarking!$U$4:$U$725,2),Benchmarking!$U$4:$U$725,0)) -> amzn | D61: =INDEX(Benchmarking!$C$4:$C$725,MATCH(LARGE(Benchmarking!$U$4:$U$725,2),Benchmarking!$U$4:$U$725,0)) -> Retail | E61: =INDEX(Benchmarking!$F$4:$F$725,MATCH(LARGE(Benchmarking!$U$4:$U$725,2),Benchmarking!$U$4:$U$725,0)) -> 460
A62: 3 | B62: =INDEX(Benchmarking!$A$4:$A$725,MATCH(LARGE(Benchmarking!$U$4:$U$725,3),Benchmarking!$U$4:$U$725,0)) -> Akoustis Technologies Inc | C62: =INDEX(Benchmarking!$B$4:$B$725,MATCH(LARGE(Benchmarking!$U$4:$U$725,3),Benchmarking!$U$4:$U$725,0)) -> akts | D62: =INDEX(Benchmarking!$C$4:$C$725,MATCH(LARGE(Benchmarking!$U$4:$U$725,3),Benchmarking!$U$4:$U$725,0)) -> Electrical Equipment | E62: =INDEX(Benchmarking!$F$4:$F$725,MATCH(LARGE(Benchmarking!$U$4:$U$725,3),Benchmarking!$U$4:$U$725,0)) -> 428
A63: 4 | B63: =INDEX(Benchmarking!$A$4:$A$725,MATCH(LARGE(Benchmarking!$U$4:$U$725,4),Benchmarking!$U$4:$U$725,0)) -> Airbnb Inc | C63: =INDEX(Benchmarking!$B$4:$B$725,MATCH(LARGE(Benchmarking!$U$4:$U$725,4),Benchmarking!$U$4:$U$725,0)) -> abnb | D63: =INDEX(Benchmarking!$C$4:$C$725,MATCH(LARGE(Benchmarking!$U$4:$U$725,4),Benchmarking!$U$4:$U$725,0)) -> Hotels Restaurants & Leisure | E63: =INDEX(Benchmarking!$F$4:$F$725,MATCH(LARGE(Benchmarking!$U$4:$U$725,4),Benchmarking!$U$4:$U$725,0)) -> 400
A64: 5 | B64: =INDEX(Benchmarking!$A$4:$A$725,MATCH(LARGE(Benchmarking!$U$4:$U$725,5),Benchmarking!$U$4:$U$725,0)) -> Raytheon Technologies Corp | C64: =INDEX(Benchmarking!$B$4:$B$725,MATCH(LARGE(Benchmarking!$U$4:$U$725,5),Benchmarking!$U$4:$U$725,0)) -> rtx | D64: =INDEX(Benchmarking!$C$4:$C$725,MATCH(LARGE(Benchmarking!$U$4:$U$725,5),Benchmarking!$U$4:$U$725,0)) -> Aerospace & Defense | E64: =INDEX(Benchmarking!$F$4:$F$725,MATCH(LARGE(Benchmarking!$U$4:$U$725,5),Benchmarking!$U$4:$U$725,0)) -> 400
A65: 6 | B65: =INDEX(Benchmarking!$A$4:$A$725,MATCH(LARGE(Benchmarking!$U$4:$U$725,6),Benchmarking!$U$4:$U$725,0)) -> Danaher Corp | C65: =INDEX(Benchmarking!$B$4:$B$725,MATCH(LARGE(Benchmarking!$U$4:$U$725,6),Benchmarking!$U$4:$U$725,0)) -> dhr | D65: =INDEX(Benchmarking!$C$4:$C$725,MATCH(LARGE(Benchmarking!$U$4:$U$725,6),Benchmarking!$U$4:$U$725,0)) -> Life Sciences Tools & Services | E65: =INDEX(Benchmarking!$F$4:$F$725,MATCH(LARGE(Benchmarking!$U$4:$U$725,6),Benchmarking!$U$4:$U$725,0)) -> 385
A66: 7 | B66: =INDEX(Benchmarking!$A$4:$A$725,MATCH(LARGE(Benchmarking!$U$4:$U$725,7),Benchmarking!$U$4:$U$725,0)) -> Microsoft Corp | C66: =INDEX(Benchmarking!$B$4:$B$725,MATCH(LARGE(Benchmarking!$U$4:$U$725,7),Benchmarking!$U$4:$U$725,0)) -> msft | D66: =INDEX(Benchmarking!$C$4:$C$725,MATCH(LARGE(Benchmarking!$U$4:$U$725,7),Benchmarking!$U$4:$U$725,0)) -> Technology | E66: =INDEX(Benchmarking!$F$4:$F$725,MATCH(LARGE(Benchmarking!$U$4:$U$725,7),Benchmarking!$U$4:$U$725,0)) -> 375
A67: 8 | B67: =INDEX(Benchmarking!$A$4:$A$725,MATCH(LARGE(Benchmarking!$U$4:$U$725,8),Benchmarking!$U$4:$U$725,0)) -> AES Corp | C67: =INDEX(Benchmarking!$B$4:$B$725,MATCH(LARGE(Benchmarking!$U$4:$U$725,8),Benchmarking!$U$4:$U$725,0)) -> aes | D67: =INDEX(Benchmarking!$C$4:$C$725,MATCH(LARGE(Benchmarking!$U$4:$U$725,8),Benchmarking!$U$4:$U$725,0)) -> Utilities | E67: =INDEX(Benchmarking!$F$4:$F$725,MATCH(LARGE(Benchmarking!$U$4:$U$725,8),Benchmarking!$U$4:$U$725,0)) -> 370
A68: 9 | B68: =INDEX(Benchmarking!$A$4:$A$725,MATCH(LARGE(Benchmarking!$U$4:$U$725,9),Benchmarking!$U$4:$U$725,0)) -> Regency Centers Corp | C68: =INDEX(Benchmarking!$B$4:$B$725,MATCH(LARGE(Benchmarking!$U$4:$U$725,9),Benchmarking!$U$4:$U$725,0)) -> reg | D68: =INDEX(Benchmarking!$C$4:$C$725,MATCH(LARGE(Benchmarking!$U$4:$U$725,9),Benchmarking!$U$4:$U$725,0)) -> Real Estate | E68: =INDEX(Benchmarking!$F$4:$F$725,MATCH(LARGE(Benchmarking!$U$4:$U$725,9),Benchmarking!$U$4:$U$725,0)) -> 365
A69: 10 | B69: =INDEX(Benchmarking!$A$4:$A$725,MATCH(LARGE(Benchmarking!$U$4:$U$725,10),Benchmarking!$U$4:$U$725,0)) -> General Mills Inc | C69: =INDEX(Benchmarking!$B$4:$B$725,MATCH(LARGE(Benchmarking!$U$4:$U$725,10),Benchmarking!$U$4:$U$725,0)) -> gis | D69: =INDEX(Benchmarking!$C$4:$C$725,MATCH(LARGE(Benchmarking!$U$4:$U$725,10),Benchmarking!$U$4:$U$725,0)) -> Food Products | E69: =INDEX(Benchmarking!$F$4:$F$725,MATCH(LARGE(Benchmarking!$U$4:$U$725,10),Benchmarking!$U$4:$U$725,0)) -> 365
A70: 11 | B70: =INDEX(Benchmarking!$A$4:$A$725,MATCH(LARGE(Benchmarking!$U$4:$U$725,11),Benchmarking!$U$4:$U$725,0)) -> UTStarcom Holdings Corp | C70: =INDEX(Benchmarking!$B$4:$B$725,MATCH(LARGE(Benchmarking!$U$4:$U$725,11),Benchmarking!$U$4:$U$725,0)) -> utsi | D70: =INDEX(Benchmarking!$C$4:$C$725,MATCH(LARGE(Benchmarking!$U$4:$U$725,11),Benchmarking!$U$4:$U$725,0)) -> Communications | E70: =INDEX(Benchmarking!$F$4:$F$725,MATCH(LARGE(Benchmarking!$U$4:$U$725,11),Benchmarking!$U$4:$U$725,0)) -> 365
A71: 12 | B71: =INDEX(Benchmarking!$A$4:$A$725,MATCH(LARGE(Benchmarking!$U$4:$U$725,12),Benchmarking!$U$4:$U$725,0)) -> Biogen Inc | C71: =INDEX(Benchmarking!$B$4:$B$725,MATCH(LARGE(Benchmarking!$U$4:$U$725,12),Benchmarking!$U$4:$U$725,0)) -> biib | D71: =INDEX(Benchmarking!$C$4:$C$725,MATCH(LARGE(Benchmarking!$U$4:$U$725,12),Benchmarking!$U$4:$U$725,0)) -> Biotechnology | E71: =INDEX(Benchmarking!$F$4:$F$725,MATCH(LARGE(Benchmarking!$U$4:$U$725,12),Benchmarking!$U$4:$U$725,0)) -> 364
A72: 13 | B72: =INDEX(Benchmarking!$A$4:$A$725,MATCH(LARGE(Benchmarking!$U$4:$U$725,13),Benchmarking!$U$4:$U$725,0)) -> PepsiCo Inc | C72: =INDEX(Benchmarking!$B$4:$B$725,MATCH(LARGE(Benchmarking!$U$4:$U$725,13),Benchmarking!$U$4:$U$725,0)) -> pep | D72: =INDEX(Benchmarking!$C$4:$C$725,MATCH(LARGE(Benchmarking!$U$4:$U$725,13),Benchmarking!$U$4:$U$725,0)) -> Beverages | E72: =INDEX(Benchmarking!$F$4:$F$725,MATCH(LARGE(Benchmarking!$U$4:$U$725,13),Benchmarking!$U$4:$U$725,0)) -> 358
A73: 14 | B73: =INDEX(Benchmarking!$A$4:$A$725,MATCH(LARGE(Benchmarking!$U$4:$U$725,14),Benchmarking!$U$4:$U$725,0)) -> Alphabet Inc | C73: =INDEX(Benchmarking!$B$4:$B$725,MATCH(LARGE(Benchmarking!$U$4:$U$725,14),Benchmarking!$U$4:$U$725,0)) -> googl | D73: =INDEX(Benchmarking!$C$4:$C$725,MATCH(LARGE(Benchmarking!$U$4:$U$725,14),Benchmarking!$U$4:$U$725,0)) -> Media | E73: =INDEX(Benchmarking!$F$4:$F$725,MATCH(LARGE(Benchmarking!$U$4:$U$725,14),Benchmarking!$U$4:$U$725,0)) -> 355
A74: 15 | B74: =INDEX(Benchmarking!$A$4:$A$725,MATCH(LARGE(Benchmarking!$U$4:$U$725,15),Benchmarking!$U$4:$U$725,0)) -> ONEOK Inc | C74: =INDEX(Benchmarking!$B$4:$B$725,MATCH(LARGE(Benchmarking!$U$4:$U$725,15),Benchmarking!$U$4:$U$725,0)) -> oke | D74: =INDEX(Benchmarking!$C$4:$C$725,MATCH(LARGE(Benchmarking!$U$4:$U$725,15),Benchmarking!$U$4:$U$725,0)) -> Energy | E74: =INDEX(Benchmarking!$F$4:$F$725,MATCH(LARGE(Benchmarking!$U$4:$U$725,15),Benchmarking!$U$4:$U$725,0)) -> 355
A76: INDUSTRY RANKING — ALL 48 GROUPS, BY AVERAGE TOTAL ESG SCORE
A77: Rank | B77: Industry | C77: Company Count | D77: Avg Total ESG | E77: Sample Size
A78: 1 | B78: =INDEX('Industry Stats'!$A$2:$A$46,MATCH(LARGE('Industry Stats'!$J$2:$J$46,1),'Industry Stats'!$J$2:$J$46,0)) -> Utilities | C78: =INDEX('Industry Stats'!$B$2:$B$46,MATCH(LARGE('Industry Stats'!$J$2:$J$46,1),'Industry Stats'!$J$2:$J$46,0)) -> 30 | D78: =INDEX('Industry Stats'!$F$2:$F$46,MATCH(LARGE('Industry Stats'!$J$2:$J$46,1),'Industry Stats'!$J$2:$J$46,0)) -> 1190.6333 | E78: =INDEX('Industry Stats'!$I$2:$I$46,MATCH(LARGE('Industry Stats'!$J$2:$J$46,1),'Industry Stats'!$J$2:$J$46,0)) -> Large sample
A79: 2 | B79: =INDEX('Industry Stats'!$A$2:$A$46,MATCH(LARGE('Industry Stats'!$J$2:$J$46,2),'Industry Stats'!$J$2:$J$46,0)) -> Tobacco | C79: =INDEX('Industry Stats'!$B$2:$B$46,MATCH(LARGE('Industry Stats'!$J$2:$J$46,2),'Industry Stats'!$J$2:$J$46,0)) -> 2 | D79: =INDEX('Industry Stats'!$F$2:$F$46,MATCH(LARGE('Industry Stats'!$J$2:$J$46,2),'Industry Stats'!$J$2:$J$46,0)) -> 1165 | E79: =INDEX('Industry Stats'!$I$2:$I$46,MATCH(LARGE('Industry Stats'!$J$2:$J$46,2),'Industry Stats'!$J$2:$J$46,0)) -> Small sample
A80: 3 | B80: =INDEX('Industry Stats'!$A$2:$A$46,MATCH(LARGE('Industry Stats'!$J$2:$J$46,3),'Industry Stats'!$J$2:$J$46,0)) -> Industrial Conglomerates | C80: =INDEX('Industry Stats'!$B$2:$B$46,MATCH(LARGE('Industry Stats'!$J$2:$J$46,3),'Industry Stats'!$J$2:$J$46,0)) -> 3 | D80: =INDEX('Industry Stats'!$F$2:$F$46,MATCH(LARGE('Industry Stats'!$J$2:$J$46,3),'Industry Stats'!$J$2:$J$46,0)) -> 1157 | E80: =INDEX('Industry Stats'!$I$2:$I$46,MATCH(LARGE('Industry Stats'!$J$2:$J$46,3),'Industry Stats'!$J$2:$J$46,0)) -> Small sample
A81: 4 | B81: =INDEX('Industry Stats'!$A$2:$A$46,MATCH(LARGE('Industry Stats'!$J$2:$J$46,4),'Industry Stats'!$J$2:$J$46,0)) -> Packaging | C81: =INDEX('Industry Stats'!$B$2:$B$46,MATCH(LARGE('Industry Stats'!$J$2:$J$46,4),'Industry Stats'!$J$2:$J$46,0)) -> 4 | D81: =INDEX('Industry Stats'!$F$2:$F$46,MATCH(LARGE('Industry Stats'!$J$2:$J$46,4),'Industry Stats'!$J$2:$J$46,0)) -> 1156 | E81: =INDEX('Industry Stats'!$I$2:$I$46,MATCH(LARGE('Industry Stats'!$J$2:$J$46,4),'Industry Stats'!$J$2:$J$46,0)) -> Small sample
A82: 5 | B82: =INDEX('Industry Stats'!$A$2:$A$46,MATCH(LARGE('Industry Stats'!$J$2:$J$46,5),'Industry Stats'!$J$2:$J$46,0)) -> Food Products | C82: =INDEX('Industry Stats'!$B$2:$B$46,MATCH(LARGE('Industry Stats'!$J$2:$J$46,5),'Industry Stats'!$J$2:$J$46,0)) -> 14 | D82: =INDEX('Industry Stats'!$F$2:$F$46,MATCH(LARGE('Industry Stats'!$J$2:$J$46,5),'Industry Stats'!$J$2:$J$46,0)) -> 1131.0714 | E82: =INDEX('Industry Stats'!$I$2:$I$46,MATCH(LARGE('Industry Stats'!$J$2:$J$46,5),'Industry Stats'!$J$2:$J$46,0)) -> Medium sample
A83: 6 | B83: =INDEX('Industry Stats'!$A$2:$A$46,MATCH(LARGE('Industry Stats'!$J$2:$J$46,6),'Industry Stats'!$J$2:$J$46,0)) -> Energy | C83: =INDEX('Industry Stats'!$B$2:$B$46,MATCH(LARGE('Industry Stats'!$J$2:$J$46,6),'Industry Stats'!$J$2:$J$46,0)) -> 21 | D83: =INDEX('Industry Stats'!$F$2:$F$46,MATCH(LARGE('Industry Stats'!$J$2:$J$46,6),'Industry Stats'!$J$2:$J$46,0)) -> 1117.7619 | E83: =INDEX('Industry Stats'!$I$2:$I$46,MATCH(LARGE('Industry Stats'!$J$2:$J$46,6),'Industry Stats'!$J$2:$J$46,0)) -> Large sample
A84: 7 | B84: =INDEX('Industry Stats'!$A$2:$A$46,MATCH(LARGE('Industry Stats'!$J$2:$J$46,7),'Industry Stats'!$J$2:$J$46,0)) -> Distributors | C84: =INDEX('Industry Stats'!$B$2:$B$46,MATCH(LARGE('Industry Stats'!$J$2:$J$46,7),'Industry Stats'!$J$2:$J$46,0)) -> 3 | D84: =INDEX('Industry Stats'!$F$2:$F$46,MATCH(LARGE('Industry Stats'!$J$2:$J$46,7),'Industry Stats'!$J$2:$J$46,0)) -> 1109.6667 | E84: =INDEX('Industry Stats'!$I$2:$I$46,MATCH(LARGE('Industry Stats'!$J$2:$J$46,7),'Industry Stats'!$J$2:$J$46,0)) -> Small sample
A85: 8 | B85: =INDEX('Industry Stats'!$A$2:$A$46,MATCH(LARGE('Industry Stats'!$J$2:$J$46,8),'Industry Stats'!$J$2:$J$46,0)) -> Construction | C85: =INDEX('Industry Stats'!$B$2:$B$46,MATCH(LARGE('Industry Stats'!$J$2:$J$46,8),'Industry Stats'!$J$2:$J$46,0)) -> 6 | D85: =INDEX('Industry Stats'!$F$2:$F$46,MATCH(LARGE('Industry Stats'!$J$2:$J$46,8),'Industry Stats'!$J$2:$J$46,0)) -> 1082.6667 | E85: =INDEX('Industry Stats'!$I$2:$I$46,MATCH(LARGE('Industry Stats'!$J$2:$J$46,8),'Industry Stats'!$J$2:$J$46,0)) -> Small sample
A86: 9 | B86: =INDEX('Industry Stats'!$A$2:$A$46,MATCH(LARGE('Industry Stats'!$J$2:$J$46,9),'Industry Stats'!$J$2:$J$46,0)) -> Road & Rail | C86: =INDEX('Industry Stats'!$B$2:$B$46,MATCH(LARGE('Industry Stats'!$J$2:$J$46,9),'Industry Stats'!$J$2:$J$46,0)) -> 6 | D86: =INDEX('Industry Stats'!$F$2:$F$46,MATCH(LARGE('Industry Stats'!$J$2:$J$46,9),'Industry Stats'!$J$2:$J$46,0)) -> 1076.3333 | E86: =INDEX('Industry Stats'!$I$2:$I$46,MATCH(LARGE('Industry Stats'!$J$2:$J$46,9),'Industry Stats'!$J$2:$J$46,0)) -> Small sample
A87: 10 | B87: =INDEX('Industry Stats'!$A$2:$A$46,MATCH(LARGE('Industry Stats'!$J$2:$J$46,10),'Industry Stats'!$J$2:$J$46,0)) -> Building | C87: =INDEX('Industry Stats'!$B$2:$B$46,MATCH(LARGE('Industry Stats'!$J$2:$J$46,10),'Industry Stats'!$J$2:$J$46,0)) -> 10 | D87: =INDEX('Industry Stats'!$F$2:$F$46,MATCH(LARGE('Industry Stats'!$J$2:$J$46,10),'Industry Stats'!$J$2:$J$46,0)) -> 1074.2 | E87: =INDEX('Industry Stats'!$I$2:$I$46,MATCH(LARGE('Industry Stats'!$J$2:$J$46,10),'Industry Stats'!$J$2:$J$46,0)) -> Medium sample
A88: 11 | B88: =INDEX('Industry Stats'!$A$2:$A$46,MATCH(LARGE('Industry Stats'!$J$2:$J$46,11),'Industry Stats'!$J$2:$J$46,0)) -> Beverages | C88: =INDEX('Industry Stats'!$B$2:$B$46,MATCH(LARGE('Industry Stats'!$J$2:$J$46,11),'Industry Stats'!$J$2:$J$46,0)) -> 4 | D88: =INDEX('Industry Stats'!$F$2:$F$46,MATCH(LARGE('Industry Stats'!$J$2:$J$46,11),'Industry Stats'!$J$2:$J$46,0)) -> 1061 | E88: =INDEX('Industry Stats'!$I$2:$I$46,MATCH(LARGE('Industry Stats'!$J$2:$J$46,11),'Industry Stats'!$J$2:$J$46,0)) -> Small sample
A89: 12 | B89: =INDEX('Industry Stats'!$A$2:$A$46,MATCH(LARGE('Industry Stats'!$J$2:$J$46,12),'Industry Stats'!$J$2:$J$46,0)) -> Chemicals | C89: =INDEX('Industry Stats'!$B$2:$B$46,MATCH(LARGE('Industry Stats'!$J$2:$J$46,12),'Industry Stats'!$J$2:$J$46,0)) -> 19 | D89: =INDEX('Industry Stats'!$F$2:$F$46,MATCH(LARGE('Industry Stats'!$J$2:$J$46,12),'Industry Stats'!$J$2:$J$46,0)) -> 1058.8947 | E89: =INDEX('Industry Stats'!$I$2:$I$46,MATCH(LARGE('Industry Stats'!$J$2:$J$46,12),'Industry Stats'!$J$2:$J$46,0)) -> Medium sample
A90: 13 | B90: =INDEX('Industry Stats'!$A$2:$A$46,MATCH(LARGE('Industry Stats'!$J$2:$J$46,13),'Industry Stats'!$J$2:$J$46,0)) -> Aerospace & Defense | C90: =INDEX('Industry Stats'!$B$2:$B$46,MATCH(LARGE('Industry Stats'!$J$2:$J$46,13),'Industry Stats'!$J$2:$J$46,0)) -> 11 | D90: =INDEX('Industry Stats'!$F$2:$F$46,MATCH(LARGE('Industry Stats'!$J$2:$J$46,13),'Industry Stats'!$J$2:$J$46,0)) -> 1048.1818 | E90: =INDEX('Industry Stats'!$I$2:$I$46,MATCH(LARGE('Industry Stats'!$J$2:$J$46,13),'Industry Stats'!$J$2:$J$46,0)) -> Medium sample
A91: 14 | B91: =INDEX('Industry Stats'!$A$2:$A$46,MATCH(LARGE('Industry Stats'!$J$2:$J$46,14),'Industry Stats'!$J$2:$J$46,0)) -> Machinery | C91: =INDEX('Industry Stats'!$B$2:$B$46,MATCH(LARGE('Industry Stats'!$J$2:$J$46,14),'Industry Stats'!$J$2:$J$46,0)) -> 21 | D91: =INDEX('Industry Stats'!$F$2:$F$46,MATCH(LARGE('Industry Stats'!$J$2:$J$46,14),'Industry Stats'!$J$2:$J$46,0)) -> 1048.0476 | E91: =INDEX('Industry Stats'!$I$2:$I$46,MATCH(LARGE('Industry Stats'!$J$2:$J$46,14),'Industry Stats'!$J$2:$J$46,0)) -> Large sample
A92: 15 | B92: =INDEX('Industry Stats'!$A$2:$A$46,MATCH(LARGE('Industry Stats'!$J$2:$J$46,15),'Industry Stats'!$J$2:$J$46,0)) -> Professional Services | C92: =INDEX('Industry Stats'!$B$2:$B$46,MATCH(LARGE('Industry Stats'!$J$2:$J$46,15),'Industry Stats'!$J$2:$J$46,0)) -> 7 | D92: =INDEX('Industry Stats'!$F$2:$F$46,MATCH(LARGE('Industry Stats'!$J$2:$J$46,15),'Industry Stats'!$J$2:$J$46,0)) -> 1047.8571 | E92: =INDEX('Industry Stats'!$I$2:$I$46,MATCH(LARGE('Industry Stats'!$J$2:$J$46,15),'Industry Stats'!$J$2:$J$46,0)) -> Small sample
A93: 16 | B93: =INDEX('Industry Stats'!$A$2:$A$46,MATCH(LARGE('Industry Stats'!$J$2:$J$46,16),'Industry Stats'!$J$2:$J$46,0)) -> Technology | C93: =INDEX('Industry Stats'!$B$2:$B$46,MATCH(LARGE('Industry Stats'!$J$2:$J$46,16),'Industry Stats'!$J$2:$J$46,0)) -> 63 | D93: =INDEX('Industry Stats'!$F$2:$F$46,MATCH(LARGE('Industry Stats'!$J$2:$J$46,16),'Industry Stats'!$J$2:$J$46,0)) -> 1031.3175 | E93: =INDEX('Industry Stats'!$I$2:$I$46,MATCH(LARGE('Industry Stats'!$J$2:$J$46,16),'Industry Stats'!$J$2:$J$46,0)) -> Large sample
A94: 17 | B94: =INDEX('Industry Stats'!$A$2:$A$46,MATCH(LARGE('Industry Stats'!$J$2:$J$46,17),'Industry Stats'!$J$2:$J$46,0)) -> Semiconductors | C94: =INDEX('Industry Stats'!$B$2:$B$46,MATCH(LARGE('Industry Stats'!$J$2:$J$46,17),'Industry Stats'!$J$2:$J$46,0)) -> 24 | D94: =INDEX('Industry Stats'!$F$2:$F$46,MATCH(LARGE('Industry Stats'!$J$2:$J$46,17),'Industry Stats'!$J$2:$J$46,0)) -> 1030.5833 | E94: =INDEX('Industry Stats'!$I$2:$I$46,MATCH(LARGE('Industry Stats'!$J$2:$J$46,17),'Industry Stats'!$J$2:$J$46,0)) -> Large sample
A95: 18 | B95: =INDEX('Industry Stats'!$A$2:$A$46,MATCH(LARGE('Industry Stats'!$J$2:$J$46,18),'Industry Stats'!$J$2:$J$46,0)) -> Logistics & Transportation | C95: =INDEX('Industry Stats'!$B$2:$B$46,MATCH(LARGE('Industry Stats'!$J$2:$J$46,18),'Industry Stats'!$J$2:$J$46,0)) -> 6 | D95: =INDEX('Industry Stats'!$F$2:$F$46,MATCH(LARGE('Industry Stats'!$J$2:$J$46,18),'Industry Stats'!$J$2:$J$46,0)) -> 1025.1667 | E95: =INDEX('Industry Stats'!$I$2:$I$46,MATCH(LARGE('Industry Stats'!$J$2:$J$46,18),'Industry Stats'!$J$2:$J$46,0)) -> Small sample
A96: 19 | B96: =INDEX('Industry Stats'!$A$2:$A$46,MATCH(LARGE('Industry Stats'!$J$2:$J$46,19),'Industry Stats'!$J$2:$J$46,0)) -> Insurance | C96: =INDEX('Industry Stats'!$B$2:$B$46,MATCH(LARGE('Industry Stats'!$J$2:$J$46,19),'Industry Stats'!$J$2:$J$46,0)) -> 27 | D96: =INDEX('Industry Stats'!$F$2:$F$46,MATCH(LARGE('Industry Stats'!$J$2:$J$46,19),'Industry Stats'!$J$2:$J$46,0)) -> 1012.3704 | E96: =INDEX('Industry Stats'!$I$2:$I$46,MATCH(LARGE('Industry Stats'!$J$2:$J$46,19),'Industry Stats'!$J$2:$J$46,0)) -> Large sample
A97: 20 | B97: =INDEX('Industry Stats'!$A$2:$A$46,MATCH(LARGE('Industry Stats'!$J$2:$J$46,20),'Industry Stats'!$J$2:$J$46,0)) -> Real Estate | C97: =INDEX('Industry Stats'!$B$2:$B$46,MATCH(LARGE('Industry Stats'!$J$2:$J$46,20),'Industry Stats'!$J$2:$J$46,0)) -> 36 | D97: =INDEX('Industry Stats'!$F$2:$F$46,MATCH(LARGE('Industry Stats'!$J$2:$J$46,20),'Industry Stats'!$J$2:$J$46,0)) -> 995.94444 | E97: =INDEX('Industry Stats'!$I$2:$I$46,MATCH(LARGE('Industry Stats'!$J$2:$J$46,20),'Industry Stats'!$J$2:$J$46,0)) -> Large sample
A98: 21 | B98: =INDEX('Industry Stats'!$A$2:$A$46,MATCH(LARGE('Industry Stats'!$J$2:$J$46,21),'Industry Stats'!$J$2:$J$46,0)) -> Commercial Services & Supplies | C98: =INDEX('Industry Stats'!$B$2:$B$46,MATCH(LARGE('Industry Stats'!$J$2:$J$46,21),'Industry Stats'!$J$2:$J$46,0)) -> 7 | D98: =INDEX('Industry Stats'!$F$2:$F$46,MATCH(LARGE('Industry Stats'!$J$2:$J$46,21),'Industry Stats'!$J$2:$J$46,0)) -> 995.85714 | E98: =INDEX('Industry Stats'!$I$2:$I$46,MATCH(LARGE('Industry Stats'!$J$2:$J$46,21),'Industry Stats'!$J$2:$J$46,0)) -> Small sample
A99: 22 | B99: =INDEX('Industry Stats'!$A$2:$A$46,MATCH(LARGE('Industry Stats'!$J$2:$J$46,22),'Industry Stats'!$J$2:$J$46,0)) -> Life Sciences Tools & Services | C99: =INDEX('Industry Stats'!$B$2:$B$46,MATCH(LARGE('Industry Stats'!$J$2:$J$46,22),'Industry Stats'!$J$2:$J$46,0)) -> 16 | D99: =INDEX('Industry Stats'!$F$2:$F$46,MATCH(LARGE('Industry Stats'!$J$2:$J$46,22),'Industry Stats'!$J$2:$J$46,0)) -> 993.125 | E99: =INDEX('Industry Stats'!$I$2:$I$46,MATCH(LARGE('Industry Stats'!$J$2:$J$46,22),'Industry Stats'!$J$2:$J$46,0)) -> Medium sample
A100: 23 | B100: =INDEX('Industry Stats'!$A$2:$A$46,MATCH(LARGE('Industry Stats'!$J$2:$J$46,23),'Industry Stats'!$J$2:$J$46,0)) -> Metals & Mining | C100: =INDEX('Industry Stats'!$B$2:$B$46,MATCH(LARGE('Industry Stats'!$J$2:$J$46,23),'Industry Stats'!$J$2:$J$46,0)) -> 10 | D100: =INDEX('Industry Stats'!$F$2:$F$46,MATCH(LARGE('Industry Stats'!$J$2:$J$46,23),'Industry Stats'!$J$2:$J$46,0)) -> 987 | E100: =INDEX('Industry Stats'!$I$2:$I$46,MATCH(LARGE('Industry Stats'!$J$2:$J$46,23),'Industry Stats'!$J$2:$J$46,0)) -> Medium sample
A101: 24 | B101: =INDEX('Industry Stats'!$A$2:$A$46,MATCH(LARGE('Industry Stats'!$J$2:$J$46,24),'Industry Stats'!$J$2:$J$46,0)) -> Consumer products | C101: =INDEX('Industry Stats'!$B$2:$B$46,MATCH(LARGE('Industry Stats'!$J$2:$J$46,24),'Industry Stats'!$J$2:$J$46,0)) -> 20 | D101: =INDEX('Industry Stats'!$F$2:$F$46,MATCH(LARGE('Industry Stats'!$J$2:$J$46,24),'Industry Stats'!$J$2:$J$46,0)) -> 945.55 | E101: =INDEX('Industry Stats'!$I$2:$I$46,MATCH(LARGE('Industry Stats'!$J$2:$J$46,24),'Industry Stats'!$J$2:$J$46,0)) -> Large sample
A102: 25 | B102: =INDEX('Industry Stats'!$A$2:$A$46,MATCH(LARGE('Industry Stats'!$J$2:$J$46,25),'Industry Stats'!$J$2:$J$46,0)) -> Textiles Apparel & Luxury Goods | C102: =INDEX('Industry Stats'!$B$2:$B$46,MATCH(LARGE('Industry Stats'!$J$2:$J$46,25),'Industry Stats'!$J$2:$J$46,0)) -> 9 | D102: =INDEX('Industry Stats'!$F$2:$F$46,MATCH(LARGE('Industry Stats'!$J$2:$J$46,25),'Industry Stats'!$J$2:$J$46,0)) -> 944.44444 | E102: =INDEX('Industry Stats'!$I$2:$I$46,MATCH(LARGE('Industry Stats'!$J$2:$J$46,25),'Industry Stats'!$J$2:$J$46,0)) -> Small sample
A103: 26 | B103: =INDEX('Industry Stats'!$A$2:$A$46,MATCH(LARGE('Industry Stats'!$J$2:$J$46,26),'Industry Stats'!$J$2:$J$46,0)) -> Health Care | C103: =INDEX('Industry Stats'!$B$2:$B$46,MATCH(LARGE('Industry Stats'!$J$2:$J$46,26),'Industry Stats'!$J$2:$J$46,0)) -> 51 | D103: =INDEX('Industry Stats'!$F$2:$F$46,MATCH(LARGE('Industry Stats'!$J$2:$J$46,26),'Industry Stats'!$J$2:$J$46,0)) -> 938.76471 | E103: =INDEX('Industry Stats'!$I$2:$I$46,MATCH(LARGE('Industry Stats'!$J$2:$J$46,26),'Industry Stats'!$J$2:$J$46,0)) -> Large sample
A104: 27 | B104: =INDEX('Industry Stats'!$A$2:$A$46,MATCH(LARGE('Industry Stats'!$J$2:$J$46,27),'Industry Stats'!$J$2:$J$46,0)) -> Communications | C104: =INDEX('Industry Stats'!$B$2:$B$46,MATCH(LARGE('Industry Stats'!$J$2:$J$46,27),'Industry Stats'!$J$2:$J$46,0)) -> 9 | D104: =INDEX('Industry Stats'!$F$2:$F$46,MATCH(LARGE('Industry Stats'!$J$2:$J$46,27),'Industry Stats'!$J$2:$J$46,0)) -> 938.22222 | E104: =INDEX('Industry Stats'!$I$2:$I$46,MATCH(LARGE('Industry Stats'!$J$2:$J$46,27),'Industry Stats'!$J$2:$J$46,0)) -> Small sample
A105: 28 | B105: =INDEX('Industry Stats'!$A$2:$A$46,MATCH(LARGE('Industry Stats'!$J$2:$J$46,28),'Industry Stats'!$J$2:$J$46,0)) -> Media | C105: =INDEX('Industry Stats'!$B$2:$B$46,MATCH(LARGE('Industry Stats'!$J$2:$J$46,28),'Industry Stats'!$J$2:$J$46,0)) -> 23 | D105: =INDEX('Industry Stats'!$F$2:$F$46,MATCH(LARGE('Industry Stats'!$J$2:$J$46,28),'Industry Stats'!$J$2:$J$46,0)) -> 935.26087 | E105: =INDEX('Industry Stats'!$I$2:$I$46,MATCH(LARGE('Industry Stats'!$J$2:$J$46,28),'Industry Stats'!$J$2:$J$46,0)) -> Large sample
...

Sheet Dashboard
A1: ESG BENCHMARKING DASHBOARD
A2: 722 companies across 47 industries | Ratings data, processed circa April–September 2022 | Every chart below answers a specific benchmarking question
A4: KEY METRICS
A5: Companies Analysed | C5: Industries Analysed | E5: Avg ESG Score | G5: Avg Environmental | I5: Avg Social | K5: Avg Governance
A6: =COUNTA(Benchmarking!B4:B725) -> 722 | C6: =47 -> 47 | E6: =AVERAGE(Benchmarking!G4:G725) -> 975.75069 | G6: =AVERAGE(Benchmarking!D4:D725) -> 404.80609 | I6: =AVERAGE(Benchmarking!E4:E725) -> 292.18283 | K6: =AVERAGE(Benchmarking!F4:F725) -> 278.76177
A8: Highest ESG Company | C8: Highest ESG Industry | E8: Largest Pillar Imbalance (Company) | G8: Companies Below Industry ESG Avg | I8: Flagged (Analytical Flag, Not Official Rating) | K8: Median Total ESG Score
A9: =Rankings!B6 -> Conocophillips | C9: =Rankings!B78 -> Utilities | E9: =Rankings!B150 -> CMS Energy Corp | G9: =COUNTIF(Benchmarking!I4:I725,"<0") -> 329 | I9: =SUMPRODUCT(--('Pillar Analysis'!Q4:Q725<>"")) -> 43 | K9: =MEDIAN(Benchmarking!G4:G725) -> 1046
A11: KPI notes: "Companies Below Industry ESG Avg" counts companies whose Total ESG Score is below their own industry's average (Benchmarking sheet). "Flagged for Investigation" counts companies meeting the High-ESG/weak-pillar test defined in Pillar Analysis (not an official risk rating).
A13: 1. Which industries have the strongest ESG performance? (Top 15 by average Total ESG score) | G13: 2. How do the three ESG pillars compare on average across the dataset?
A33: 3. Which individual companies have the strongest overall ESG scores? (Top 10) | G33: 4. How are Total ESG scores distributed across the 722 companies?
A53: 5. How do standout companies compare with their own industry benchmark? (Top 10 above vs. bottom 10 below) | G53: 6. Which companies show the largest imbalance between E, S and G? (Top 10 by pillar range)
A62: SUPPORTING DATA FOR CHARTS (do not delete — charts reference these cells)
A63: Pillar | B63: Average Score
A64: Environmental | B64: =AVERAGE(Benchmarking!D4:D725) -> 404.80609
A65: Social | B65: =AVERAGE(Benchmarking!E4:E725) -> 292.18283
A66: Governance | B66: =AVERAGE(Benchmarking!F4:F725) -> 278.76177
A68: Total ESG Score Range | B68: Number of Companies
A69: 600-700 | B69: =COUNTIFS(Benchmarking!$G$4:$G$725,">="&600,Benchmarking!$G$4:$G$725,"<"&700) -> 118
A70: 700-800 | B70: =COUNTIFS(Benchmarking!$G$4:$G$725,">="&700,Benchmarking!$G$4:$G$725,"<"&800) -> 88
A71: 800-900 | B71: =COUNTIFS(Benchmarking!$G$4:$G$725,">="&800,Benchmarking!$G$4:$G$725,"<"&900) -> 65
A72: 900-1000 | B72: =COUNTIFS(Benchmarking!$G$4:$G$725,">="&900,Benchmarking!$G$4:$G$725,"<"&1000) -> 57
A73: 1000-1100 | B73: =COUNTIFS(Benchmarking!$G$4:$G$725,">="&1000,Benchmarking!$G$4:$G$725,"<"&1100) -> 82
A74: 1100-1200 | B74: =COUNTIFS(Benchmarking!$G$4:$G$725,">="&1100,Benchmarking!$G$4:$G$725,"<"&1200) -> 229
A75: 1200-1300 | B75: =COUNTIFS(Benchmarking!$G$4:$G$725,">="&1200,Benchmarking!$G$4:$G$725,"<"&1300) -> 59
A76: 1300-1400 | B76: =COUNTIFS(Benchmarking!$G$4:$G$725,">="&1300,Benchmarking!$G$4:$G$725,"<"&1400) -> 12
A77: 1400-1500 | B77: =COUNTIFS(Benchmarking!$G$4:$G$725,">="&1400,Benchmarking!$G$4:$G$725,"<"&1500) -> 9
A78: 1500-1600 | B78: =COUNTIFS(Benchmarking!$G$4:$G$725,">="&1500,Benchmarking!$G$4:$G$725,"<="&1600) -> 3
A80: Company vs Industry staging (Top 10 strong outperformers + Bottom 10 underperformers)
A81: Company | B81: ESG vs Industry
A82: =Rankings!B168 -> Airbnb Inc | B82: =Rankings!G168 -> 556.13636
A83: =Rankings!B169 -> Amazon.com Inc | B83: =Rankings!G169 -> 514.42308
A84: =Rankings!B170 -> Microsoft Corp | B84: =Rankings!G170 -> 501.68254
A85: =Rankings!B171 -> Newmont Corporation | B85: =Rankings!G171 -> 432
A86: =Rankings!B172 -> Conocophillips | B86: =Rankings!G172 -> 418.2381
A87: =Rankings!B173 -> Air Products and Chemicals Inc | B87: =Rankings!G173 -> 383.10526
A88: =Rankings!B174 -> Aptiv PLC | B88: =Rankings!G174 -> 370.66667
A89: =Rankings!B175 -> Becton Dickinson and Co | B89: =Rankings!G175 -> 367.23529
A90: =Rankings!B176 -> Hannon Armstrong Sustainable Infrastructure Capital Inc | B90: =Rankings!G176 -> 367.05556
A91: =Rankings!B177 -> Amphenol Corp | B91: =Rankings!G177 -> 357
A92: =Rankings!B186 -> Xcel Energy Inc | B92: =Rankings!G186 -> -561.63333
A93: =Rankings!B187 -> Granite Construction Inc | B93: =Rankings!G187 -> -482.66667
A94: =Rankings!B188 -> Chevron Corp | B94: =Rankings!G188 -> -480.7619
A95: =Rankings!B189 -> Coca-Cola Co | B95: =Rankings!G189 -> -460
A96: =Rankings!B190 -> Primeenergy Resources Corp | B96: =Rankings!G190 -> -457.7619
A97: =Rankings!B191 -> Dow Inc | B97: =Rankings!G191 -> -432.89474
A98: =Rankings!B192 -> Advanced Micro Devices Inc | B98: =Rankings!G192 -> -422.58333
A99: =Rankings!B193 -> HEICO Corp | B99: =Rankings!G193 -> -415.18182
A100: =Rankings!B194 -> Adobe Inc | B100: =Rankings!G194 -> -410.31746
A101: =Rankings!B195 -> Broadcom Inc | B101: =Rankings!G195 -> -408.58333

Sheet Executive Summary
A1: EXECUTIVE SUMMARY
A2: ESG Company Benchmarking Model | 722 companies, 45 standardized industry groups | Prepared as a practical ESG analytics deliverable | Readable in 2-3 minutes
A4: EXECUTIVE OVERVIEW
A5: This model benchmarks 722 publicly listed companies across 47 raw industry labels (standardized down to 45 analytical industry groups — see Methodology) using a third-party ESG ratings dataset (Environmental, Social and Governance scores and sub-grades, processed by the ratings provider between April and September 2022). It converts raw company-level ratings into industry benchmarks, pillar-level diagnostics, rankings, and a small set of outlier and business-insight findings — the kind of first-pass analytical view an ESG analyst or investor would want before requesting underlying disclosures.
A7: KEY FINDINGS
A8: • Industry performance varies widely: average Total ESG scores across the 45 standardized industry groups range from about 709 (Unclassified — no industry tag in the source data) up to about 1,191 for Utilities (n=30) — a gap of over 480 points on the 600-1,536 scale.
A9: • A high aggregate ESG score can hide a materially weak individual pillar. CMS Energy Corp scores 1,192 overall (87th percentile) while its Governance score of 75 sits in the bottom 0.1% of all companies — the starkest case identified in the dataset.
A10: • 45.6% of companies (329 of 722) score below their own standardized industry's average Total ESG score, confirming that "above/below industry benchmark" is a meaningfully different question from "high/low in absolute terms."
A11: • 43 companies (about 6% of the dataset) meet this project's High-ESG/weak-pillar analytical test — a project-created flag, not an official ESG rating — and are marked for further review on the Pillar Analysis sheet.
A12: • Governance scores are the most tightly clustered pillar (mean 279, std. dev. 47) versus Environmental (mean 405, std. dev. 145), meaning Environmental performance is the primary driver of separation between high- and low-scoring companies.
A13: • Several of the highest-scoring industry groups by average (Tobacco n=2, Industrial Conglomerates n=3, Packaging n=4) rely on very small samples, so their rankings should be read as indicative, not statistically robust.
A14: • Governance appears as the weakest pillar in a disproportionate share of the flagged high-ESG/weak-pillar cases, warranting closer review of governance sub-indicators specifically.
... A77: METHODOLOGY & TRANSPARENCY NOTE
A78: Companies analysed: | C78: =COUNTA(Benchmarking!B4:B725) -> 722
A79: Raw industry text values in source data: | C79: =47 -> 47
A80: Standardized analytical industry groups used for benchmarking: | C80: =45 -> 45
A81: Dataset vintage (processing dates): | C81: ="Apr–Sep 2022" -> Apr–Sep 2022
A83: • What the scores represent: environment_score, social_score and governance_score are the ratings provider's component scores; total_score = environment_score + social_score + governance_score (verified exactly on all 722 records; no exceptions).
A84: • Industry-label standardization: the Benchmarking sheet computes a standardized industry label per company (=IF(industry="N/A","Unclassified",TRIM(SUBSTITUTE(industry," and "," & ")))) so that text-formatting variants of the same industry are benchmarked together. This is a formula in the analytical layer only — Raw Data is never modified.
A85: • Industry averages: calculated with AVERAGEIF/COUNTIF against the standardized industry column, and Max/Min Total ESG per group via legacy array-entered MAX(IF())/MIN(IF()) formulas — chosen specifically for broad Excel compatibility (no MAXIFS/MINIFS, no dynamic-array functions like UNIQUE, so the workbook opens and calculates cleanly in older Excel versions with no unsupported-function errors).
A86: • Company-vs-industry differences: Company score minus its standardized industry group's average score on the same measure (Total, Environmental, Social, Governance) — positive means above the industry benchmark, negative means below.
A87: • Outlier / percentile methodology: percentile rank = RANK(value, full column, ascending) / COUNT(full column). The "High ESG / weak pillar" flag requires Total-score percentile ≥ 0.70 AND (Total percentile − weakest-pillar percentile) ≥ 0.40 — both thresholds are explicit and adjustable, not hidden constants. This flag, and the Pillar Range measure, are project-created analytical tools for this workbook and are not official ESG ratings.
A88: • All figures in the Benchmarking, Pillar Analysis, Rankings and Dashboard sheets are live formulas referencing the Raw Data table; adding or editing a company in Raw Data will recalculate the whole model.

Sheet Industry Stats
A1: Industry (standardized) | B1: Company Count | C1: Avg Environmental | D1: Avg Social | E1: Avg Governance | F1: Avg Total ESG | G1: Max Total ESG | H1: Min Total ESG | I1: Sample Size Flag | J1: RankKey (AvgTotal, tie-break)
A2: Aerospace & Defense | B2: =COUNTIF(Benchmarking!$C$4:$C$725,"Aerospace & Defense") -> 11 | C2: =AVERAGEIF(Benchmarking!$C$4:$C$725,"Aerospace & Defense",Benchmarking!$D$4:$D$725) -> 461.36364 | D2: =AVERAGEIF(Benchmarking!$C$4:$C$725,"Aerospace & Defense",Benchmarking!$E$4:$E$725) -> 296.36364 | E2: =AVERAGEIF(Benchmarking!$C$4:$C$725,"Aerospace & Defense",Benchmarking!$F$4:$F$725) -> 290.45455 | F2: =AVERAGEIF(Benchmarking!$C$4:$C$725,"Aerospace & Defense",Benchmarking!$G$4:$G$725) -> 1048.1818 | G2: {=MAX(IF(Benchmarking!$C$4:$C$725="Aerospace & Defense",Benchmarking!$G$4:$G$725))} -> 1250 | H2: {=MIN(IF(Benchmarking!$C$4:$C$725="Aerospace & Defense",Benchmarking!$G$4:$G$725))} -> 633 | I2: =IF(B2>=20,"Large sample",IF(B2>=10,"Medium sample","Small sample")) -> Medium sample | J2: =F2+(1000-ROW())/1000000 -> 1048.1828
A3: Airlines | B3: =COUNTIF(Benchmarking!$C$4:$C$725,"Airlines") -> 7 | C3: =AVERAGEIF(Benchmarking!$C$4:$C$725,"Airlines",Benchmarking!$D$4:$D$725) -> 326.71429 | D3: =AVERAGEIF(Benchmarking!$C$4:$C$725,"Airlines",Benchmarking!$E$4:$E$725) -> 265.71429 | E3: =AVERAGEIF(Benchmarking!$C$4:$C$725,"Airlines",Benchmarking!$F$4:$F$725) -> 246.28571 | F3: =AVERAGEIF(Benchmarking!$C$4:$C$725,"Airlines",Benchmarking!$G$4:$G$725) -> 838.71429 | G3: {=MAX(IF(Benchmarking!$C$4:$C$725="Airlines",Benchmarking!$G$4:$G$725))} -> 1128 | H3: {=MIN(IF(Benchmarking!$C$4:$C$725="Airlines",Benchmarking!$G$4:$G$725))} -> 629 | I3: =IF(B3>=20,"Large sample",IF(B3>=10,"Medium sample","Small sample")) -> Small sample | J3: =F3+(1000-ROW())/1000000 -> 838.71528
A4: Auto Components | B4: =COUNTIF(Benchmarking!$C$4:$C$725,"Auto Components") -> 3 | C4: =AVERAGEIF(Benchmarking!$C$4:$C$725,"Auto Components",Benchmarking!$D$4:$D$725) -> 338.33333 | D4: =AVERAGEIF(Benchmarking!$C$4:$C$725,"Auto Components",Benchmarking!$E$4:$E$725) -> 248.33333 | E4: =AVERAGEIF(Benchmarking!$C$4:$C$725,"Auto Components",Benchmarking!$F$4:$F$725) -> 246.66667 | F4: =AVERAGEIF(Benchmarking!$C$4:$C$725,"Auto Components",Benchmarking!$G$4:$G$725) -> 833.33333 | G4: {=MAX(IF(Benchmarking!$C$4:$C$725="Auto Components",Benchmarking!$G$4:$G$725))} -> 1204 | H4: {=MIN(IF(Benchmarking!$C$4:$C$725="Auto Components",Benchmarking!$G$4:$G$725))} -> 600 | I4: =IF(B4>=20,"Large sample",IF(B4>=10,"Medium sample","Small sample")) -> Small sample | J4: =F4+(1000-ROW())/1000000 -> 833.33433
A5: Automobiles | B5: =COUNTIF(Benchmarking!$C$4:$C$725,"Automobiles") -> 4 | C5: =AVERAGEIF(Benchmarking!$C$4:$C$725,"Automobiles",Benchmarking!$D$4:$D$725) -> 393 | D5: =AVERAGEIF(Benchmarking!$C$4:$C$725,"Automobiles",Benchmarking!$E$4:$E$725) -> 229.25 | E5: =AVERAGEIF(Benchmarking!$C$4:$C$725,"Automobiles",Benchmarking!$F$4:$F$725) -> 237 | F5: =AVERAGEIF(Benchmarking!$C$4:$C$725,"Automobiles",Benchmarking!$G$4:$G$725) -> 859.25 | G5: {=MAX(IF(Benchmarking!$C$4:$C$725="Automobiles",Benchmarking!$G$4:$G$725))} -> 1068 | H5: {=MIN(IF(Benchmarking!$C$4:$C$725="Automobiles",Benchmarking!$G$4:$G$725))} -> 623 | I5: =IF(B5>=20,"Large sample",IF(B5>=10,"Medium sample","Small sample")) -> Small sample | J5: =F5+(1000-ROW())/1000000 -> 859.25099
A6: Banking | B6: =COUNTIF(Benchmarking!$C$4:$C$725,"Banking") -> 29 | C6: =AVERAGEIF(Benchmarking!$C$4:$C$725,"Banking",Benchmarking!$D$4:$D$725) -> 341.48276 | D6: =AVERAGEIF(Benchmarking!$C$4:$C$725,"Banking",Benchmarking!$E$4:$E$725) -> 292.34483 | E6: =AVERAGEIF(Benchmarking!$C$4:$C$725,"Banking",Benchmarking!$F$4:$F$725) -> 264.48276 | F6: =AVERAGEIF(Benchmarking!$C$4:$C$725,"Banking",Benchmarking!$G$4:$G$725) -> 898.31034 | G6: {=MAX(IF(Benchmarking!$C$4:$C$725="Banking",Benchmarking!$G$4:$G$725))} -> 1208 | H6: {=MIN(IF(Benchmarking!$C$4:$C$725="Banking",Benchmarking!$G$4:$G$725))} -> 600 | I6: =IF(B6>=20,"Large sample",IF(B6>=10,"Medium sample","Small sample")) -> Large sample | J6: =F6+(1000-ROW())/1000000 -> 898.31134
A7: Beverages | B7: =COUNTIF(Benchmarking!$C$4:$C$725,"Beverages") -> 4 | C7: =AVERAGEIF(Benchmarking!$C$4:$C$725,"Beverages",Benchmarking!$D$4:$D$725) -> 473.25 | D7: =AVERAGEIF(Benchmarking!$C$4:$C$725,"Beverages",Benchmarking!$E$4:$E$725) -> 299.5 | E7: =AVERAGEIF(Benchmarking!$C$4:$C$725,"Beverages",Benchmarking!$F$4:$F$725) -> 288.25 | F7: =AVERAGEIF(Benchmarking!$C$4:$C$725,"Beverages",Benchmarking!$G$4:$G$725) -> 1061 | G7: {=MAX(IF(Benchmarking!$C$4:$C$725="Beverages",Benchmarking!$G$4:$G$725))} -> 1417 | H7: {=MIN(IF(Benchmarking!$C$4:$C$725="Beverages",Benchmarking!$G$4:$G$725))} -> 601 | I7: =IF(B7>=20,"Large sample",IF(B7>=10,"Medium sample","Small sample")) -> Small sample | J7: =F7+(1000-ROW())/1000000 -> 1061.001
A8: Biotechnology | B8: =COUNTIF(Benchmarking!$C$4:$C$725,"Biotechnology") -> 56 | C8: =AVERAGEIF(Benchmarking!$C$4:$C$725,"Biotechnology",Benchmarking!$D$4:$D$725) -> 306.53571 | D8: =AVERAGEIF(Benchmarking!$C$4:$C$725,"Biotechnology",Benchmarking!$E$4:$E$725) -> 268.85714 | E8: =AVERAGEIF(Benchmarking!$C$4:$C$725,"Biotechnology",Benchmarking!$F$4:$F$725) -> 291.51786 | F8: =AVERAGEIF(Benchmarking!$C$4:$C$725,"Biotechnology",Benchmarking!$G$4:$G$725) -> 866.91071 | G8: {=MAX(IF(Benchmarking!$C$4:$C$725="Biotechnology",Benchmarking!$G$4:$G$725))} -> 1215 | H8: {=MIN(IF(Benchmarking!$C$4:$C$725="Biotechnology",Benchmarking!$G$4:$G$725))} -> 604 | I8: =IF(B8>=20,"Large sample",IF(B8>=10,"Medium sample","Small sample")) -> Large sample | J8: =F8+(1000-ROW())/1000000 -> 866.91171
A9: Building | B9: =COUNTIF(Benchmarking!$C$4:$C$725,"Building") -> 10 | C9: =AVERAGEIF(Benchmarking!$C$4:$C$725,"Building",Benchmarking!$D$4:$D$725) -> 476.7 | D9: =AVERAGEIF(Benchmarking!$C$4:$C$725,"Building",Benchmarking!$E$4:$E$725) -> 305.1 | E9: =AVERAGEIF(Benchmarking!$C$4:$C$725,"Building",Benchmarking!$F$4:$F$725) -> 292.4 | F9: =AVERAGEIF(Benchmarking!$C$4:$C$725,"Building",Benchmarking!$G$4:$G$725) -> 1074.2 | G9: {=MAX(IF(Benchmarking!$C$4:$C$725="Building",Benchmarking!$G$4:$G$725))} -> 1409 | H9: {=MIN(IF(Benchmarking!$C$4:$C$725="Building",Benchmarking!$G$4:$G$725))} -> 694 | I9: =IF(B9>=20,"Large sample",IF(B9>=10,"Medium sample","Small sample")) -> Medium sample | J9: =F9+(1000-ROW())/1000000 -> 1074.201
A10: Chemicals | B10: =COUNTIF(Benchmarking!$C$4:$C$725,"Chemicals") -> 19 | C10: =AVERAGEIF(Benchmarking!$C$4:$C$725,"Chemicals",Benchmarking!$D$4:$D$725) -> 463.73684 | D10: =AVERAGEIF(Benchmarking!$C$4:$C$725,"Chemicals",Benchmarking!$E$4:$E$725) -> 304.36842 | E10: =AVERAGEIF(Benchmarking!$C$4:$C$725,"Chemicals",Benchmarking!$F$4:$F$725) -> 290.78947 | F10: =AVERAGEIF(Benchmarking!$C$4:$C$725,"Chemicals",Benchmarking!$G$4:$G$725) -> 1058.8947 | G10: {=MAX(IF(Benchmarking!$C$4:$C$725="Chemicals",Benchmarking!$G$4:$G$725))} -> 1442 | H10: {=MIN(IF(Benchmarking!$C$4:$C$725="Chemicals",Benchmarking!$G$4:$G$725))} -> 626 | I10: =IF(B10>=20,"Large sample",IF(B10>=10,"Medium sample","Small sample")) -> Medium sample | J10: =F10+(1000-ROW())/1000000 -> 1058.8957
A11: Commercial Services & Supplies | B11: =COUNTIF(Benchmarking!$C$4:$C$725,"Commercial Services & Supplies") -> 7 | C11: =AVERAGEIF(Benchmarking!$C$4:$C$725,"Commercial Services & Supplies",Benchmarking!$D$4:$D$725) -> 419.42857 | D11: =AVERAGEIF(Benchmarking!$C$4:$C$725,"Commercial Services & Supplies",Benchmarking!$E$4:$E$725) -> 301.28571 | E11: =AVERAGEIF(Benchmarking!$C$4:$C$725,"Commercial Services & Supplies",Benchmarking!$F$4:$F$725) -> 275.14286 | F11: =AVERAGEIF(Benchmarking!$C$4:$C$725,"Commercial Services & Supplies",Benchmarking!$G$4:$G$725) -> 995.85714 | G11: {=MAX(IF(Benchmarking!$C$4:$C$725="Commercial Services & Supplies",Benchmarking!$G$4:$G$725))} -> 1306 | H11: {=MIN(IF(Benchmarking!$C$4:$C$725="Commercial Services & Supplies",Benchmarking!$G$4:$G$725))} -> 679 | I11: =IF(B11>=20,"Large sample",IF(B11>=10,"Medium sample","Small sample")) -> Small sample | J11: =F11+(1000-ROW())/1000000 -> 995.85813
A12: Communications | B12: =COUNTIF(Benchmarking!$C$4:$C$725,"Communications") -> 9 | C12: =AVERAGEIF(Benchmarking!$C$4:$C$725,"Communications",Benchmarking!$D$4:$D$725) -> 385 | D12: =AVERAGEIF(Benchmarking!$C$4:$C$725,"Communications",Benchmarking!$E$4:$E$725) -> 278.77778 | E12: =AVERAGEIF(Benchmarking!$C$4:$C$725,"Communications",Benchmarking!$F$4:$F$725) -> 274.44444 | F12: =AVERAGEIF(Benchmarking!$C$4:$C$725,"Communications",Benchmarking!$G$4:$G$725) -> 938.22222 | G12: {=MAX(IF(Benchmarking!$C$4:$C$725="Communications",Benchmarking!$G$4:$G$725))} -> 1157 | H12: {=MIN(IF(Benchmarking!$C$4:$C$725="Communications",Benchmarking!$G$4:$G$725))} -> 636 | I12: =IF(B12>=20,"Large sample",IF(B12>=10,"Medium sample","Small sample")) -> Small sample | J12: =F12+(1000-ROW())/1000000 -> 938.22321
A13: Construction | B13: =COUNTIF(Benchmarking!$C$4:$C$725,"Construction") -> 6 | C13: =AVERAGEIF(Benchmarking!$C$4:$C$725,"Construction",Benchmarking!$D$4:$D$725) -> 495.33333 | D13: =AVERAGEIF(Benchmarking!$C$4:$C$725,"Construction",Benchmarking!$E$4:$E$725) -> 306.16667 | E13: =AVERAGEIF(Benchmarking!$C$4:$C$725,"Construction",Benchmarking!$F$4:$F$725) -> 281.16667 | F13: =AVERAGEIF(Benchmarking!$C$4:$C$725,"Construction",Benchmarking!$G$4:$G$725) -> 1082.6667 | G13: {=MAX(IF(Benchmarking!$C$4:$C$725="Construction",Benchmarking!$G$4:$G$725))} -> 1256 | H13: {=MIN(IF(Benchmarking!$C$4:$C$725="Construction",Benchmarking!$G$4:$G$725))} -> 600 | I13: =IF(B13>=20,"Large sample",IF(B13>=10,"Medium sample","Small sample")) -> Small sample | J13: =F13+(1000-ROW())/1000000 -> 1082.6677
A14: Consumer products | B14: =COUNTIF(Benchmarking!$C$4:$C$725,"Consumer products") -> 20 | C14: =AVERAGEIF(Benchmarking!$C$4:$C$725,"Consumer products",Benchmarking!$D$4:$D$725) -> 384.9 | D14: =AVERAGEIF(Benchmarking!$C$4:$C$725,"Consumer products",Benchmarking!$E$4:$E$725) -> 285.7 | E14: =AVERAGEIF(Benchmarking!$C$4:$C$725,"Consumer products",Benchmarking!$F$4:$F$725) -> 274.95 | F14: =AVERAGEIF(Benchmarking!$C$4:$C$725,"Consumer products",Benchmarking!$G$4:$G$725) -> 945.55 | G14: {=MAX(IF(Benchmarking!$C$4:$C$725="Consumer products",Benchmarking!$G$4:$G$725))} -> 1292 | H14: {=MIN(IF(Benchmarking!$C$4:$C$725="Consumer products",Benchmarking!$G$4:$G$725))} -> 647 | I14: =IF(B14>=20,"Large sample",IF(B14>=10,"Medium sample","Small sample")) -> Large sample | J14: =F14+(1000-ROW())/1000000 -> 945.55099
A15: Distributors | B15: =COUNTIF(Benchmarking!$C$4:$C$725,"Distributors") -> 3 | C15: =AVERAGEIF(Benchmarking!$C$4:$C$725,"Distributors",Benchmarking!$D$4:$D$725) -> 525 | D15: =AVERAGEIF(Benchmarking!$C$4:$C$725,"Distributors",Benchmarking!$E$4:$E$725) -> 277 | E15: =AVERAGEIF(Benchmarking!$C$4:$C$725,"Distributors",Benchmarking!$F$4:$F$725) -> 307.66667 | F15: =AVERAGEIF(Benchmarking!$C$4:$C$725,"Distributors",Benchmarking!$G$4:$G$725) -> 1109.6667 | G15: {=MAX(IF(Benchmarking!$C$4:$C$725="Distributors",Benchmarking!$G$4:$G$725))} -> 1144 | H15: {=MIN(IF(Benchmarking!$C$4:$C$725="Distributors",Benchmarking!$G$4:$G$725))} -> 1065 | I15: =IF(B15>=20,"Large sample",IF(B15>=10,"Medium sample","Small sample")) -> Small sample | J15: =F15+(1000-ROW())/1000000 -> 1109.6677
A16: Diversified Consumer Services | B16: =COUNTIF(Benchmarking!$C$4:$C$725,"Diversified Consumer Services") -> 3 | C16: =AVERAGEIF(Benchmarking!$C$4:$C$725,"Diversified Consumer Services",Benchmarking!$D$4:$D$725) -> 286 | D16: =AVERAGEIF(Benchmarking!$C$4:$C$725,"Diversified Consumer Services",Benchmarking!$E$4:$E$725) -> 233.33333 | E16: =AVERAGEIF(Benchmarking!$C$4:$C$725,"Diversified Consumer Services",Benchmarking!$F$4:$F$725) -> 220 | F16: =AVERAGEIF(Benchmarking!$C$4:$C$725,"Diversified Consumer Services",Benchmarking!$G$4:$G$725) -> 739.33333 | G16: {=MAX(IF(Benchmarking!$C$4:$C$725="Diversified Consumer Services",Benchmarking!$G$4:$G$725))} -> 912 | H16: {=MIN(IF(Benchmarking!$C$4:$C$725="Diversified Consumer Services",Benchmarking!$G$4:$G$725))} -> 608 | I16: =IF(B16>=20,"Large sample",IF(B16>=10,"Medium sample","Small sample")) -> Small sample | J16: =F16+(1000-ROW())/1000000 -> 739.33432
A17: Electrical Equipment | B17: =COUNTIF(Benchmarking!$C$4:$C$725,"Electrical Equipment") -> 27 | C17: =AVERAGEIF(Benchmarking!$C$4:$C$725,"Electrical Equipment",Benchmarking!$D$4:$D$725) -> 381.7037 | D17: =AVERAGEIF(Benchmarking!$C$4:$C$725,"Electrical Equipment",Benchmarking!$E$4:$E$725) -> 272.11111 | E17: =AVERAGEIF(Benchmarking!$C$4:$C$725,"Electrical Equipment",Benchmarking!$F$4:$F$725) -> 279.18519 | F17: =AVERAGEIF(Benchmarking!$C$4:$C$725,"Electrical Equipment",Benchmarking!$G$4:$G$725) -> 933 | G17: {=MAX(IF(Benchmarking!$C$4:$C$725="Electrical Equipment",Benchmarking!$G$4:$G$725))} -> 1290 | H17: {=MIN(IF(Benchmarking!$C$4:$C$725="Electrical Equipment",Benchmarking!$G$4:$G$725))} -> 600 | I17: =IF(B17>=20,"Large sample",IF(B17>=10,"Medium sample","Small sample")) -> Large sample | J17: =F17+(1000-ROW())/1000000 -> 933.00098
A18: Energy | B18: =COUNTIF(Benchmarking!$C$4:$C$725,"Energy") -> 21 | C18: =AVERAGEIF(Benchmarking!$C$4:$C$725,"Energy",Benchmarking!$D$4:$D$725) -> 515.09524 | D18: =AVERAGEIF(Benchmarking!$C$4:$C$725,"Energy",Benchmarking!$E$4:$E$725) -> 308.95238 | E18: =AVERAGEIF(Benchmarking!$C$4:$C$725,"Energy",Benchmarking!$F$4:$F$725) -> 293.71429 | F18: =AVERAGEIF(Benchmarking!$C$4:$C$725,"Energy",Benchmarking!$G$4:$G$725) -> 1117.7619 | G18: {=MAX(IF(Benchmarking!$C$4:$C$725="Energy",Benchmarking!$G$4:$G$725))} -> 1536 | H18: {=MIN(IF(Benchmarking!$C$4:$C$725="Energy",Benchmarking!$G$4:$G$725))} -> 637 | I18: =IF(B18>=20,"Large sample",IF(B18>=10,"Medium sample","Small sample")) -> Large sample | J18: =F18+(1000-ROW())/1000000 -> 1117.7629
A19: Financial Services | B19: =COUNTIF(Benchmarking!$C$4:$C$725,"Financial Services") -> 33 | C19: =AVERAGEIF(Benchmarking!$C$4:$C$725,"Financial Services",Benchmarking!$D$4:$D$725) -> 367.63636 | D19: =AVERAGEIF(Benchmarking!$C$4:$C$725,"Financial Services",Benchmarking!$E$4:$E$725) -> 276.45455 | E19: =AVERAGEIF(Benchmarking!$C$4:$C$725,"Financial Services",Benchmarking!$F$4:$F$725) -> 265.24242 | F19: =AVERAGEIF(Benchmarking!$C$4:$C$725,"Financial Services",Benchmarking!$G$4:$G$725) -> 909.33333 | G19: {=MAX(IF(Benchmarking!$C$4:$C$725="Financial Services",Benchmarking!$G$4:$G$725))} -> 1262 | H19: {=MIN(IF(Benchmarking!$C$4:$C$725="Financial Services",Benchmarking!$G$4:$G$725))} -> 610 | I19: =IF(B19>=20,"Large sample",IF(B19>=10,"Medium sample","Small sample")) -> Large sample | J19: =F19+(1000-ROW())/1000000 -> 909.33431
A20: Food Products | B20: =COUNTIF(Benchmarking!$C$4:$C$725,"Food Products") -> 14 | C20: =AVERAGEIF(Benchmarking!$C$4:$C$725,"Food Products",Benchmarking!$D$4:$D$725) -> 516.57143 | D20: =AVERAGEIF(Benchmarking!$C$4:$C$725,"Food Products",Benchmarking!$E$4:$E$725) -> 311.28571 | E20: =AVERAGEIF(Benchmarking!$C$4:$C$725,"Food Products",Benchmarking!$F$4:$F$725) -> 303.21429 | F20: =AVERAGEIF(Benchmarking!$C$4:$C$725,"Food Products",Benchmarking!$G$4:$G$725) -> 1131.0714 | G20: {=MAX(IF(Benchmarking!$C$4:$C$725="Food Products",Benchmarking!$G$4:$G$725))} -> 1276 | H20: {=MIN(IF(Benchmarking!$C$4:$C$725="Food Products",Benchmarking!$G$4:$G$725))} -> 901 | I20: =IF(B20>=20,"Large sample",IF(B20>=10,"Medium sample","Small sample")) -> Medium sample | J20: =F20+(1000-ROW())/1000000 -> 1131.0724
A21: Health Care | B21: =COUNTIF(Benchmarking!$C$4:$C$725,"Health Care") -> 51 | C21: =AVERAGEIF(Benchmarking!$C$4:$C$725,"Health Care",Benchmarking!$D$4:$D$725) -> 374.52941 | D21: =AVERAGEIF(Benchmarking!$C$4:$C$725,"Health Care",Benchmarking!$E$4:$E$725) -> 287.43137 | E21: =AVERAGEIF(Benchmarking!$C$4:$C$725,"Health Care",Benchmarking!$F$4:$F$725) -> 276.80392 | F21: =AVERAGEIF(Benchmarking!$C$4:$C$725,"Health Care",Benchmarking!$G$4:$G$725) -> 938.76471 | G21: {=MAX(IF(Benchmarking!$C$4:$C$725="Health Care",Benchmarking!$G$4:$G$725))} -> 1306 | H21: {=MIN(IF(Benchmarking!$C$4:$C$725="Health Care",Benchmarking!$G$4:$G$725))} -> 600 | I21: =IF(B21>=20,"Large sample",IF(B21>=10,"Medium sample","Small sample")) -> Large sample | J21: =F21+(1000-ROW())/1000000 -> 938.76568
A22: Hotels Restaurants & Leisure | B22: =COUNTIF(Benchmarking!$C$4:$C$725,"Hotels Restaurants & Leisure") -> 22 | C22: =AVERAGEIF(Benchmarking!$C$4:$C$725,"Hotels Restaurants & Leisure",Benchmarking!$D$4:$D$725) -> 374.63636 | D22: =AVERAGEIF(Benchmarking!$C$4:$C$725,"Hotels Restaurants & Leisure",Benchmarking!$E$4:$E$725) -> 283.04545 | E22: =AVERAGEIF(Benchmarking!$C$4:$C$725,"Hotels Restaurants & Leisure",Benchmarking!$F$4:$F$725) -> 261.18182 | F22: =AVERAGEIF(Benchmarking!$C$4:$C$725,"Hotels Restaurants & Leisure",Benchmarking!$G$4:$G$725) -> 918.86364 | G22: {=MAX(IF(Benchmarking!$C$4:$C$725="Hotels Restaurants & Leisure",Benchmarking!$G$4:$G$725))} -> 1475 | H22: {=MIN(IF(Benchmarking!$C$4:$C$725="Hotels Restaurants & Leisure",Benchmarking!$G$4:$G$725))} -> 600 | I22: =IF(B22>=20,"Large sample",IF(B22>=10,"Medium sample","Small sample")) -> Large sample | J22: =F22+(1000-ROW())/1000000 -> 918.86461
A23: Hotels, Restaurants & Leisure | B23: =COUNTIF(Benchmarking!$C$4:$C$725,"Hotels, Restaurants & Leisure") -> 2 | C23: =AVERAGEIF(Benchmarking!$C$4:$C$725,"Hotels, Restaurants & Leisure",Benchmarking!$D$4:$D$725) -> 270 | D23: =AVERAGEIF(Benchmarking!$C$4:$C$725,"Hotels, Restaurants & Leisure",Benchmarking!$E$4:$E$725) -> 248.5 | E23: =AVERAGEIF(Benchmarking!$C$4:$C$725,"Hotels, Restaurants & Leisure",Benchmarking!$F$4:$F$725) -> 227.5 | F23: =AVERAGEIF(Benchmarking!$C$4:$C$725,"Hotels, Restaurants & Leisure",Benchmarking!$G$4:$G$725) -> 746 | G23: {=MAX(IF(Benchmarking!$C$4:$C$725="Hotels, Restaurants & Leisure",Benchmarking!$G$4:$G$725))} -> 843 | H23: {=MIN(IF(Benchmarking!$C$4:$C$725="Hotels, Restaurants & Leisure",Benchmarking!$G$4:$G$725))} -> 649 | I23: =IF(B23>=20,"Large sample",IF(B23>=10,"Medium sample","Small sample")) -> Small sample | J23: =F23+(1000-ROW())/1000000 -> 746.00098
A24: Industrial Conglomerates | B24: =COUNTIF(Benchmarking!$C$4:$C$725,"Industrial Conglomerates") -> 3 | C24: =AVERAGEIF(Benchmarking!$C$4:$C$725,"Industrial Conglomerates",Benchmarking!$D$4:$D$725) -> 534.66667 | D24: =AVERAGEIF(Benchmarking!$C$4:$C$725,"Industrial Conglomerates",Benchmarking!$E$4:$E$725) -> 318 | E24: =AVERAGEIF(Benchmarking!$C$4:$C$725,"Industrial Conglomerates",Benchmarking!$F$4:$F$725) -> 304.33333 | F24: =AVERAGEIF(Benchmarking!$C$4:$C$725,"Industrial Conglomerates",Benchmarking!$G$4:$G$725) -> 1157 | G24: {=MAX(IF(Benchmarking!$C$4:$C$725="Industrial Conglomerates",Benchmarking!$G$4:$G$725))} -> 1197 | H24: {=MIN(IF(Benchmarking!$C$4:$C$725="Industrial Conglomerates",Benchmarking!$G$4:$G$725))} -> 1133 | I24: =IF(B24>=20,"Large sample",IF(B24>=10,"Medium sample","Small sample")) -> Small sample | J24: =F24+(1000-ROW())/1000000 -> 1157.001
A25: Insurance | B25: =COUNTIF(Benchmarking!$C$4:$C$725,"Insurance") -> 27 | C25: =AVERAGEIF(Benchmarking!$C$4:$C$725,"Insurance",Benchmarking!$D$4:$D$725) -> 425.25926 | D25: =AVERAGEIF(Benchmarking!$C$4:$C$725,"Insurance",Benchmarking!$E$4:$E$725) -> 295.66667 | E25: =AVERAGEIF(Benchmarking!$C$4:$C$725,"Insurance",Benchmarking!$F$4:$F$725) -> 291.44444 | F25: =AVERAGEIF(Benchmarking!$C$4:$C$725,"Insurance",Benchmarking!$G$4:$G$725) -> 1012.3704 | G25: {=MAX(IF(Benchmarking!$C$4:$C$725="Insurance",Benchmarking!$G$4:$G$725))} -> 1300 | H25: {=MIN(IF(Benchmarking!$C$4:$C$725="Insurance",Benchmarking!$G$4:$G$725))} -> 668 | I25: =IF(B25>=20,"Large sample",IF(B25>=10,"Medium sample","Small sample")) -> Large sample | J25: =F25+(1000-ROW())/1000000 -> 1012.3713
A26: Leisure Products | B26: =COUNTIF(Benchmarking!$C$4:$C$725,"Leisure Products") -> 3 | C26: =AVERAGEIF(Benchmarking!$C$4:$C$725,"Leisure Products",Benchmarking!$D$4:$D$725) -> 252.33333 | D26: =AVERAGEIF(Benchmarking!$C$4:$C$725,"Leisure Products",Benchmarking!$E$4:$E$725) -> 259.33333 | E26: =AVERAGEIF(Benchmarking!$C$4:$C$725,"Leisure Products",Benchmarking!$F$4:$F$725) -> 268.33333 | F26: =AVERAGEIF(Benchmarking!$C$4:$C$725,"Leisure Products",Benchmarking!$G$4:$G$725) -> 780 | G26: {=MAX(IF(Benchmarking!$C$4:$C$725="Leisure Products",Benchmarking!$G$4:$G$725))} -> 856 | H26: {=MIN(IF(Benchmarking!$C$4:$C$725="Leisure Products",Benchmarking!$G$4:$G$725))} -> 657 | I26: =IF(B26>=20,"Large sample",IF(B26>=10,"Medium sample","Small sample")) -> Small sample | J26: =F26+(1000-ROW())/1000000 -> 780.00097
A27: Life Sciences Tools & Services | B27: =COUNTIF(Benchmarking!$C$4:$C$725,"Life Sciences Tools & Services") -> 16 | C27: =AVERAGEIF(Benchmarking!$C$4:$C$725,"Life Sciences Tools & Services",Benchmarking!$D$4:$D$725) -> 421.375 | D27: =AVERAGEIF(Benchmarking!$C$4:$C$725,"Life Sciences Tools & Services",Benchmarking!$E$4:$E$725) -> 294.5 | E27: =AVERAGEIF(Benchmarking!$C$4:$C$725,"Life Sciences Tools & Services",Benchmarking!$F$4:$F$725) -> 277.25 | F27: =AVERAGEIF(Benchmarking!$C$4:$C$725,"Life Sciences Tools & Services",Benchmarking!$G$4:$G$725) -> 993.125 | G27: {=MAX(IF(Benchmarking!$C$4:$C$725="Life Sciences Tools & Services",Benchmarking!$G$4:$G$725))} -> 1259 | H27: {=MIN(IF(Benchmarking!$C$4:$C$725="Life Sciences Tools & Services",Benchmarking!$G$4:$G$725))} -> 659 | I27: =IF(B27>=20,"Large sample",IF(B27>=10,"Medium sample","Small sample")) -> Medium sample | J27: =F27+(1000-ROW())/1000000 -> 993.12597
A28: Logistics & Transportation | B28: =COUNTIF(Benchmarking!$C$4:$C$725,"Logistics & Transportation") -> 6 | C28: =AVERAGEIF(Benchmarking!$C$4:$C$725,"Logistics & Transportation",Benchmarking!$D$4:$D$725) -> 452.33333 | D28: =AVERAGEIF(Benchmarking!$C$4:$C$725,"Logistics & Transportation",Benchmarking!$E$4:$E$725) -> 289.5 | E28: =AVERAGEIF(Benchmarking!$C$4:$C$725,"Logistics & Transportation",Benchmarking!$F$4:$F$725) -> 283.33333 | F28: =AVERAGEIF(Benchmarking!$C$4:$C$725,"Logistics & Transportation",Benchmarking!$G$4:$G$725) -> 1025.1667 | G28: {=MAX(IF(Benchmarking!$C$4:$C$725="Logistics & Transportation",Benchmarking!$G$4:$G$725))} -> 1243 | H28: {=MIN(IF(Benchmarking!$C$4:$C$725="Logistics & Transportation",Benchmarking!$G$4:$G$725))} -> 769 | I28: =IF(B28>=20,"Large sample",IF(B28>=10,"Medium sample","Small sample")) -> Small sample | J28: =F28+(1000-ROW())/1000000 -> 1025.1676
A29: Machinery | B29: =COUNTIF(Benchmarking!$C$4:$C$725,"Machinery") -> 21 | C29: =AVERAGEIF(Benchmarking!$C$4:$C$725,"Machinery",Benchmarking!$D$4:$D$725) -> 459.57143 | D29: =AVERAGEIF(Benchmarking!$C$4:$C$725,"Machinery",Benchmarking!$E$4:$E$725) -> 313.66667 | E29: =AVERAGEIF(Benchmarking!$C$4:$C$725,"Machinery",Benchmarking!$F$4:$F$725) -> 274.80952 | F29: =AVERAGEIF(Benchmarking!$C$4:$C$725,"Machinery",Benchmarking!$G$4:$G$725) -> 1048.0476 | G29: {=MAX(IF(Benchmarking!$C$4:$C$725="Machinery",Benchmarking!$G$4:$G$725))} -> 1238 | H29: {=MIN(IF(Benchmarking!$C$4:$C$725="Machinery",Benchmarking!$G$4:$G$725))} -> 709 | I29: =IF(B29>=20,"Large sample",IF(B29>=10,"Medium sample","Small sample")) -> Large sample | J29: =F29+(1000-ROW())/1000000 -> 1048.0486
A30: Marine | B30: =COUNTIF(Benchmarking!$C$4:$C$725,"Marine") -> 3 | C30: =AVERAGEIF(Benchmarking!$C$4:$C$725,"Marine",Benchmarking!$D$4:$D$725) -> 305.33333 | D30: =AVERAGEIF(Benchmarking!$C$4:$C$725,"Marine",Benchmarking!$E$4:$E$725) -> 285 | E30: =AVERAGEIF(Benchmarking!$C$4:$C$725,"Marine",Benchmarking!$F$4:$F$725) -> 275 | F30: =AVERAGEIF(Benchmarking!$C$4:$C$725,"Marine",Benchmarking!$G$4:$G$725) -> 865.33333 | G30: {=MAX(IF(Benchmarking!$C$4:$C$725="Marine",Benchmarking!$G$4:$G$725))} -> 1000 | H30: {=MIN(IF(Benchmarking!$C$4:$C$725="Marine",Benchmarking!$G$4:$G$725))} -> 646 | I30: =IF(B30>=20,"Large sample",IF(B30>=10,"Medium sample","Small sample")) -> Small sample | J30: =F30+(1000-ROW())/1000000 -> 865.3343
A31: Media | B31: =COUNTIF(Benchmarking!$C$4:$C$725,"Media") -> 23 | C31: =AVERAGEIF(Benchmarking!$C$4:$C$725,"Media",Benchmarking!$D$4:$D$725) -> 346.91304 | D31: =AVERAGEIF(Benchmarking!$C$4:$C$725,"Media",Benchmarking!$E$4:$E$725) -> 313 | E31: =AVERAGEIF(Benchmarking!$C$4:$C$725,"Media",Benchmarking!$F$4:$F$725) -> 275.34783 | F31: =AVERAGEIF(Benchmarking!$C$4:$C$725,"Media",Benchmarking!$G$4:$G$725) -> 935.26087 | G31: {=MAX(IF(Benchmarking!$C$4:$C$725="Media",Benchmarking!$G$4:$G$725))} -> 1181 | H31: {=MIN(IF(Benchmarking!$C$4:$C$725="Media",Benchmarking!$G$4:$G$725))} -> 607 | I31: =IF(B31>=20,"Large sample",IF(B31>=10,"Medium sample","Small sample")) -> Large sample | J31: =F31+(1000-ROW())/1000000 -> 935.26184
A32: Metals & Mining | B32: =COUNTIF(Benchmarking!$C$4:$C$725,"Metals & Mining") -> 10 | C32: =AVERAGEIF(Benchmarking!$C$4:$C$725,"Metals & Mining",Benchmarking!$D$4:$D$725) -> 427.3 | D32: =AVERAGEIF(Benchmarking!$C$4:$C$725,"Metals & Mining",Benchmarking!$E$4:$E$725) -> 289.2 | E32: =AVERAGEIF(Benchmarking!$C$4:$C$725,"Metals & Mining",Benchmarking!$F$4:$F$725) -> 270.5 | F32: =AVERAGEIF(Benchmarking!$C$4:$C$725,"Metals & Mining",Benchmarking!$G$4:$G$725) -> 987 | G32: {=MAX(IF(Benchmarking!$C$4:$C$725="Metals & Mining",Benchmarking!$G$4:$G$725))} -> 1419 | H32: {=MIN(IF(Benchmarking!$C$4:$C$725="Metals & Mining",Benchmarking!$G$4:$G$725))} -> 615 | I32: =IF(B32>=20,"Large sample",IF(B32>=10,"Medium sample","Small sample")) -> Medium sample | J32: =F32+(1000-ROW())/1000000 -> 987.00097
A33: Packaging | B33: =COUNTIF(Benchmarking!$C$4:$C$725,"Packaging") -> 4 | C33: =AVERAGEIF(Benchmarking!$C$4:$C$725,"Packaging",Benchmarking!$D$4:$D$725) -> 536.25 | D33: =AVERAGEIF(Benchmarking!$C$4:$C$725,"Packaging",Benchmarking!$E$4:$E$725) -> 323 | E33: =AVERAGEIF(Benchmarking!$C$4:$C$725,"Packaging",Benchmarking!$F$4:$F$725) -> 296.75 | F33: =AVERAGEIF(Benchmarking!$C$4:$C$725,"Packaging",Benchmarking!$G$4:$G$725) -> 1156 | G33: {=MAX(IF(Benchmarking!$C$4:$C$725="Packaging",Benchmarking!$G$4:$G$725))} -> 1207 | H33: {=MIN(IF(Benchmarking!$C$4:$C$725="Packaging",Benchmarking!$G$4:$G$725))} -> 1103 | I33: =IF(B33>=20,"Large sample",IF(B33>=10,"Medium sample","Small sample")) -> Small sample | J33: =F33+(1000-ROW())/1000000 -> 1156.001
A34: Pharmaceuticals | B34: =COUNTIF(Benchmarking!$C$4:$C$725,"Pharmaceuticals") -> 21 | C34: =AVERAGEIF(Benchmarking!$C$4:$C$725,"Pharmaceuticals",Benchmarking!$D$4:$D$725) -> 360.04762 | D34: =AVERAGEIF(Benchmarking!$C$4:$C$725,"Pharmaceuticals",Benchmarking!$E$4:$E$725) -> 269.66667 | E34: =AVERAGEIF(Benchmarking!$C$4:$C$725,"Pharmaceuticals",Benchmarking!$F$4:$F$725) -> 273.95238 | F34: =AVERAGEIF(Benchmarking!$C$4:$C$725,"Pharmaceuticals",Benchmarking!$G$4:$G$725) -> 903.66667 | G34: {=MAX(IF(Benchmarking!$C$4:$C$725="Pharmaceuticals",Benchmarking!$G$4:$G$725))} -> 1180 | H34: {=MIN(IF(Benchmarking!$C$4:$C$725="Pharmaceuticals",Benchmarking!$G$4:$G$725))} -> 645 | I34: =IF(B34>=20,"Large sample",IF(B34>=10,"Medium sample","Small sample")) -> Large sample | J34: =F34+(1000-ROW())/1000000 -> 903.66763
A35: Professional Services | B35: =COUNTIF(Benchmarking!$C$4:$C$725,"Professional Services") -> 7 | C35: =AVERAGEIF(Benchmarking!$C$4:$C$725,"Professional Services",Benchmarking!$D$4:$D$725) -> 435 | D35: =AVERAGEIF(Benchmarking!$C$4:$C$725,"Professional Services",Benchmarking!$E$4:$E$725) -> 312.42857 | E35: =AVERAGEIF(Benchmarking!$C$4:$C$725,"Professional Services",Benchmarking!$F$4:$F$725) -> 300.42857 | F35: =AVERAGEIF(Benchmarking!$C$4:$C$725,"Professional Services",Benchmarking!$G$4:$G$725) -> 1047.8571 | G35: {=MAX(IF(Benchmarking!$C$4:$C$725="Professional Services",Benchmarking!$G$4:$G$725))} -> 1281 | H35: {=MIN(IF(Benchmarking!$C$4:$C$725="Professional Services",Benchmarking!$G$4:$G$725))} -> 817 | I35: =IF(B35>=20,"Large sample",IF(B35>=10,"Medium sample","Small sample")) -> Small sample | J35: =F35+(1000-ROW())/1000000 -> 1047.8581
A36: Real Estate | B36: =COUNTIF(Benchmarking!$C$4:$C$725,"Real Estate") -> 36 | C36: =AVERAGEIF(Benchmarking!$C$4:$C$725,"Real Estate",Benchmarking!$D$4:$D$725) -> 431.38889 | D36: =AVERAGEIF(Benchmarking!$C$4:$C$725,"Real Estate",Benchmarking!$E$4:$E$725) -> 290.91667 | E36: =AVERAGEIF(Benchmarking!$C$4:$C$725,"Real Estate",Benchmarking!$F$4:$F$725) -> 273.63889 | F36: =AVERAGEIF(Benchmarking!$C$4:$C$725,"Real Estate",Benchmarking!$G$4:$G$725) -> 995.94444 | G36: {=MAX(IF(Benchmarking!$C$4:$C$725="Real Estate",Benchmarking!$G$4:$G$725))} -> 1363 | H36: {=MIN(IF(Benchmarking!$C$4:$C$725="Real Estate",Benchmarking!$G$4:$G$725))} -> 609 | I36: =IF(B36>=20,"Large sample",IF(B36>=10,"Medium sample","Small sample")) -> Large sample | J36: =F36+(1000-ROW())/1000000 -> 995.94541
A37: Retail | B37: =COUNTIF(Benchmarking!$C$4:$C$725,"Retail") -> 26 | C37: =AVERAGEIF(Benchmarking!$C$4:$C$725,"Retail",Benchmarking!$D$4:$D$725) -> 380.30769 | D37: =AVERAGEIF(Benchmarking!$C$4:$C$725,"Retail",Benchmarking!$E$4:$E$725) -> 274.96154 | E37: =AVERAGEIF(Benchmarking!$C$4:$C$725,"Retail",Benchmarking!$F$4:$F$725) -> 263.30769 | F37: =AVERAGEIF(Benchmarking!$C$4:$C$725,"Retail",Benchmarking!$G$4:$G$725) -> 918.57692 | G37: {=MAX(IF(Benchmarking!$C$4:$C$725="Retail",Benchmarking!$G$4:$G$725))} -> 1433 | H37: {=MIN(IF(Benchmarking!$C$4:$C$725="Retail",Benchmarking!$G$4:$G$725))} -> 618 | I37: =IF(B37>=20,"Large sample",IF(B37>=10,"Medium sample","Small sample")) -> Large sample | J37: =F37+(1000-ROW())/1000000 -> 918.57789
A38: Road & Rail | B38: =COUNTIF(Benchmarking!$C$4:$C$725,"Road & Rail") -> 6 | C38: =AVERAGEIF(Benchmarking!$C$4:$C$725,"Road & Rail",Benchmarking!$D$4:$D$725) -> 452.83333 | D38: =AVERAGEIF(Benchmarking!$C$4:$C$725,"Road & Rail",Benchmarking!$E$4:$E$725) -> 326.33333 | E38: =AVERAGEIF(Benchmarking!$C$4:$C$725,"Road & Rail",Benchmarking!$F$4:$F$725) -> 297.16667 | F38: =AVERAGEIF(Benchmarking!$C$4:$C$725,"Road & Rail",Benchmarking!$G$4:$G$725) -> 1076.3333 | G38: {=MAX(IF(Benchmarking!$C$4:$C$725="Road & Rail",Benchmarking!$G$4:$G$725))} -> 1178 | H38: {=MIN(IF(Benchmarking!$C$4:$C$725="Road & Rail",Benchmarking!$G$4:$G$725))} -> 792 | I38: =IF(B38>=20,"Large sample",IF(B38>=10,"Medium sample","Small sample")) -> Small sample | J38: =F38+(1000-ROW())/1000000 -> 1076.3343
A39: Semiconductors | B39: =COUNTIF(Benchmarking!$C$4:$C$725,"Semiconductors") -> 24 | C39: =AVERAGEIF(Benchmarking!$C$4:$C$725,"Semiconductors",Benchmarking!$D$4:$D$725) -> 448.45833 | D39: =AVERAGEIF(Benchmarking!$C$4:$C$725,"Semiconductors",Benchmarking!$E$4:$E$725) -> 296.70833 | E39: =AVERAGEIF(Benchmarking!$C$4:$C$725,"Semiconductors",Benchmarking!$F$4:$F$725) -> 285.41667 | F39: =AVERAGEIF(Benchmarking!$C$4:$C$725,"Semiconductors",Benchmarking!$G$4:$G$725) -> 1030.5833 | G39: {=MAX(IF(Benchmarking!$C$4:$C$725="Semiconductors",Benchmarking!$G$4:$G$725))} -> 1195 | H39: {=MIN(IF(Benchmarking!$C$4:$C$725="Semiconductors",Benchmarking!$G$4:$G$725))} -> 608 | I39: =IF(B39>=20,"Large sample",IF(B39>=10,"Medium sample","Small sample")) -> Large sample | J39: =F39+(1000-ROW())/1000000 -> 1030.5843
A40: Technology | B40: =COUNTIF(Benchmarking!$C$4:$C$725,"Technology") -> 63 | C40: =AVERAGEIF(Benchmarking!$C$4:$C$725,"Technology",Benchmarking!$D$4:$D$725) -> 438.11111 | D40: =AVERAGEIF(Benchmarking!$C$4:$C$725,"Technology",Benchmarking!$E$4:$E$725) -> 307.90476 | E40: =AVERAGEIF(Benchmarking!$C$4:$C$725,"Technology",Benchmarking!$F$4:$F$725) -> 285.30159 | F40: =AVERAGEIF(Benchmarking!$C$4:$C$725,"Technology",Benchmarking!$G$4:$G$725) -> 1031.3175 | G40: {=MAX(IF(Benchmarking!$C$4:$C$725="Technology",Benchmarking!$G$4:$G$725))} -> 1533 | H40: {=MIN(IF(Benchmarking!$C$4:$C$725="Technology",Benchmarking!$G$4:$G$725))} -> 621 | I40: =IF(B40>=20,"Large sample",IF(B40>=10,"Medium sample","Small sample")) -> Large sample | J40: =F40+(1000-ROW())/1000000 -> 1031.3184
A41: Telecommunication | B41: =COUNTIF(Benchmarking!$C$4:$C$725,"Telecommunication") -> 3 | C41: =AVERAGEIF(Benchmarking!$C$4:$C$725,"Telecommunication",Benchmarking!$D$4:$D$725) -> 362.33333 | D41: =AVERAGEIF(Benchmarking!$C$4:$C$725,"Telecommunication",Benchmarking!$E$4:$E$725) -> 286 | E41: =AVERAGEIF(Benchmarking!$C$4:$C$725,"Telecommunication",Benchmarking!$F$4:$F$725) -> 280 | F41: =AVERAGEIF(Benchmarking!$C$4:$C$725,"Telecommunication",Benchmarking!$G$4:$G$725) -> 928.33333 | G41: {=MAX(IF(Benchmarking!$C$4:$C$725="Telecommunication",Benchmarking!$G$4:$G$725))} -> 1167 | H41: {=MIN(IF(Benchmarking!$C$4:$C$725="Telecommunication",Benchmarking!$G$4:$G$725))} -> 715 | I41: =IF(B41>=20,"Large sample",IF(B41>=10,"Medium sample","Small sample")) -> Small sample | J41: =F41+(1000-ROW())/1000000 -> 928.33429
A42: Textiles Apparel & Luxury Goods | B42: =COUNTIF(Benchmarking!$C$4:$C$725,"Textiles Apparel & Luxury Goods") -> 9 | C42: =AVERAGEIF(Benchmarking!$C$4:$C$725,"Textiles Apparel & Luxury Goods",Benchmarking!$D$4:$D$725) -> 382.11111 | D42: =AVERAGEIF(Benchmarking!$C$4:$C$725,"Textiles Apparel & Luxury Goods",Benchmarking!$E$4:$E$725) -> 280 | E42: =AVERAGEIF(Benchmarking!$C$4:$C$725,"Textiles Apparel & Luxury Goods",Benchmarking!$F$4:$F$725) -> 282.33333 | F42: =AVERAGEIF(Benchmarking!$C$4:$C$725,"Textiles Apparel & Luxury Goods",Benchmarking!$G$4:$G$725) -> 944.44444 | G42: {=MAX(IF(Benchmarking!$C$4:$C$725="Textiles Apparel & Luxury Goods",Benchmarking!$G$4:$G$725))} -> 1106 | H42: {=MIN(IF(Benchmarking!$C$4:$C$725="Textiles Apparel & Luxury Goods",Benchmarking!$G$4:$G$725))} -> 621 | I42: =IF(B42>=20,"Large sample",IF(B42>=10,"Medium sample","Small sample")) -> Small sample | J42: =F42+(1000-ROW())/1000000 -> 944.4454
A43: Tobacco | B43: =COUNTIF(Benchmarking!$C$4:$C$725,"Tobacco") -> 2 | C43: =AVERAGEIF(Benchmarking!$C$4:$C$725,"Tobacco",Benchmarking!$D$4:$D$725) -> 510 | D43: =AVERAGEIF(Benchmarking!$C$4:$C$725,"Tobacco",Benchmarking!$E$4:$E$725) -> 327 | E43: =AVERAGEIF(Benchmarking!$C$4:$C$725,"Tobacco",Benchmarking!$F$4:$F$725) -> 328 | F43: =AVERAGEIF(Benchmarking!$C$4:$C$725,"Tobacco",Benchmarking!$G$4:$G$725) -> 1165 | G43: {=MAX(IF(Benchmarking!$C$4:$C$725="Tobacco",Benchmarking!$G$4:$G$725))} -> 1168 | H43: {=MIN(IF(Benchmarking!$C$4:$C$725="Tobacco",Benchmarking!$G$4:$G$725))} -> 1162 | I43: =IF(B43>=20,"Large sample",IF(B43>=10,"Medium sample","Small sample")) -> Small sample | J43: =F43+(1000-ROW())/1000000 -> 1165.001
A44: Trading Companies & Distributors | B44: =COUNTIF(Benchmarking!$C$4:$C$725,"Trading Companies & Distributors") -> 5 | C44: =AVERAGEIF(Benchmarking!$C$4:$C$725,"Trading Companies & Distributors",Benchmarking!$D$4:$D$725) -> 332.8 | D44: =AVERAGEIF(Benchmarking!$C$4:$C$725,"Trading Companies & Distributors",Benchmarking!$E$4:$E$725) -> 302.4 | E44: =AVERAGEIF(Benchmarking!$C$4:$C$725,"Trading Companies & Distributors",Benchmarking!$F$4:$F$725) -> 250 | F44: =AVERAGEIF(Benchmarking!$C$4:$C$725,"Trading Companies & Distributors",Benchmarking!$G$4:$G$725) -> 885.2 | G44: {=MAX(IF(Benchmarking!$C$4:$C$725="Trading Companies & Distributors",Benchmarking!$G$4:$G$725))} -> 1090 | H44: {=MIN(IF(Benchmarking!$C$4:$C$725="Trading Companies & Distributors",Benchmarking!$G$4:$G$725))} -> 641 | I44: =IF(B44>=20,"Large sample",IF(B44>=10,"Medium sample","Small sample")) -> Small sample | J44: =F44+(1000-ROW())/1000000 -> 885.20096
A45: Utilities | B45: =COUNTIF(Benchmarking!$C$4:$C$725,"Utilities") -> 30 | C45: =AVERAGEIF(Benchmarking!$C$4:$C$725,"Utilities",Benchmarking!$D$4:$D$725) -> 550.96667 | D45: =AVERAGEIF(Benchmarking!$C$4:$C$725,"Utilities",Benchmarking!$E$4:$E$725) -> 357.4 | E45: =AVERAGEIF(Benchmarking!$C$4:$C$725,"Utilities",Benchmarking!$F$4:$F$725) -> 282.26667 | F45: =AVERAGEIF(Benchmarking!$C$4:$C$725,"Utilities",Benchmarking!$G$4:$G$725) -> 1190.6333 | G45: {=MAX(IF(Benchmarking!$C$4:$C$725="Utilities",Benchmarking!$G$4:$G$725))} -> 1528 | H45: {=MIN(IF(Benchmarking!$C$4:$C$725="Utilities",Benchmarking!$G$4:$G$725))} -> 629 | I45: =IF(B45>=20,"Large sample",IF(B45>=10,"Medium sample","Small sample")) -> Large sample | J45: =F45+(1000-ROW())/1000000 -> 1190.6343
A46: Unclassified | B46: =COUNTIF(Benchmarking!$C$4:$C$725,"Unclassified") -> 13 | C46: =AVERAGEIF(Benchmarking!$C$4:$C$725,"Unclassified",Benchmarking!$D$4:$D$725) -> 215.38462 | D46: =AVERAGEIF(Benchmarking!$C$4:$C$725,"Unclassified",Benchmarking!$E$4:$E$725) -> 231.15385 | E46: =AVERAGEIF(Benchmarking!$C$4:$C$725,"Unclassified",Benchmarking!$F$4:$F$725) -> 262.76923 | F46: =AVERAGEIF(Benchmarking!$C$4:$C$725,"Unclassified",Benchmarking!$G$4:$G$725) -> 709.30769 | G46: {=MAX(IF(Benchmarking!$C$4:$C$725="Unclassified",Benchmarking!$G$4:$G$725))} -> 816 | H46: {=MIN(IF(Benchmarking!$C$4:$C$725="Unclassified",Benchmarking!$G$4:$G$725))} -> 600 | I46: =IF(B46>=20,"Large sample",IF(B46>=10,"Medium sample","Small sample")) -> Medium sample | J46: =F46+(1000-ROW())/1000000 -> 709.30865
